Workbook

Sheet 首页+选择功能
B1: 省份按月电价查询
A2: 省份 | B2: 江苏
A3: 月份 | B3: 年均
A4: 电压等级 | B4: 两部制220kV
A5: 综合平段电价 | B5: {=_xlfn.XLOOKUP($B$3,$C$6:$O$6,$C$12:$O$12)}
A6: 序号 | B6: 2026年电价表 | C6: 46023 | D6: 46054 | E6: 46082 | F6: 46113 | G6: 46143 | H6: 46174 | I6: 46204 | J6: 46235 | K6: 46266 | L6: 46296 | M6: 46327 | N6: 46357 | O6: 年均 | P6: 趋势图
A7: 1 | B7: 代理购电价格 | C7: {=_xlfn.XLOOKUP($B$2&$B7,'总表-2026'!$B$3:'总表-2026'!$B$253&'总表-2026'!$C$3:'总表-2026'!$C$253,'总表-2026'!D$3:'总表-2026'!D$253)} | D7: {=_xlfn.XLOOKUP($B$2&$B7,'总表-2026'!$B$3:'总表-2026'!$B$253&'总表-2026'!$C$3:'总表-2026'!$C$253,'总表-2026'!E$3:'总表-2026'!E$253)} | E7: {=_xlfn.XLOOKUP($B$2&$B7,'总表-2026'!$B$3:'总表-2026'!$B$253&'总表-2026'!$C$3:'总表-2026'!$C$253,'总表-2026'!F$3:'总表-2026'!F$253)} | F7: {=_xlfn.XLOOKUP($B$2&$B7,'总表-2026'!$B$3:'总表-2026'!$B$253&'总表-2026'!$C$3:'总表-2026'!$C$253,'总表-2026'!G$3:'总表-2026'!G$253)} | G7: {=_xlfn.XLOOKUP($B$2&$B7,'总表-2026'!$B$3:'总表-2026'!$B$253&'总表-2026'!$C$3:'总表-2026'!$C$253,'总表-2026'!H$3:'总表-2026'!H$253)} | H7: {=_xlfn.XLOOKUP($B$2&$B7,'总表-2026'!$B$3:'总表-2026'!$B$253&'总表-2026'!$C$3:'总表-2026'!$C$253,'总表-2026'!I$3:'总表-2026'!I$253)} | I7: {=_xlfn.XLOOKUP($B$2&$B7,'总表-2026'!$B$3:'总表-2026'!$B$253&'总表-2026'!$C$3:'总表-2026'!$C$253,'总表-2026'!J$3:'总表-2026'!J$253)} | J7: {=_xlfn.XLOOKUP($B$2&$B7,'总表-2026'!$B$3:'总表-2026'!$B$253&'总表-2026'!$C$3:'总表-2026'!$C$253,'总表-2026'!K$3:'总表-2026'!K$253)} | ... O7: {=_xlfn.XLOOKUP($B$2&$B7,'总表-2026'!$B$3:'总表-2026'!$B$253&'总表-2026'!$C$3:'总表-2026'!$C$253,'总表-2026'!P$3:'总表-2026'!P$253)}
A8: 2 | B8: 上网环节线损电价 | C8: {=_xlfn.XLOOKUP($B$2&$B8,'总表-2026'!$B$3:'总表-2026'!$B$253&'总表-2026'!$C$3:'总表-2026'!$C$253,'总表-2026'!D$3:'总表-2026'!D$253)} | D8: {=_xlfn.XLOOKUP($B$2&$B8,'总表-2026'!$B$3:'总表-2026'!$B$253&'总表-2026'!$C$3:'总表-2026'!$C$253,'总表-2026'!E$3:'总表-2026'!E$253)} | E8: {=_xlfn.XLOOKUP($B$2&$B8,'总表-2026'!$B$3:'总表-2026'!$B$253&'总表-2026'!$C$3:'总表-2026'!$C$253,'总表-2026'!F$3:'总表-2026'!F$253)} | F8: {=_xlfn.XLOOKUP($B$2&$B8,'总表-2026'!$B$3:'总表-2026'!$B$253&'总表-2026'!$C$3:'总表-2026'!$C$253,'总表-2026'!G$3:'总表-2026'!G$253)} | G8: {=_xlfn.XLOOKUP($B$2&$B8,'总表-2026'!$B$3:'总表-2026'!$B$253&'总表-2026'!$C$3:'总表-2026'!$C$253,'总表-2026'!H$3:'总表-2026'!H$253)} | H8: {=_xlfn.XLOOKUP($B$2&$B8,'总表-2026'!$B$3:'总表-2026'!$B$253&'总表-2026'!$C$3:'总表-2026'!$C$253,'总表-2026'!I$3:'总表-2026'!I$253)} | I8: {=_xlfn.XLOOKUP($B$2&$B8,'总表-2026'!$B$3:'总表-2026'!$B$253&'总表-2026'!$C$3:'总表-2026'!$C$253,'总表-2026'!J$3:'总表-2026'!J$253)} | J8: {=_xlfn.XLOOKUP($B$2&$B8,'总表-2026'!$B$3:'总表-2026'!$B$253&'总表-2026'!$C$3:'总表-2026'!$C$253,'总表-2026'!K$3:'总表-2026'!K$253)} | ... O8: {=_xlfn.XLOOKUP($B$2&$B8,'总表-2026'!$B$3:'总表-2026'!$B$253&'总表-2026'!$C$3:'总表-2026'!$C$253,'总表-2026'!P$3:'总表-2026'!P$253)}
A9: 3 | B9: 电度输配电价 | C9: {=_xlfn.XLOOKUP($B$2&$B9,'总表-2026'!$B$3:'总表-2026'!$B$253&'总表-2026'!$C$3:'总表-2026'!$C$253,'总表-2026'!D$3:'总表-2026'!D$253)} | D9: {=_xlfn.XLOOKUP($B$2&$B9,'总表-2026'!$B$3:'总表-2026'!$B$253&'总表-2026'!$C$3:'总表-2026'!$C$253,'总表-2026'!E$3:'总表-2026'!E$253)} | E9: {=_xlfn.XLOOKUP($B$2&$B9,'总表-2026'!$B$3:'总表-2026'!$B$253&'总表-2026'!$C$3:'总表-2026'!$C$253,'总表-2026'!F$3:'总表-2026'!F$253)} | F9: {=_xlfn.XLOOKUP($B$2&$B9,'总表-2026'!$B$3:'总表-2026'!$B$253&'总表-2026'!$C$3:'总表-2026'!$C$253,'总表-2026'!G$3:'总表-2026'!G$253)} | G9: {=_xlfn.XLOOKUP($B$2&$B9,'总表-2026'!$B$3:'总表-2026'!$B$253&'总表-2026'!$C$3:'总表-2026'!$C$253,'总表-2026'!H$3:'总表-2026'!H$253)} | H9: {=_xlfn.XLOOKUP($B$2&$B9,'总表-2026'!$B$3:'总表-2026'!$B$253&'总表-2026'!$C$3:'总表-2026'!$C$253,'总表-2026'!I$3:'总表-2026'!I$253)} | I9: {=_xlfn.XLOOKUP($B$2&$B9,'总表-2026'!$B$3:'总表-2026'!$B$253&'总表-2026'!$C$3:'总表-2026'!$C$253,'总表-2026'!J$3:'总表-2026'!J$253)} | J9: {=_xlfn.XLOOKUP($B$2&$B9,'总表-2026'!$B$3:'总表-2026'!$B$253&'总表-2026'!$C$3:'总表-2026'!$C$253,'总表-2026'!K$3:'总表-2026'!K$253)} | ... O9: {=_xlfn.XLOOKUP($B$2&$B9,'总表-2026'!$B$3:'总表-2026'!$B$253&'总表-2026'!$C$3:'总表-2026'!$C$253,'总表-2026'!P$3:'总表-2026'!P$253)}
A10: 4 | B10: 政府性基金及附加 | C10: {=_xlfn.XLOOKUP($B$2&$B10,'总表-2026'!$B$3:'总表-2026'!$B$253&'总表-2026'!$C$3:'总表-2026'!$C$253,'总表-2026'!D$3:'总表-2026'!D$253)} | D10: {=_xlfn.XLOOKUP($B$2&$B10,'总表-2026'!$B$3:'总表-2026'!$B$253&'总表-2026'!$C$3:'总表-2026'!$C$253,'总表-2026'!E$3:'总表-2026'!E$253)} | E10: {=_xlfn.XLOOKUP($B$2&$B10,'总表-2026'!$B$3:'总表-2026'!$B$253&'总表-2026'!$C$3:'总表-2026'!$C$253,'总表-2026'!F$3:'总表-2026'!F$253)} | F10: {=_xlfn.XLOOKUP($B$2&$B10,'总表-2026'!$B$3:'总表-2026'!$B$253&'总表-2026'!$C$3:'总表-2026'!$C$253,'总表-2026'!G$3:'总表-2026'!G$253)} | G10: {=_xlfn.XLOOKUP($B$2&$B10,'总表-2026'!$B$3:'总表-2026'!$B$253&'总表-2026'!$C$3:'总表-2026'!$C$253,'总表-2026'!H$3:'总表-2026'!H$253)} | H10: {=_xlfn.XLOOKUP($B$2&$B10,'总表-2026'!$B$3:'总表-2026'!$B$253&'总表-2026'!$C$3:'总表-2026'!$C$253,'总表-2026'!I$3:'总表-2026'!I$253)} | I10: {=_xlfn.XLOOKUP($B$2&$B10,'总表-2026'!$B$3:'总表-2026'!$B$253&'总表-2026'!$C$3:'总表-2026'!$C$253,'总表-2026'!J$3:'总表-2026'!J$253)} | J10: {=_xlfn.XLOOKUP($B$2&$B10,'总表-2026'!$B$3:'总表-2026'!$B$253&'总表-2026'!$C$3:'总表-2026'!$C$253,'总表-2026'!K$3:'总表-2026'!K$253)} | ... O10: {=_xlfn.XLOOKUP($B$2&$B10,'总表-2026'!$B$3:'总表-2026'!$B$253&'总表-2026'!$C$3:'总表-2026'!$C$253,'总表-2026'!P$3:'总表-2026'!P$253)}
A11: 5 | B11: 系统运行费折价 | C11: {=_xlfn.XLOOKUP($B$2&$B11,'总表-2026'!$B$3:'总表-2026'!$B$253&'总表-2026'!$C$3:'总表-2026'!$C$253,'总表-2026'!D$3:'总表-2026'!D$253)} | D11: {=_xlfn.XLOOKUP($B$2&$B11,'总表-2026'!$B$3:'总表-2026'!$B$253&'总表-2026'!$C$3:'总表-2026'!$C$253,'总表-2026'!E$3:'总表-2026'!E$253)} | E11: {=_xlfn.XLOOKUP($B$2&$B11,'总表-2026'!$B$3:'总表-2026'!$B$253&'总表-2026'!$C$3:'总表-2026'!$C$253,'总表-2026'!F$3:'总表-2026'!F$253)} | F11: {=_xlfn.XLOOKUP($B$2&$B11,'总表-2026'!$B$3:'总表-2026'!$B$253&'总表-2026'!$C$3:'总表-2026'!$C$253,'总表-2026'!G$3:'总表-2026'!G$253)} | G11: {=_xlfn.XLOOKUP($B$2&$B11,'总表-2026'!$B$3:'总表-2026'!$B$253&'总表-2026'!$C$3:'总表-2026'!$C$253,'总表-2026'!H$3:'总表-2026'!H$253)} | H11: {=_xlfn.XLOOKUP($B$2&$B11,'总表-2026'!$B$3:'总表-2026'!$B$253&'总表-2026'!$C$3:'总表-2026'!$C$253,'总表-2026'!I$3:'总表-2026'!I$253)} | I11: {=_xlfn.XLOOKUP($B$2&$B11,'总表-2026'!$B$3:'总表-2026'!$B$253&'总表-2026'!$C$3:'总表-2026'!$C$253,'总表-2026'!J$3:'总表-2026'!J$253)} | J11: {=_xlfn.XLOOKUP($B$2&$B11,'总表-2026'!$B$3:'总表-2026'!$B$253&'总表-2026'!$C$3:'总表-2026'!$C$253,'总表-2026'!K$3:'总表-2026'!K$253)} | ... O11: {=_xlfn.XLOOKUP($B$2&$B11,'总表-2026'!$B$3:'总表-2026'!$B$253&'总表-2026'!$C$3:'总表-2026'!$C$253,'总表-2026'!P$3:'总表-2026'!P$253)}
A12: 6 | B12: 综合平段电价--电网代购 | C12: {=_xlfn.XLOOKUP($B$2&$B12,'总表-2026'!$B$3:'总表-2026'!$B$253&'总表-2026'!$C$3:'总表-2026'!$C$253,'总表-2026'!D$3:'总表-2026'!D$253)} | D12: {=_xlfn.XLOOKUP($B$2&$B12,'总表-2026'!$B$3:'总表-2026'!$B$253&'总表-2026'!$C$3:'总表-2026'!$C$253,'总表-2026'!E$3:'总表-2026'!E$253)} | E12: {=_xlfn.XLOOKUP($B$2&$B12,'总表-2026'!$B$3:'总表-2026'!$B$253&'总表-2026'!$C$3:'总表-2026'!$C$253,'总表-2026'!F$3:'总表-2026'!F$253)} | F12: {=_xlfn.XLOOKUP($B$2&$B12,'总表-2026'!$B$3:'总表-2026'!$B$253&'总表-2026'!$C$3:'总表-2026'!$C$253,'总表-2026'!G$3:'总表-2026'!G$253)} | G12: {=_xlfn.XLOOKUP($B$2&$B12,'总表-2026'!$B$3:'总表-2026'!$B$253&'总表-2026'!$C$3:'总表-2026'!$C$253,'总表-2026'!H$3:'总表-2026'!H$253)} | H12: {=_xlfn.XLOOKUP($B$2&$B12,'总表-2026'!$B$3:'总表-2026'!$B$253&'总表-2026'!$C$3:'总表-2026'!$C$253,'总表-2026'!I$3:'总表-2026'!I$253)} | I12: {=_xlfn.XLOOKUP($B$2&$B12,'总表-2026'!$B$3:'总表-2026'!$B$253&'总表-2026'!$C$3:'总表-2026'!$C$253,'总表-2026'!J$3:'总表-2026'!J$253)} | J12: {=_xlfn.XLOOKUP($B$2&$B12,'总表-2026'!$B$3:'总表-2026'!$B$253&'总表-2026'!$C$3:'总表-2026'!$C$253,'总表-2026'!K$3:'总表-2026'!K$253)} | ... O12: {=_xlfn.XLOOKUP($B$2&$B12,'总表-2026'!$B$3:'总表-2026'!$B$253&'总表-2026'!$C$3:'总表-2026'!$C$253,'总表-2026'!P$3:'总表-2026'!P$253)}
A13: 7 | B13: 入市交易购电价格 | C13: {=_xlfn.XLOOKUP($B$2&$B13,'总表-2026'!$B$3:'总表-2026'!$B$253&'总表-2026'!$C$3:'总表-2026'!$C$253,'总表-2026'!D$3:'总表-2026'!D$253)} | D13: {=_xlfn.XLOOKUP($B$2&$B13,'总表-2026'!$B$3:'总表-2026'!$B$253&'总表-2026'!$C$3:'总表-2026'!$C$253,'总表-2026'!E$3:'总表-2026'!E$253)} | E13: {=_xlfn.XLOOKUP($B$2&$B13,'总表-2026'!$B$3:'总表-2026'!$B$253&'总表-2026'!$C$3:'总表-2026'!$C$253,'总表-2026'!F$3:'总表-2026'!F$253)} | F13: {=_xlfn.XLOOKUP($B$2&$B13,'总表-2026'!$B$3:'总表-2026'!$B$253&'总表-2026'!$C$3:'总表-2026'!$C$253,'总表-2026'!G$3:'总表-2026'!G$253)} | G13: {=_xlfn.XLOOKUP($B$2&$B13,'总表-2026'!$B$3:'总表-2026'!$B$253&'总表-2026'!$C$3:'总表-2026'!$C$253,'总表-2026'!H$3:'总表-2026'!H$253)} | H13: {=_xlfn.XLOOKUP($B$2&$B13,'总表-2026'!$B$3:'总表-2026'!$B$253&'总表-2026'!$C$3:'总表-2026'!$C$253,'总表-2026'!I$3:'总表-2026'!I$253)} | I13: {=_xlfn.XLOOKUP($B$2&$B13,'总表-2026'!$B$3:'总表-2026'!$B$253&'总表-2026'!$C$3:'总表-2026'!$C$253,'总表-2026'!J$3:'总表-2026'!J$253)} | J13: {=_xlfn.XLOOKUP($B$2&$B13,'总表-2026'!$B$3:'总表-2026'!$B$253&'总表-2026'!$C$3:'总表-2026'!$C$253,'总表-2026'!K$3:'总表-2026'!K$253)} | ... O13: {=_xlfn.XLOOKUP($B$2&$B13,'总表-2026'!$B$3:'总表-2026'!$B$253&'总表-2026'!$C$3:'总表-2026'!$C$253,'总表-2026'!P$3:'总表-2026'!P$253)}
A14: 8 | B14: 综合平段电价--入市交易 | C14: {=_xlfn.XLOOKUP($B$2&$B14,'总表-2026'!$B$3:'总表-2026'!$B$253&'总表-2026'!$C$3:'总表-2026'!$C$253,'总表-2026'!D$3:'总表-2026'!D$253)} | D14: {=_xlfn.XLOOKUP($B$2&$B14,'总表-2026'!$B$3:'总表-2026'!$B$253&'总表-2026'!$C$3:'总表-2026'!$C$253,'总表-2026'!E$3:'总表-2026'!E$253)} | E14: {=_xlfn.XLOOKUP($B$2&$B14,'总表-2026'!$B$3:'总表-2026'!$B$253&'总表-2026'!$C$3:'总表-2026'!$C$253,'总表-2026'!F$3:'总表-2026'!F$253)} | F14: {=_xlfn.XLOOKUP($B$2&$B14,'总表-2026'!$B$3:'总表-2026'!$B$253&'总表-2026'!$C$3:'总表-2026'!$C$253,'总表-2026'!G$3:'总表-2026'!G$253)} | G14: {=_xlfn.XLOOKUP($B$2&$B14,'总表-2026'!$B$3:'总表-2026'!$B$253&'总表-2026'!$C$3:'总表-2026'!$C$253,'总表-2026'!H$3:'总表-2026'!H$253)} | H14: {=_xlfn.XLOOKUP($B$2&$B14,'总表-2026'!$B$3:'总表-2026'!$B$253&'总表-2026'!$C$3:'总表-2026'!$C$253,'总表-2026'!I$3:'总表-2026'!I$253)} | I14: {=_xlfn.XLOOKUP($B$2&$B14,'总表-2026'!$B$3:'总表-2026'!$B$253&'总表-2026'!$C$3:'总表-2026'!$C$253,'总表-2026'!J$3:'总表-2026'!J$253)} | J14: {=_xlfn.XLOOKUP($B$2&$B14,'总表-2026'!$B$3:'总表-2026'!$B$253&'总表-2026'!$C$3:'总表-2026'!$C$253,'总表-2026'!K$3:'总表-2026'!K$253)} | ... O14: {=_xlfn.XLOOKUP($B$2&$B14,'总表-2026'!$B$3:'总表-2026'!$B$253&'总表-2026'!$C$3:'总表-2026'!$C$253,'总表-2026'!P$3:'总表-2026'!P$253)}
A34: 序号 | B34: 2025年电价表 | C34: 45658 | D34: 45689 | E34: 45717 | F34: 45748 | G34: 45778 | H34: 45809 | I34: 45839 | J34: 45870 | K34: 45901 | L34: 45931 | M34: 45962 | N34: 45992 | O34: 年均 | P34: 趋势图
A35: 1 | B35: 代理购电价格 | C35: {=_xlfn.XLOOKUP($B$2&$B35,'总表-2025'!$B$3:'总表-2025'!$B$253&'总表-2025'!$C$3:'总表-2025'!$C$253,'总表-2025'!D$3:'总表-2025'!D$253)} | D35: {=_xlfn.XLOOKUP($B$2&$B35,'总表-2025'!$B$3:'总表-2025'!$B$253&'总表-2025'!$C$3:'总表-2025'!$C$253,'总表-2025'!E$3:'总表-2025'!E$253)} | E35: {=_xlfn.XLOOKUP($B$2&$B35,'总表-2025'!$B$3:'总表-2025'!$B$253&'总表-2025'!$C$3:'总表-2025'!$C$253,'总表-2025'!F$3:'总表-2025'!F$253)} | F35: {=_xlfn.XLOOKUP($B$2&$B35,'总表-2025'!$B$3:'总表-2025'!$B$253&'总表-2025'!$C$3:'总表-2025'!$C$253,'总表-2025'!G$3:'总表-2025'!G$253)} | G35: {=_xlfn.XLOOKUP($B$2&$B35,'总表-2025'!$B$3:'总表-2025'!$B$253&'总表-2025'!$C$3:'总表-2025'!$C$253,'总表-2025'!H$3:'总表-2025'!H$253)} | H35: {=_xlfn.XLOOKUP($B$2&$B35,'总表-2025'!$B$3:'总表-2025'!$B$253&'总表-2025'!$C$3:'总表-2025'!$C$253,'总表-2025'!I$3:'总表-2025'!I$253)} | I35: {=_xlfn.XLOOKUP($B$2&$B35,'总表-2025'!$B$3:'总表-2025'!$B$253&'总表-2025'!$C$3:'总表-2025'!$C$253,'总表-2025'!J$3:'总表-2025'!J$253)} | J35: {=_xlfn.XLOOKUP($B$2&$B35,'总表-2025'!$B$3:'总表-2025'!$B$253&'总表-2025'!$C$3:'总表-2025'!$C$253,'总表-2025'!K$3:'总表-2025'!K$253)} | ... O35: {=_xlfn.XLOOKUP($B$2&$B35,'总表-2025'!$B$3:'总表-2025'!$B$253&'总表-2025'!$C$3:'总表-2025'!$C$253,'总表-2025'!P$3:'总表-2025'!P$253)}
A36: 2 | B36: 上网环节线损电价 | C36: {=_xlfn.XLOOKUP($B$2&$B36,'总表-2025'!$B$3:'总表-2025'!$B$253&'总表-2025'!$C$3:'总表-2025'!$C$253,'总表-2025'!D$3:'总表-2025'!D$253)} | D36: {=_xlfn.XLOOKUP($B$2&$B36,'总表-2025'!$B$3:'总表-2025'!$B$253&'总表-2025'!$C$3:'总表-2025'!$C$253,'总表-2025'!E$3:'总表-2025'!E$253)} | E36: {=_xlfn.XLOOKUP($B$2&$B36,'总表-2025'!$B$3:'总表-2025'!$B$253&'总表-2025'!$C$3:'总表-2025'!$C$253,'总表-2025'!F$3:'总表-2025'!F$253)} | F36: {=_xlfn.XLOOKUP($B$2&$B36,'总表-2025'!$B$3:'总表-2025'!$B$253&'总表-2025'!$C$3:'总表-2025'!$C$253,'总表-2025'!G$3:'总表-2025'!G$253)} | G36: {=_xlfn.XLOOKUP($B$2&$B36,'总表-2025'!$B$3:'总表-2025'!$B$253&'总表-2025'!$C$3:'总表-2025'!$C$253,'总表-2025'!H$3:'总表-2025'!H$253)} | H36: {=_xlfn.XLOOKUP($B$2&$B36,'总表-2025'!$B$3:'总表-2025'!$B$253&'总表-2025'!$C$3:'总表-2025'!$C$253,'总表-2025'!I$3:'总表-2025'!I$253)} | I36: {=_xlfn.XLOOKUP($B$2&$B36,'总表-2025'!$B$3:'总表-2025'!$B$253&'总表-2025'!$C$3:'总表-2025'!$C$253,'总表-2025'!J$3:'总表-2025'!J$253)} | J36: {=_xlfn.XLOOKUP($B$2&$B36,'总表-2025'!$B$3:'总表-2025'!$B$253&'总表-2025'!$C$3:'总表-2025'!$C$253,'总表-2025'!K$3:'总表-2025'!K$253)} | ... O36: {=_xlfn.XLOOKUP($B$2&$B36,'总表-2025'!$B$3:'总表-2025'!$B$253&'总表-2025'!$C$3:'总表-2025'!$C$253,'总表-2025'!P$3:'总表-2025'!P$253)}
A37: 3 | B37: 电度输配电价 | C37: {=_xlfn.XLOOKUP($B$2&$B37,'总表-2025'!$B$3:'总表-2025'!$B$253&'总表-2025'!$C$3:'总表-2025'!$C$253,'总表-2025'!D$3:'总表-2025'!D$253)} | D37: {=_xlfn.XLOOKUP($B$2&$B37,'总表-2025'!$B$3:'总表-2025'!$B$253&'总表-2025'!$C$3:'总表-2025'!$C$253,'总表-2025'!E$3:'总表-2025'!E$253)} | E37: {=_xlfn.XLOOKUP($B$2&$B37,'总表-2025'!$B$3:'总表-2025'!$B$253&'总表-2025'!$C$3:'总表-2025'!$C$253,'总表-2025'!F$3:'总表-2025'!F$253)} | F37: {=_xlfn.XLOOKUP($B$2&$B37,'总表-2025'!$B$3:'总表-2025'!$B$253&'总表-2025'!$C$3:'总表-2025'!$C$253,'总表-2025'!G$3:'总表-2025'!G$253)} | G37: {=_xlfn.XLOOKUP($B$2&$B37,'总表-2025'!$B$3:'总表-2025'!$B$253&'总表-2025'!$C$3:'总表-2025'!$C$253,'总表-2025'!H$3:'总表-2025'!H$253)} | H37: {=_xlfn.XLOOKUP($B$2&$B37,'总表-2025'!$B$3:'总表-2025'!$B$253&'总表-2025'!$C$3:'总表-2025'!$C$253,'总表-2025'!I$3:'总表-2025'!I$253)} | I37: {=_xlfn.XLOOKUP($B$2&$B37,'总表-2025'!$B$3:'总表-2025'!$B$253&'总表-2025'!$C$3:'总表-2025'!$C$253,'总表-2025'!J$3:'总表-2025'!J$253)} | J37: {=_xlfn.XLOOKUP($B$2&$B37,'总表-2025'!$B$3:'总表-2025'!$B$253&'总表-2025'!$C$3:'总表-2025'!$C$253,'总表-2025'!K$3:'总表-2025'!K$253)} | ... O37: {=_xlfn.XLOOKUP($B$2&$B37,'总表-2025'!$B$3:'总表-2025'!$B$253&'总表-2025'!$C$3:'总表-2025'!$C$253,'总表-2025'!P$3:'总表-2025'!P$253)}
A38: 4 | B38: 政府性基金及附加 | C38: {=_xlfn.XLOOKUP($B$2&$B38,'总表-2025'!$B$3:'总表-2025'!$B$253&'总表-2025'!$C$3:'总表-2025'!$C$253,'总表-2025'!D$3:'总表-2025'!D$253)} | D38: {=_xlfn.XLOOKUP($B$2&$B38,'总表-2025'!$B$3:'总表-2025'!$B$253&'总表-2025'!$C$3:'总表-2025'!$C$253,'总表-2025'!E$3:'总表-2025'!E$253)} | E38: {=_xlfn.XLOOKUP($B$2&$B38,'总表-2025'!$B$3:'总表-2025'!$B$253&'总表-2025'!$C$3:'总表-2025'!$C$253,'总表-2025'!F$3:'总表-2025'!F$253)} | F38: {=_xlfn.XLOOKUP($B$2&$B38,'总表-2025'!$B$3:'总表-2025'!$B$253&'总表-2025'!$C$3:'总表-2025'!$C$253,'总表-2025'!G$3:'总表-2025'!G$253)} | G38: {=_xlfn.XLOOKUP($B$2&$B38,'总表-2025'!$B$3:'总表-2025'!$B$253&'总表-2025'!$C$3:'总表-2025'!$C$253,'总表-2025'!H$3:'总表-2025'!H$253)} | H38: {=_xlfn.XLOOKUP($B$2&$B38,'总表-2025'!$B$3:'总表-2025'!$B$253&'总表-2025'!$C$3:'总表-2025'!$C$253,'总表-2025'!I$3:'总表-2025'!I$253)} | I38: {=_xlfn.XLOOKUP($B$2&$B38,'总表-2025'!$B$3:'总表-2025'!$B$253&'总表-2025'!$C$3:'总表-2025'!$C$253,'总表-2025'!J$3:'总表-2025'!J$253)} | J38: {=_xlfn.XLOOKUP($B$2&$B38,'总表-2025'!$B$3:'总表-2025'!$B$253&'总表-2025'!$C$3:'总表-2025'!$C$253,'总表-2025'!K$3:'总表-2025'!K$253)} | ... O38: {=_xlfn.XLOOKUP($B$2&$B38,'总表-2025'!$B$3:'总表-2025'!$B$253&'总表-2025'!$C$3:'总表-2025'!$C$253,'总表-2025'!P$3:'总表-2025'!P$253)}
A39: 5 | B39: 系统运行费折价 | C39: {=_xlfn.XLOOKUP($B$2&$B39,'总表-2025'!$B$3:'总表-2025'!$B$253&'总表-2025'!$C$3:'总表-2025'!$C$253,'总表-2025'!D$3:'总表-2025'!D$253)} | D39: {=_xlfn.XLOOKUP($B$2&$B39,'总表-2025'!$B$3:'总表-2025'!$B$253&'总表-2025'!$C$3:'总表-2025'!$C$253,'总表-2025'!E$3:'总表-2025'!E$253)} | E39: {=_xlfn.XLOOKUP($B$2&$B39,'总表-2025'!$B$3:'总表-2025'!$B$253&'总表-2025'!$C$3:'总表-2025'!$C$253,'总表-2025'!F$3:'总表-2025'!F$253)} | F39: {=_xlfn.XLOOKUP($B$2&$B39,'总表-2025'!$B$3:'总表-2025'!$B$253&'总表-2025'!$C$3:'总表-2025'!$C$253,'总表-2025'!G$3:'总表-2025'!G$253)} | G39: {=_xlfn.XLOOKUP($B$2&$B39,'总表-2025'!$B$3:'总表-2025'!$B$253&'总表-2025'!$C$3:'总表-2025'!$C$253,'总表-2025'!H$3:'总表-2025'!H$253)} | H39: {=_xlfn.XLOOKUP($B$2&$B39,'总表-2025'!$B$3:'总表-2025'!$B$253&'总表-2025'!$C$3:'总表-2025'!$C$253,'总表-2025'!I$3:'总表-2025'!I$253)} | I39: {=_xlfn.XLOOKUP($B$2&$B39,'总表-2025'!$B$3:'总表-2025'!$B$253&'总表-2025'!$C$3:'总表-2025'!$C$253,'总表-2025'!J$3:'总表-2025'!J$253)} | J39: {=_xlfn.XLOOKUP($B$2&$B39,'总表-2025'!$B$3:'总表-2025'!$B$253&'总表-2025'!$C$3:'总表-2025'!$C$253,'总表-2025'!K$3:'总表-2025'!K$253)} | ... O39: {=_xlfn.XLOOKUP($B$2&$B39,'总表-2025'!$B$3:'总表-2025'!$B$253&'总表-2025'!$C$3:'总表-2025'!$C$253,'总表-2025'!P$3:'总表-2025'!P$253)}
A40: 6 | B40: 综合平段电价--电网代购 | C40: {=_xlfn.XLOOKUP($B$2&$B40,'总表-2025'!$B$3:'总表-2025'!$B$253&'总表-2025'!$C$3:'总表-2025'!$C$253,'总表-2025'!D$3:'总表-2025'!D$253)} | D40: {=_xlfn.XLOOKUP($B$2&$B40,'总表-2025'!$B$3:'总表-2025'!$B$253&'总表-2025'!$C$3:'总表-2025'!$C$253,'总表-2025'!E$3:'总表-2025'!E$253)} | E40: {=_xlfn.XLOOKUP($B$2&$B40,'总表-2025'!$B$3:'总表-2025'!$B$253&'总表-2025'!$C$3:'总表-2025'!$C$253,'总表-2025'!F$3:'总表-2025'!F$253)} | F40: {=_xlfn.XLOOKUP($B$2&$B40,'总表-2025'!$B$3:'总表-2025'!$B$253&'总表-2025'!$C$3:'总表-2025'!$C$253,'总表-2025'!G$3:'总表-2025'!G$253)} | G40: {=_xlfn.XLOOKUP($B$2&$B40,'总表-2025'!$B$3:'总表-2025'!$B$253&'总表-2025'!$C$3:'总表-2025'!$C$253,'总表-2025'!H$3:'总表-2025'!H$253)} | H40: {=_xlfn.XLOOKUP($B$2&$B40,'总表-2025'!$B$3:'总表-2025'!$B$253&'总表-2025'!$C$3:'总表-2025'!$C$253,'总表-2025'!I$3:'总表-2025'!I$253)} | I40: {=_xlfn.XLOOKUP($B$2&$B40,'总表-2025'!$B$3:'总表-2025'!$B$253&'总表-2025'!$C$3:'总表-2025'!$C$253,'总表-2025'!J$3:'总表-2025'!J$253)} | J40: {=_xlfn.XLOOKUP($B$2&$B40,'总表-2025'!$B$3:'总表-2025'!$B$253&'总表-2025'!$C$3:'总表-2025'!$C$253,'总表-2025'!K$3:'总表-2025'!K$253)} | ... O40: {=_xlfn.XLOOKUP($B$2&$B40,'总表-2025'!$B$3:'总表-2025'!$B$253&'总表-2025'!$C$3:'总表-2025'!$C$253,'总表-2025'!P$3:'总表-2025'!P$253)}
A41: 7 | B41: 入市交易购电价格 | C41: {=_xlfn.XLOOKUP($B$2&$B41,'总表-2025'!$B$3:'总表-2025'!$B$253&'总表-2025'!$C$3:'总表-2025'!$C$253,'总表-2025'!D$3:'总表-2025'!D$253)} | D41: {=_xlfn.XLOOKUP($B$2&$B41,'总表-2025'!$B$3:'总表-2025'!$B$253&'总表-2025'!$C$3:'总表-2025'!$C$253,'总表-2025'!E$3:'总表-2025'!E$253)} | E41: {=_xlfn.XLOOKUP($B$2&$B41,'总表-2025'!$B$3:'总表-2025'!$B$253&'总表-2025'!$C$3:'总表-2025'!$C$253,'总表-2025'!F$3:'总表-2025'!F$253)} | F41: {=_xlfn.XLOOKUP($B$2&$B41,'总表-2025'!$B$3:'总表-2025'!$B$253&'总表-2025'!$C$3:'总表-2025'!$C$253,'总表-2025'!G$3:'总表-2025'!G$253)} | G41: {=_xlfn.XLOOKUP($B$2&$B41,'总表-2025'!$B$3:'总表-2025'!$B$253&'总表-2025'!$C$3:'总表-2025'!$C$253,'总表-2025'!H$3:'总表-2025'!H$253)} | H41: {=_xlfn.XLOOKUP($B$2&$B41,'总表-2025'!$B$3:'总表-2025'!$B$253&'总表-2025'!$C$3:'总表-2025'!$C$253,'总表-2025'!I$3:'总表-2025'!I$253)} | I41: {=_xlfn.XLOOKUP($B$2&$B41,'总表-2025'!$B$3:'总表-2025'!$B$253&'总表-2025'!$C$3:'总表-2025'!$C$253,'总表-2025'!J$3:'总表-2025'!J$253)} | J41: {=_xlfn.XLOOKUP($B$2&$B41,'总表-2025'!$B$3:'总表-2025'!$B$253&'总表-2025'!$C$3:'总表-2025'!$C$253,'总表-2025'!K$3:'总表-2025'!K$253)} | ... O41: {=_xlfn.XLOOKUP($B$2&$B41,'总表-2025'!$B$3:'总表-2025'!$B$253&'总表-2025'!$C$3:'总表-2025'!$C$253,'总表-2025'!P$3:'总表-2025'!P$253)}
A42: 8 | B42: 综合平段电价--入市交易 | C42: {=_xlfn.XLOOKUP($B$2&$B42,'总表-2025'!$B$3:'总表-2025'!$B$253&'总表-2025'!$C$3:'总表-2025'!$C$253,'总表-2025'!D$3:'总表-2025'!D$253)} | D42: {=_xlfn.XLOOKUP($B$2&$B42,'总表-2025'!$B$3:'总表-2025'!$B$253&'总表-2025'!$C$3:'总表-2025'!$C$253,'总表-2025'!E$3:'总表-2025'!E$253)} | E42: {=_xlfn.XLOOKUP($B$2&$B42,'总表-2025'!$B$3:'总表-2025'!$B$253&'总表-2025'!$C$3:'总表-2025'!$C$253,'总表-2025'!F$3:'总表-2025'!F$253)} | F42: {=_xlfn.XLOOKUP($B$2&$B42,'总表-2025'!$B$3:'总表-2025'!$B$253&'总表-2025'!$C$3:'总表-2025'!$C$253,'总表-2025'!G$3:'总表-2025'!G$253)} | G42: {=_xlfn.XLOOKUP($B$2&$B42,'总表-2025'!$B$3:'总表-2025'!$B$253&'总表-2025'!$C$3:'总表-2025'!$C$253,'总表-2025'!H$3:'总表-2025'!H$253)} | H42: {=_xlfn.XLOOKUP($B$2&$B42,'总表-2025'!$B$3:'总表-2025'!$B$253&'总表-2025'!$C$3:'总表-2025'!$C$253,'总表-2025'!I$3:'总表-2025'!I$253)} | I42: {=_xlfn.XLOOKUP($B$2&$B42,'总表-2025'!$B$3:'总表-2025'!$B$253&'总表-2025'!$C$3:'总表-2025'!$C$253,'总表-2025'!J$3:'总表-2025'!J$253)} | J42: {=_xlfn.XLOOKUP($B$2&$B42,'总表-2025'!$B$3:'总表-2025'!$B$253&'总表-2025'!$C$3:'总表-2025'!$C$253,'总表-2025'!K$3:'总表-2025'!K$253)} | ... O42: {=_xlfn.XLOOKUP($B$2&$B42,'总表-2025'!$B$3:'总表-2025'!$B$253&'总表-2025'!$C$3:'总表-2025'!$C$253,'总表-2025'!P$3:'总表-2025'!P$253)}
A62: 序号 | B62: 作图用表 | C62: 45658 | D62: 45689 | E62: 45717 | F62: 45748 | G62: 45778 | H62: 45809 | I62: 45839 | J62: 45870 | K62: 45901 | L62: 45931 | M62: 45962 | N62: 45992 | O62: 46023 | P62: 46054 | Q62: 46082 | R62: 46113 | S62: 46143 | T62: 46174 | U62: 46204 | V62: 46235 | W62: 46266 | X62: 46296 | Y62: 46327 | Z62: 46357
A63: 1 | B63: 代理购电价格 Y2025 | C63: =C35 | D63: =D35 | E63: =E35 | F63: =F35 | G63: =G35 | H63: =H35 | I63: =I35 | J63: =J35 | ... N63: =N35 | O63: =O64
A64: 1 | B64: 代理购电价格 Y2026 | O64: =C7 | P64: =D7 | Q64: =E7 | R64: =F7 | S64: =G7 | T64: =H7 | U64: =I7 | V64: =J7 | ... Z64: =N7
A65: 2 | B65: 综合平段电价--电网代购 Y2025 | C65: =C40 | D65: =D40 | E65: =E40 | F65: =F40 | G65: =G40 | H65: =H40 | I65: =I40 | J65: =J40 | ... N65: =N40 | O65: =O66
A66: 2 | B66: 综合平段电价--电网代购 Y2026 | O66: =C12 | P66: =D12 | Q66: =E12 | R66: =F12 | S66: =G12 | T66: =H12 | U66: =I12 | V66: =J12 | ... Z66: =N12
A67: 3 | B67: 上网环节线损电价 Y2025 | C67: =C36 | D67: =D36 | E67: =E36 | F67: =F36 | G67: =G36 | H67: =H36 | I67: =I36 | J67: =J36 | ... N67: =N36 | O67: =C8
A68: 3 | B68: 上网环节线损电价 Y2026 | O68: =C8 | P68: =D8 | Q68: =E8 | R68: =F8 | S68: =G8 | T68: =H8 | U68: =I8 | V68: =J8 | ... Z68: =N8
A69: 4 | B69: 系统运行费折价 Y2025 | C69: =C39 | D69: =D39 | E69: =E39 | F69: =F39 | G69: =G39 | H69: =H39 | I69: =I39 | J69: =J39 | ... N69: =N39 | O69: =C11
A70: 4 | B70: 系统运行费折价 Y2026 | O70: =C11 | P70: =D11 | Q70: =E11 | R70: =F11 | S70: =G11 | T70: =H11 | U70: =I11 | V70: =J11 | ... Z70: =N11
B75: 省间电价对比
A76: 电压等级 | B76: 两部制220kV
A77: 省份1 | B77: 冀北
A78: 省份2 | B78: 江苏
A79: 省份3 | B79: 天津
A80: 省份4 | B80: 蒙西
A81: 省份5 | B81: 上海
A101: 序号 | B101: 综合平段--电网代购价 | C101: 45658 | D101: 45689 | E101: 45717 | F101: 45748 | G101: 45778 | H101: 45809 | I101: 45839 | J101: 45870 | K101: 45901 | L101: 45931 | M101: 45962 | N101: 45992 | O101: 46023 | P101: 46054 | Q101: 46082 | R101: 46113 | S101: 46143 | T101: 46174 | U101: 46204 | V101: 46235 | W101: 46266 | X101: 46296 | Y101: 46327 | Z101: 46357
A102: 省份1 | B102: =B77 | C102: {=_xlfn.XLOOKUP($B102&$B$12,'总表-2025'!$B$3:$B$258&'总表-2025'!$C$3:$C$258,'总表-2025'!D$3:D$258)} | D102: {=_xlfn.XLOOKUP($B102&$B$12,'总表-2025'!$B$3:$B$258&'总表-2025'!$C$3:$C$258,'总表-2025'!E$3:E$258)} | E102: {=_xlfn.XLOOKUP($B102&$B$12,'总表-2025'!$B$3:$B$258&'总表-2025'!$C$3:$C$258,'总表-2025'!F$3:F$258)} | F102: {=_xlfn.XLOOKUP($B102&$B$12,'总表-2025'!$B$3:$B$258&'总表-2025'!$C$3:$C$258,'总表-2025'!G$3:G$258)} | G102: {=_xlfn.XLOOKUP($B102&$B$12,'总表-2025'!$B$3:$B$258&'总表-2025'!$C$3:$C$258,'总表-2025'!H$3:H$258)} | H102: {=_xlfn.XLOOKUP($B102&$B$12,'总表-2025'!$B$3:$B$258&'总表-2025'!$C$3:$C$258,'总表-2025'!I$3:I$258)} | I102: {=_xlfn.XLOOKUP($B102&$B$12,'总表-2025'!$B$3:$B$258&'总表-2025'!$C$3:$C$258,'总表-2025'!J$3:J$258)} | J102: {=_xlfn.XLOOKUP($B102&$B$12,'总表-2025'!$B$3:$B$258&'总表-2025'!$C$3:$C$258,'总表-2025'!K$3:K$258)} | ... N102: {=_xlfn.XLOOKUP($B102&$B$12,'总表-2025'!$B$3:$B$258&'总表-2025'!$C$3:$C$258,'总表-2025'!O$3:O$258)} | O102: {=_xlfn.XLOOKUP($B102&$B$12,'总表-2026'!$B$3:$B$258&'总表-2026'!$C$3:$C$258,'总表-2026'!D$3:D$258)} | P102: {=_xlfn.XLOOKUP($B102&$B$12,'总表-2026'!$B$3:$B$258&'总表-2026'!$C$3:$C$258,'总表-2026'!E$3:E$258)} | Q102: {=_xlfn.XLOOKUP($B102&$B$12,'总表-2026'!$B$3:$B$258&'总表-2026'!$C$3:$C$258,'总表-2026'!F$3:F$258)} | R102: {=_xlfn.XLOOKUP($B102&$B$12,'总表-2026'!$B$3:$B$258&'总表-2026'!$C$3:$C$258,'总表-2026'!G$3:G$258)} | S102: {=_xlfn.XLOOKUP($B102&$B$12,'总表-2026'!$B$3:$B$258&'总表-2026'!$C$3:$C$258,'总表-2026'!H$3:H$258)} | T102: {=_xlfn.XLOOKUP($B102&$B$12,'总表-2026'!$B$3:$B$258&'总表-2026'!$C$3:$C$258,'总表-2026'!I$3:I$258)} | U102: {=_xlfn.XLOOKUP($B102&$B$12,'总表-2026'!$B$3:$B$258&'总表-2026'!$C$3:$C$258,'总表-2026'!J$3:J$258)} | V102: {=_xlfn.XLOOKUP($B102&$B$12,'总表-2026'!$B$3:$B$258&'总表-2026'!$C$3:$C$258,'总表-2026'!K$3:K$258)} | ... Z102: {=_xlfn.XLOOKUP($B102&$B$12,'总表-2026'!$B$3:$B$258&'总表-2026'!$C$3:$C$258,'总表-2026'!O$3:O$258)}
A103: 省份2 | B103: =B78 | C103: {=_xlfn.XLOOKUP($B103&$B$12,'总表-2025'!$B$3:$B$258&'总表-2025'!$C$3:$C$258,'总表-2025'!D$3:D$258)} | D103: {=_xlfn.XLOOKUP($B103&$B$12,'总表-2025'!$B$3:$B$258&'总表-2025'!$C$3:$C$258,'总表-2025'!E$3:E$258)} | E103: {=_xlfn.XLOOKUP($B103&$B$12,'总表-2025'!$B$3:$B$258&'总表-2025'!$C$3:$C$258,'总表-2025'!F$3:F$258)} | F103: {=_xlfn.XLOOKUP($B103&$B$12,'总表-2025'!$B$3:$B$258&'总表-2025'!$C$3:$C$258,'总表-2025'!G$3:G$258)} | G103: {=_xlfn.XLOOKUP($B103&$B$12,'总表-2025'!$B$3:$B$258&'总表-2025'!$C$3:$C$258,'总表-2025'!H$3:H$258)} | H103: {=_xlfn.XLOOKUP($B103&$B$12,'总表-2025'!$B$3:$B$258&'总表-2025'!$C$3:$C$258,'总表-2025'!I$3:I$258)} | I103: {=_xlfn.XLOOKUP($B103&$B$12,'总表-2025'!$B$3:$B$258&'总表-2025'!$C$3:$C$258,'总表-2025'!J$3:J$258)} | J103: {=_xlfn.XLOOKUP($B103&$B$12,'总表-2025'!$B$3:$B$258&'总表-2025'!$C$3:$C$258,'总表-2025'!K$3:K$258)} | ... N103: {=_xlfn.XLOOKUP($B103&$B$12,'总表-2025'!$B$3:$B$258&'总表-2025'!$C$3:$C$258,'总表-2025'!O$3:O$258)} | O103: {=_xlfn.XLOOKUP($B103&$B$12,'总表-2026'!$B$3:$B$258&'总表-2026'!$C$3:$C$258,'总表-2026'!D$3:D$258)} | P103: {=_xlfn.XLOOKUP($B103&$B$12,'总表-2026'!$B$3:$B$258&'总表-2026'!$C$3:$C$258,'总表-2026'!E$3:E$258)} | Q103: {=_xlfn.XLOOKUP($B103&$B$12,'总表-2026'!$B$3:$B$258&'总表-2026'!$C$3:$C$258,'总表-2026'!F$3:F$258)} | R103: {=_xlfn.XLOOKUP($B103&$B$12,'总表-2026'!$B$3:$B$258&'总表-2026'!$C$3:$C$258,'总表-2026'!G$3:G$258)} | S103: {=_xlfn.XLOOKUP($B103&$B$12,'总表-2026'!$B$3:$B$258&'总表-2026'!$C$3:$C$258,'总表-2026'!H$3:H$258)} | T103: {=_xlfn.XLOOKUP($B103&$B$12,'总表-2026'!$B$3:$B$258&'总表-2026'!$C$3:$C$258,'总表-2026'!I$3:I$258)} | U103: {=_xlfn.XLOOKUP($B103&$B$12,'总表-2026'!$B$3:$B$258&'总表-2026'!$C$3:$C$258,'总表-2026'!J$3:J$258)} | V103: {=_xlfn.XLOOKUP($B103&$B$12,'总表-2026'!$B$3:$B$258&'总表-2026'!$C$3:$C$258,'总表-2026'!K$3:K$258)} | ... Z103: {=_xlfn.XLOOKUP($B103&$B$12,'总表-2026'!$B$3:$B$258&'总表-2026'!$C$3:$C$258,'总表-2026'!O$3:O$258)}
A104: 省份3 | B104: =B79 | C104: {=_xlfn.XLOOKUP($B104&$B$12,'总表-2025'!$B$3:$B$258&'总表-2025'!$C$3:$C$258,'总表-2025'!D$3:D$258)} | D104: {=_xlfn.XLOOKUP($B104&$B$12,'总表-2025'!$B$3:$B$258&'总表-2025'!$C$3:$C$258,'总表-2025'!E$3:E$258)} | E104: {=_xlfn.XLOOKUP($B104&$B$12,'总表-2025'!$B$3:$B$258&'总表-2025'!$C$3:$C$258,'总表-2025'!F$3:F$258)} | F104: {=_xlfn.XLOOKUP($B104&$B$12,'总表-2025'!$B$3:$B$258&'总表-2025'!$C$3:$C$258,'总表-2025'!G$3:G$258)} | G104: {=_xlfn.XLOOKUP($B104&$B$12,'总表-2025'!$B$3:$B$258&'总表-2025'!$C$3:$C$258,'总表-2025'!H$3:H$258)} | H104: {=_xlfn.XLOOKUP($B104&$B$12,'总表-2025'!$B$3:$B$258&'总表-2025'!$C$3:$C$258,'总表-2025'!I$3:I$258)} | I104: {=_xlfn.XLOOKUP($B104&$B$12,'总表-2025'!$B$3:$B$258&'总表-2025'!$C$3:$C$258,'总表-2025'!J$3:J$258)} | J104: {=_xlfn.XLOOKUP($B104&$B$12,'总表-2025'!$B$3:$B$258&'总表-2025'!$C$3:$C$258,'总表-2025'!K$3:K$258)} | ... N104: {=_xlfn.XLOOKUP($B104&$B$12,'总表-2025'!$B$3:$B$258&'总表-2025'!$C$3:$C$258,'总表-2025'!O$3:O$258)} | O104: {=_xlfn.XLOOKUP($B104&$B$12,'总表-2026'!$B$3:$B$258&'总表-2026'!$C$3:$C$258,'总表-2026'!D$3:D$258)} | P104: {=_xlfn.XLOOKUP($B104&$B$12,'总表-2026'!$B$3:$B$258&'总表-2026'!$C$3:$C$258,'总表-2026'!E$3:E$258)} | Q104: {=_xlfn.XLOOKUP($B104&$B$12,'总表-2026'!$B$3:$B$258&'总表-2026'!$C$3:$C$258,'总表-2026'!F$3:F$258)} | R104: {=_xlfn.XLOOKUP($B104&$B$12,'总表-2026'!$B$3:$B$258&'总表-2026'!$C$3:$C$258,'总表-2026'!G$3:G$258)} | S104: {=_xlfn.XLOOKUP($B104&$B$12,'总表-2026'!$B$3:$B$258&'总表-2026'!$C$3:$C$258,'总表-2026'!H$3:H$258)} | T104: {=_xlfn.XLOOKUP($B104&$B$12,'总表-2026'!$B$3:$B$258&'总表-2026'!$C$3:$C$258,'总表-2026'!I$3:I$258)} | U104: {=_xlfn.XLOOKUP($B104&$B$12,'总表-2026'!$B$3:$B$258&'总表-2026'!$C$3:$C$258,'总表-2026'!J$3:J$258)} | V104: {=_xlfn.XLOOKUP($B104&$B$12,'总表-2026'!$B$3:$B$258&'总表-2026'!$C$3:$C$258,'总表-2026'!K$3:K$258)} | ... Z104: {=_xlfn.XLOOKUP($B104&$B$12,'总表-2026'!$B$3:$B$258&'总表-2026'!$C$3:$C$258,'总表-2026'!O$3:O$258)}
A105: 省份4 | B105: =B80 | C105: {=_xlfn.XLOOKUP($B105&$B$12,'总表-2025'!$B$3:$B$258&'总表-2025'!$C$3:$C$258,'总表-2025'!D$3:D$258)} | D105: {=_xlfn.XLOOKUP($B105&$B$12,'总表-2025'!$B$3:$B$258&'总表-2025'!$C$3:$C$258,'总表-2025'!E$3:E$258)} | E105: {=_xlfn.XLOOKUP($B105&$B$12,'总表-2025'!$B$3:$B$258&'总表-2025'!$C$3:$C$258,'总表-2025'!F$3:F$258)} | F105: {=_xlfn.XLOOKUP($B105&$B$12,'总表-2025'!$B$3:$B$258&'总表-2025'!$C$3:$C$258,'总表-2025'!G$3:G$258)} | G105: {=_xlfn.XLOOKUP($B105&$B$12,'总表-2025'!$B$3:$B$258&'总表-2025'!$C$3:$C$258,'总表-2025'!H$3:H$258)} | H105: {=_xlfn.XLOOKUP($B105&$B$12,'总表-2025'!$B$3:$B$258&'总表-2025'!$C$3:$C$258,'总表-2025'!I$3:I$258)} | I105: {=_xlfn.XLOOKUP($B105&$B$12,'总表-2025'!$B$3:$B$258&'总表-2025'!$C$3:$C$258,'总表-2025'!J$3:J$258)} | J105: {=_xlfn.XLOOKUP($B105&$B$12,'总表-2025'!$B$3:$B$258&'总表-2025'!$C$3:$C$258,'总表-2025'!K$3:K$258)} | ... N105: {=_xlfn.XLOOKUP($B105&$B$12,'总表-2025'!$B$3:$B$258&'总表-2025'!$C$3:$C$258,'总表-2025'!O$3:O$258)} | O105: {=_xlfn.XLOOKUP($B105&$B$12,'总表-2026'!$B$3:$B$258&'总表-2026'!$C$3:$C$258,'总表-2026'!D$3:D$258)} | P105: {=_xlfn.XLOOKUP($B105&$B$12,'总表-2026'!$B$3:$B$258&'总表-2026'!$C$3:$C$258,'总表-2026'!E$3:E$258)} | Q105: {=_xlfn.XLOOKUP($B105&$B$12,'总表-2026'!$B$3:$B$258&'总表-2026'!$C$3:$C$258,'总表-2026'!F$3:F$258)} | R105: {=_xlfn.XLOOKUP($B105&$B$12,'总表-2026'!$B$3:$B$258&'总表-2026'!$C$3:$C$258,'总表-2026'!G$3:G$258)} | S105: {=_xlfn.XLOOKUP($B105&$B$12,'总表-2026'!$B$3:$B$258&'总表-2026'!$C$3:$C$258,'总表-2026'!H$3:H$258)} | T105: {=_xlfn.XLOOKUP($B105&$B$12,'总表-2026'!$B$3:$B$258&'总表-2026'!$C$3:$C$258,'总表-2026'!I$3:I$258)} | U105: {=_xlfn.XLOOKUP($B105&$B$12,'总表-2026'!$B$3:$B$258&'总表-2026'!$C$3:$C$258,'总表-2026'!J$3:J$258)} | V105: {=_xlfn.XLOOKUP($B105&$B$12,'总表-2026'!$B$3:$B$258&'总表-2026'!$C$3:$C$258,'总表-2026'!K$3:K$258)} | ... Z105: {=_xlfn.XLOOKUP($B105&$B$12,'总表-2026'!$B$3:$B$258&'总表-2026'!$C$3:$C$258,'总表-2026'!O$3:O$258)}
A106: 省份5 | B106: =B81 | C106: {=_xlfn.XLOOKUP($B106&$B$12,'总表-2025'!$B$3:$B$258&'总表-2025'!$C$3:$C$258,'总表-2025'!D$3:D$258)} | D106: {=_xlfn.XLOOKUP($B106&$B$12,'总表-2025'!$B$3:$B$258&'总表-2025'!$C$3:$C$258,'总表-2025'!E$3:E$258)} | E106: {=_xlfn.XLOOKUP($B106&$B$12,'总表-2025'!$B$3:$B$258&'总表-2025'!$C$3:$C$258,'总表-2025'!F$3:F$258)} | F106: {=_xlfn.XLOOKUP($B106&$B$12,'总表-2025'!$B$3:$B$258&'总表-2025'!$C$3:$C$258,'总表-2025'!G$3:G$258)} | G106: {=_xlfn.XLOOKUP($B106&$B$12,'总表-2025'!$B$3:$B$258&'总表-2025'!$C$3:$C$258,'总表-2025'!H$3:H$258)} | H106: {=_xlfn.XLOOKUP($B106&$B$12,'总表-2025'!$B$3:$B$258&'总表-2025'!$C$3:$C$258,'总表-2025'!I$3:I$258)} | I106: {=_xlfn.XLOOKUP($B106&$B$12,'总表-2025'!$B$3:$B$258&'总表-2025'!$C$3:$C$258,'总表-2025'!J$3:J$258)} | J106: {=_xlfn.XLOOKUP($B106&$B$12,'总表-2025'!$B$3:$B$258&'总表-2025'!$C$3:$C$258,'总表-2025'!K$3:K$258)} | ... N106: {=_xlfn.XLOOKUP($B106&$B$12,'总表-2025'!$B$3:$B$258&'总表-2025'!$C$3:$C$258,'总表-2025'!O$3:O$258)} | O106: {=_xlfn.XLOOKUP($B106&$B$12,'总表-2026'!$B$3:$B$258&'总表-2026'!$C$3:$C$258,'总表-2026'!D$3:D$258)} | P106: {=_xlfn.XLOOKUP($B106&$B$12,'总表-2026'!$B$3:$B$258&'总表-2026'!$C$3:$C$258,'总表-2026'!E$3:E$258)} | Q106: {=_xlfn.XLOOKUP($B106&$B$12,'总表-2026'!$B$3:$B$258&'总表-2026'!$C$3:$C$258,'总表-2026'!F$3:F$258)} | R106: {=_xlfn.XLOOKUP($B106&$B$12,'总表-2026'!$B$3:$B$258&'总表-2026'!$C$3:$C$258,'总表-2026'!G$3:G$258)} | S106: {=_xlfn.XLOOKUP($B106&$B$12,'总表-2026'!$B$3:$B$258&'总表-2026'!$C$3:$C$258,'总表-2026'!H$3:H$258)} | T106: {=_xlfn.XLOOKUP($B106&$B$12,'总表-2026'!$B$3:$B$258&'总表-2026'!$C$3:$C$258,'总表-2026'!I$3:I$258)} | U106: {=_xlfn.XLOOKUP($B106&$B$12,'总表-2026'!$B$3:$B$258&'总表-2026'!$C$3:$C$258,'总表-2026'!J$3:J$258)} | V106: {=_xlfn.XLOOKUP($B106&$B$12,'总表-2026'!$B$3:$B$258&'总表-2026'!$C$3:$C$258,'总表-2026'!K$3:K$258)} | ... Z106: {=_xlfn.XLOOKUP($B106&$B$12,'总表-2026'!$B$3:$B$258&'总表-2026'!$C$3:$C$258,'总表-2026'!O$3:O$258)}

Sheet 总表-2026
B1: 电压等级 | C1: ='首页+选择功能'!B4
A2: 序号 | B2: 省份 | C2: 2026年电价表 | D2: 1月 | E2: 2月 | F2: 3月 | G2: 4月 | H2: 5月 | I2: 6月 | J2: 7月 | K2: 8月 | L2: 9月 | M2: 10月 | N2: 11月 | O2: 12月 | P2: 年均 | Q2: 趋势图
A3: 1 | B3: 北京 | C3: 代理购电价格 | D3: ='分表1-2026电网代购价'!D2 | E3: ='分表1-2026电网代购价'!E2 | F3: ='分表1-2026电网代购价'!F2 | G3: ='分表1-2026电网代购价'!G2 | H3: ='分表1-2026电网代购价'!H2 | P3: =IF(SUM(D3:O3)=0,"0",AVERAGEIF(D3:O3,"<>0",D3:O3))
A4: 2 | B4: 北京 | C4: 上网环节线损电价 | D4: ='分表2-2026上网环节线损'!C2 | E4: ='分表2-2026上网环节线损'!D2 | F4: ='分表2-2026上网环节线损'!E2 | G4: ='分表2-2026上网环节线损'!F2 | H4: ='分表2-2026上网环节线损'!G2 | P4: =IF(SUM(D4:O4)=0,"0",AVERAGEIF(D4:O4,"<>0",D4:O4))
A5: 3 | B5: 北京 | C5: 电度输配电价 | D5: {=_xlfn.XLOOKUP($C$1,'分表4-电度输配电价'!$C2：'分表4-电度输配电价'!$C9&'分表4-电度输配电价'!$D2：'分表4-电度输配电价'!$D9,'分表4-电度输配电价'!$E2：'分表4-电度输配电价'!$E9)} | E5: {=_xlfn.XLOOKUP($C$1,'分表4-电度输配电价'!$C2：'分表4-电度输配电价'!$C9&'分表4-电度输配电价'!$D2：'分表4-电度输配电价'!$D9,'分表4-电度输配电价'!$E2：'分表4-电度输配电价'!$E9)} | F5: {=_xlfn.XLOOKUP($C$1,'分表4-电度输配电价'!$C2：'分表4-电度输配电价'!$C9&'分表4-电度输配电价'!$D2：'分表4-电度输配电价'!$D9,'分表4-电度输配电价'!$E2：'分表4-电度输配电价'!$E9)} | G5: {=_xlfn.XLOOKUP($C$1,'分表4-电度输配电价'!$C2：'分表4-电度输配电价'!$C9&'分表4-电度输配电价'!$D2：'分表4-电度输配电价'!$D9,'分表4-电度输配电价'!$E2：'分表4-电度输配电价'!$E9)} | H5: {=_xlfn.XLOOKUP($C$1,'分表4-电度输配电价'!$C2：'分表4-电度输配电价'!$C9&'分表4-电度输配电价'!$D2：'分表4-电度输配电价'!$D9,'分表4-电度输配电价'!$E2：'分表4-电度输配电价'!$E9)} | P5: =IF(SUM(D5:O5)=0,"0",AVERAGEIF(D5:O5,"<>0",D5:O5))
A6: 4 | B6: 北京 | C6: 政府性基金及附加 | D6: {=_xlfn.XLOOKUP($B$6,'分表5-政府性基金及附加'!$B$2：'分表5-政府性基金及附加'!$B$199,'分表5-政府性基金及附加'!$D$2：'分表5-政府性基金及附加'!$D$199)} | E6: {=_xlfn.XLOOKUP($B$6,'分表5-政府性基金及附加'!$B$2：'分表5-政府性基金及附加'!$B$199,'分表5-政府性基金及附加'!$D$2：'分表5-政府性基金及附加'!$D$199)} | F6: {=_xlfn.XLOOKUP($B$6,'分表5-政府性基金及附加'!$B$2：'分表5-政府性基金及附加'!$B$199,'分表5-政府性基金及附加'!$D$2：'分表5-政府性基金及附加'!$D$199)} | G6: {=_xlfn.XLOOKUP($B$6,'分表5-政府性基金及附加'!$B$2：'分表5-政府性基金及附加'!$B$199,'分表5-政府性基金及附加'!$D$2：'分表5-政府性基金及附加'!$D$199)} | H6: {=_xlfn.XLOOKUP($B$6,'分表5-政府性基金及附加'!$B$2：'分表5-政府性基金及附加'!$B$199,'分表5-政府性基金及附加'!$D$2：'分表5-政府性基金及附加'!$D$199)} | P6: =IF(SUM(D6:O6)=0,"0",AVERAGEIF(D6:O6,"<>0",D6:O6))
A7: 5 | B7: 北京 | C7: 系统运行费折价 | D7: ='分表3-2026系统运行费'!D2 | E7: ='分表3-2026系统运行费'!E2 | F7: ='分表3-2026系统运行费'!F2 | G7: ='分表3-2026系统运行费'!G2 | H7: ='分表3-2026系统运行费'!H2 | P7: =IF(SUM(D7:O7)=0,"0",AVERAGEIF(D7:O7,"<>0",D7:O7))
A8: 6 | B8: 北京 | C8: 综合平段电价--电网代购 | D8: =IF(D5="/","/",SUM(D3:D7)) | E8: =IF(E5="/","/",SUM(E3:E7)) | F8: =IF(F5="/","/",SUM(F3:F7)) | G8: =IF(G5="/","/",SUM(G3:G7)) | H8: =IF(H5="/","/",SUM(H3:H7)) | P8: =IF(SUM(D8:O8)=0,"0",AVERAGEIF(D8:O8,"<>0",D8:O8))
A9: 7 | B9: 北京 | C9: 入市交易购电价格 | D9: ='分表7-2026交易价格'!D2 | E9: ='分表7-2026交易价格'!E2 | F9: ='分表7-2026交易价格'!F2 | G9: ='分表7-2026交易价格'!G2 | H9: ='分表7-2026交易价格'!H2 | P9: =IF(SUM(D9:O9)=0,"0",AVERAGEIF(D9:O9,"<>0",D9:O9))
A10: 8 | B10: 北京 | C10: 综合平段电价--入市交易 | D10: =IF(D5="/","/",IF(D9>0,D9+SUM(D4:D7),"/")) | E10: =IF(E5="/","/",IF(E9>0,E9+SUM(E4:E7),"/")) | F10: =IF(F5="/","/",IF(F9>0,F9+SUM(F4:F7),"/")) | G10: =IF(G5="/","/",IF(G9>0,G9+SUM(G4:G7),"/")) | H10: =IF(H5="/","/",IF(H9>0,H9+SUM(H4:H7),"/")) | P10: =IF(SUM(D10:O10)=0,"0",AVERAGEIF(D10:O10,"<>0",D10:O10))
A11: 9 | B11: 天津 | C11: 代理购电价格 | D11: ='分表1-2026电网代购价'!D5 | E11: ='分表1-2026电网代购价'!E5 | F11: ='分表1-2026电网代购价'!F5 | G11: ='分表1-2026电网代购价'!G5 | H11: ='分表1-2026电网代购价'!H5 | P11: =IF(SUM(D11:O11)=0,"0",AVERAGEIF(D11:O11,"<>0",D11:O11))
A12: 10 | B12: 天津 | C12: 上网环节线损电价 | D12: ='分表2-2026上网环节线损'!C3 | E12: ='分表2-2026上网环节线损'!D3 | F12: ='分表2-2026上网环节线损'!E3 | G12: ='分表2-2026上网环节线损'!F3 | H12: ='分表2-2026上网环节线损'!G3 | P12: =IF(SUM(D12:O12)=0,"0",AVERAGEIF(D12:O12,"<>0",D12:O12))
A13: 11 | B13: 天津 | C13: 电度输配电价 | D13: {=_xlfn.XLOOKUP($C$1,'分表4-电度输配电价'!$C10：'分表4-电度输配电价'!$C17&'分表4-电度输配电价'!$D10：'分表4-电度输配电价'!$D17,'分表4-电度输配电价'!$E10：'分表4-电度输配电价'!$E17)} | E13: {=_xlfn.XLOOKUP($C$1,'分表4-电度输配电价'!$C10：'分表4-电度输配电价'!$C17&'分表4-电度输配电价'!$D10：'分表4-电度输配电价'!$D17,'分表4-电度输配电价'!$E10：'分表4-电度输配电价'!$E17)} | F13: {=_xlfn.XLOOKUP($C$1,'分表4-电度输配电价'!$C10：'分表4-电度输配电价'!$C17&'分表4-电度输配电价'!$D10：'分表4-电度输配电价'!$D17,'分表4-电度输配电价'!$E10：'分表4-电度输配电价'!$E17)} | G13: {=_xlfn.XLOOKUP($C$1,'分表4-电度输配电价'!$C10：'分表4-电度输配电价'!$C17&'分表4-电度输配电价'!$D10：'分表4-电度输配电价'!$D17,'分表4-电度输配电价'!$E10：'分表4-电度输配电价'!$E17)} | H13: {=_xlfn.XLOOKUP($C$1,'分表4-电度输配电价'!$C10：'分表4-电度输配电价'!$C17&'分表4-电度输配电价'!$D10：'分表4-电度输配电价'!$D17,'分表4-电度输配电价'!$E10：'分表4-电度输配电价'!$E17)} | P13: =IF(SUM(D13:O13)=0,"0",AVERAGEIF(D13:O13,"<>0",D13:O13))
A14: 12 | B14: 天津 | C14: 政府性基金及附加 | D14: {=_xlfn.XLOOKUP($B$14,'分表5-政府性基金及附加'!$B$2：'分表5-政府性基金及附加'!$B$199,'分表5-政府性基金及附加'!$D$2：'分表5-政府性基金及附加'!$D$199)} | E14: {=_xlfn.XLOOKUP($B$14,'分表5-政府性基金及附加'!$B$2：'分表5-政府性基金及附加'!$B$199,'分表5-政府性基金及附加'!$D$2：'分表5-政府性基金及附加'!$D$199)} | F14: {=_xlfn.XLOOKUP($B$14,'分表5-政府性基金及附加'!$B$2：'分表5-政府性基金及附加'!$B$199,'分表5-政府性基金及附加'!$D$2：'分表5-政府性基金及附加'!$D$199)} | G14: {=_xlfn.XLOOKUP($B$14,'分表5-政府性基金及附加'!$B$2：'分表5-政府性基金及附加'!$B$199,'分表5-政府性基金及附加'!$D$2：'分表5-政府性基金及附加'!$D$199)} | H14: {=_xlfn.XLOOKUP($B$14,'分表5-政府性基金及附加'!$B$2：'分表5-政府性基金及附加'!$B$199,'分表5-政府性基金及附加'!$D$2：'分表5-政府性基金及附加'!$D$199)} | P14: =IF(SUM(D14:O14)=0,"0",AVERAGEIF(D14:O14,"<>0",D14:O14))
A15: 13 | B15: 天津 | C15: 系统运行费折价 | D15: ='分表3-2026系统运行费'!Q2 | E15: ='分表3-2026系统运行费'!R2 | F15: ='分表3-2026系统运行费'!S2 | G15: ='分表3-2026系统运行费'!T2 | H15: ='分表3-2026系统运行费'!U2 | P15: =IF(SUM(D15:O15)=0,"0",AVERAGEIF(D15:O15,"<>0",D15:O15))
A16: 14 | B16: 天津 | C16: 综合平段电价--电网代购 | D16: =IF(D13="/","/",SUM(D11:D15)) | E16: =IF(E13="/","/",SUM(E11:E15)) | F16: =IF(F13="/","/",SUM(F11:F15)) | G16: =IF(G13="/","/",SUM(G11:G15)) | H16: =IF(H13="/","/",SUM(H11:H15)) | P16: =IF(SUM(D16:O16)=0,"0",AVERAGEIF(D16:O16,"<>0",D16:O16))
A17: 15 | B17: 天津 | C17: 入市交易购电价格 | D17: ='分表7-2026交易价格'!D3 | E17: ='分表7-2026交易价格'!E3 | F17: ='分表7-2026交易价格'!F3 | G17: ='分表7-2026交易价格'!G3 | H17: ='分表7-2026交易价格'!H3 | P17: =IF(SUM(D17:O17)=0,"0",AVERAGEIF(D17:O17,"<>0",D17:O17))
A18: 16 | B18: 天津 | C18: 综合平段电价--入市交易 | D18: =IF(D13="/","/",IF(D17>0,D17+SUM(D12:D15),"/")) | E18: =IF(E13="/","/",IF(E17>0,E17+SUM(E12:E15),"/")) | F18: =IF(F13="/","/",IF(F17>0,F17+SUM(F12:F15),"/")) | G18: =IF(G13="/","/",IF(G17>0,G17+SUM(G12:G15),"/")) | H18: =IF(H13="/","/",IF(H17>0,H17+SUM(H12:H15),"/")) | P18: =IF(SUM(D18:O18)=0,"0",AVERAGEIF(D18:O18,"<>0",D18:O18))
A19: 17 | B19: 河北南网 | C19: 代理购电价格 | D19: ='分表1-2026电网代购价'!D8 | E19: ='分表1-2026电网代购价'!E8 | F19: ='分表1-2026电网代购价'!F8 | G19: ='分表1-2026电网代购价'!G8 | H19: ='分表1-2026电网代购价'!H8 | P19: =IF(SUM(D19:O19)=0,"0",AVERAGEIF(D19:O19,"<>0",D19:O19))
A20: 18 | B20: 河北南网 | C20: 上网环节线损电价 | D20: ='分表2-2026上网环节线损'!C4 | E20: ='分表2-2026上网环节线损'!D4 | F20: ='分表2-2026上网环节线损'!E4 | G20: ='分表2-2026上网环节线损'!F4 | H20: ='分表2-2026上网环节线损'!G4 | P20: =IF(SUM(D20:O20)=0,"0",AVERAGEIF(D20:O20,"<>0",D20:O20))
A21: 19 | B21: 河北南网 | C21: 电度输配电价 | D21: {=_xlfn.XLOOKUP($C$1,'分表4-电度输配电价'!$C18：'分表4-电度输配电价'!$C25&'分表4-电度输配电价'!$D18：'分表4-电度输配电价'!$D25,'分表4-电度输配电价'!$E18：'分表4-电度输配电价'!$E25)} | E21: {=_xlfn.XLOOKUP($C$1,'分表4-电度输配电价'!$C18：'分表4-电度输配电价'!$C25&'分表4-电度输配电价'!$D18：'分表4-电度输配电价'!$D25,'分表4-电度输配电价'!$E18：'分表4-电度输配电价'!$E25)} | F21: {=_xlfn.XLOOKUP($C$1,'分表4-电度输配电价'!$C18：'分表4-电度输配电价'!$C25&'分表4-电度输配电价'!$D18：'分表4-电度输配电价'!$D25,'分表4-电度输配电价'!$E18：'分表4-电度输配电价'!$E25)} | G21: {=_xlfn.XLOOKUP($C$1,'分表4-电度输配电价'!$C18：'分表4-电度输配电价'!$C25&'分表4-电度输配电价'!$D18：'分表4-电度输配电价'!$D25,'分表4-电度输配电价'!$E18：'分表4-电度输配电价'!$E25)} | H21: {=_xlfn.XLOOKUP($C$1,'分表4-电度输配电价'!$C18：'分表4-电度输配电价'!$C25&'分表4-电度输配电价'!$D18：'分表4-电度输配电价'!$D25,'分表4-电度输配电价'!$E18：'分表4-电度输配电价'!$E25)} | P21: =IF(SUM(D21:O21)=0,"0",AVERAGEIF(D21:O21,"<>0",D21:O21))
A22: 20 | B22: 河北南网 | C22: 政府性基金及附加 | D22: {=_xlfn.XLOOKUP($B$22,'分表5-政府性基金及附加'!$B$2：'分表5-政府性基金及附加'!$B$199,'分表5-政府性基金及附加'!$D$2：'分表5-政府性基金及附加'!$D$199)} | E22: {=_xlfn.XLOOKUP($B$22,'分表5-政府性基金及附加'!$B$2：'分表5-政府性基金及附加'!$B$199,'分表5-政府性基金及附加'!$D$2：'分表5-政府性基金及附加'!$D$199)} | F22: {=_xlfn.XLOOKUP($B$22,'分表5-政府性基金及附加'!$B$2：'分表5-政府性基金及附加'!$B$199,'分表5-政府性基金及附加'!$D$2：'分表5-政府性基金及附加'!$D$199)} | G22: {=_xlfn.XLOOKUP($B$22,'分表5-政府性基金及附加'!$B$2：'分表5-政府性基金及附加'!$B$199,'分表5-政府性基金及附加'!$D$2：'分表5-政府性基金及附加'!$D$199)} | H22: {=_xlfn.XLOOKUP($B$22,'分表5-政府性基金及附加'!$B$2：'分表5-政府性基金及附加'!$B$199,'分表5-政府性基金及附加'!$D$2：'分表5-政府性基金及附加'!$D$199)} | P22: =IF(SUM(D22:O22)=0,"0",AVERAGEIF(D22:O22,"<>0",D22:O22))
A23: 21 | B23: 河北南网 | C23: 系统运行费折价 | D23: ='分表3-2026系统运行费'!AD2 | E23: ='分表3-2026系统运行费'!AE2 | F23: ='分表3-2026系统运行费'!AF2 | G23: ='分表3-2026系统运行费'!AG2 | H23: ='分表3-2026系统运行费'!AH2 | P23: =IF(SUM(D23:O23)=0,"0",AVERAGEIF(D23:O23,"<>0",D23:O23))
A24: 22 | B24: 河北南网 | C24: 综合平段电价--电网代购 | D24: =IF(D21="/","/",SUM(D19:D23)) | E24: =IF(E21="/","/",SUM(E19:E23)) | F24: =IF(F21="/","/",SUM(F19:F23)) | G24: =IF(G21="/","/",SUM(G19:G23)) | H24: =IF(H21="/","/",SUM(H19:H23)) | P24: =IF(SUM(D24:O24)=0,"0",AVERAGEIF(D24:O24,"<>0",D24:O24))
A25: 23 | B25: 河北南网 | C25: 入市交易购电价格 | D25: ='分表7-2026交易价格'!D4 | E25: ='分表7-2026交易价格'!E4 | F25: ='分表7-2026交易价格'!F4 | G25: ='分表7-2026交易价格'!G4 | H25: ='分表7-2026交易价格'!H4 | P25: =IF(SUM(D25:O25)=0,"0",AVERAGEIF(D25:O25,"<>0",D25:O25))
A26: 24 | B26: 河北南网 | C26: 综合平段电价--入市交易 | D26: =IF(D21="/","/",IF(D25>0,D25+SUM(D20:D23),"/")) | E26: =IF(E21="/","/",IF(E25>0,E25+SUM(E20:E23),"/")) | F26: =IF(F21="/","/",IF(F25>0,F25+SUM(F20:F23),"/")) | G26: =IF(G21="/","/",IF(G25>0,G25+SUM(G20:G23),"/")) | H26: =IF(H21="/","/",IF(H25>0,H25+SUM(H20:H23),"/")) | P26: =IF(SUM(D26:O26)=0,"0",AVERAGEIF(D26:O26,"<>0",D26:O26))
A27: 25 | B27: 冀北 | C27: 代理购电价格 | D27: ='分表1-2026电网代购价'!D11 | E27: ='分表1-2026电网代购价'!E11 | F27: ='分表1-2026电网代购价'!F11 | G27: ='分表1-2026电网代购价'!G11 | H27: ='分表1-2026电网代购价'!H11 | P27: =IF(SUM(D27:O27)=0,"0",AVERAGEIF(D27:O27,"<>0",D27:O27))
A28: 26 | B28: 冀北 | C28: 上网环节线损电价 | D28: ='分表2-2026上网环节线损'!C5 | E28: ='分表2-2026上网环节线损'!D5 | F28: ='分表2-2026上网环节线损'!E5 | G28: ='分表2-2026上网环节线损'!F5 | H28: ='分表2-2026上网环节线损'!G5 | P28: =IF(SUM(D28:O28)=0,"0",AVERAGEIF(D28:O28,"<>0",D28:O28))
A29: 27 | B29: 冀北 | C29: 电度输配电价 | D29: {=_xlfn.XLOOKUP($C$1,'分表4-电度输配电价'!$C26：'分表4-电度输配电价'!$C33&'分表4-电度输配电价'!$D26：'分表4-电度输配电价'!$D33,'分表4-电度输配电价'!$E26：'分表4-电度输配电价'!$E33)} | E29: {=_xlfn.XLOOKUP($C$1,'分表4-电度输配电价'!$C26：'分表4-电度输配电价'!$C33&'分表4-电度输配电价'!$D26：'分表4-电度输配电价'!$D33,'分表4-电度输配电价'!$E26：'分表4-电度输配电价'!$E33)} | F29: {=_xlfn.XLOOKUP($C$1,'分表4-电度输配电价'!$C26：'分表4-电度输配电价'!$C33&'分表4-电度输配电价'!$D26：'分表4-电度输配电价'!$D33,'分表4-电度输配电价'!$E26：'分表4-电度输配电价'!$E33)} | G29: {=_xlfn.XLOOKUP($C$1,'分表4-电度输配电价'!$C26：'分表4-电度输配电价'!$C33&'分表4-电度输配电价'!$D26：'分表4-电度输配电价'!$D33,'分表4-电度输配电价'!$E26：'分表4-电度输配电价'!$E33)} | H29: {=_xlfn.XLOOKUP($C$1,'分表4-电度输配电价'!$C26：'分表4-电度输配电价'!$C33&'分表4-电度输配电价'!$D26：'分表4-电度输配电价'!$D33,'分表4-电度输配电价'!$E26：'分表4-电度输配电价'!$E33)} | P29: =IF(SUM(D29:O29)=0,"0",AVERAGEIF(D29:O29,"<>0",D29:O29))
A30: 28 | B30: 冀北 | C30: 政府性基金及附加 | D30: {=_xlfn.XLOOKUP($B$30,'分表5-政府性基金及附加'!$B$2：'分表5-政府性基金及附加'!$B$199,'分表5-政府性基金及附加'!$D$2：'分表5-政府性基金及附加'!$D$199)} | E30: {=_xlfn.XLOOKUP($B$30,'分表5-政府性基金及附加'!$B$2：'分表5-政府性基金及附加'!$B$199,'分表5-政府性基金及附加'!$D$2：'分表5-政府性基金及附加'!$D$199)} | F30: {=_xlfn.XLOOKUP($B$30,'分表5-政府性基金及附加'!$B$2：'分表5-政府性基金及附加'!$B$199,'分表5-政府性基金及附加'!$D$2：'分表5-政府性基金及附加'!$D$199)} | G30: {=_xlfn.XLOOKUP($B$30,'分表5-政府性基金及附加'!$B$2：'分表5-政府性基金及附加'!$B$199,'分表5-政府性基金及附加'!$D$2：'分表5-政府性基金及附加'!$D$199)} | H30: {=_xlfn.XLOOKUP($B$30,'分表5-政府性基金及附加'!$B$2：'分表5-政府性基金及附加'!$B$199,'分表5-政府性基金及附加'!$D$2：'分表5-政府性基金及附加'!$D$199)} | P30: =IF(SUM(D30:O30)=0,"0",AVERAGEIF(D30:O30,"<>0",D30:O30))
A31: 29 | B31: 冀北 | C31: 系统运行费折价 | D31: ='分表3-2026系统运行费'!AQ2 | E31: ='分表3-2026系统运行费'!AR2 | F31: ='分表3-2026系统运行费'!AS2 | G31: ='分表3-2026系统运行费'!AT2 | H31: ='分表3-2026系统运行费'!AU2 | P31: =IF(SUM(D31:O31)=0,"0",AVERAGEIF(D31:O31,"<>0",D31:O31))
A32: 30 | B32: 冀北 | C32: 综合平段电价--电网代购 | D32: =IF(D29="/","/",SUM(D27:D31)) | E32: =IF(E29="/","/",SUM(E27:E31)) | F32: =IF(F29="/","/",SUM(F27:F31)) | G32: =IF(G29="/","/",SUM(G27:G31)) | H32: =IF(H29="/","/",SUM(H27:H31)) | P32: =IF(SUM(D32:O32)=0,"0",AVERAGEIF(D32:O32,"<>0",D32:O32))
A33: 31 | B33: 冀北 | C33: 入市交易购电价格 | D33: ='分表7-2026交易价格'!D5 | E33: ='分表7-2026交易价格'!E5 | F33: ='分表7-2026交易价格'!F5 | G33: ='分表7-2026交易价格'!G5 | H33: ='分表7-2026交易价格'!H5 | P33: =IF(SUM(D33:O33)=0,"0",AVERAGEIF(D33:O33,"<>0",D33:O33))
A34: 32 | B34: 冀北 | C34: 综合平段电价--入市交易 | D34: =IF(D29="/","/",IF(D33>0,D33+SUM(D28:D31),"/")) | E34: =IF(E29="/","/",IF(E33>0,E33+SUM(E28:E31),"/")) | F34: =IF(F29="/","/",IF(F33>0,F33+SUM(F28:F31),"/")) | G34: =IF(G29="/","/",IF(G33>0,G33+SUM(G28:G31),"/")) | H34: =IF(H29="/","/",IF(H33>0,H33+SUM(H28:H31),"/")) | P34: =IF(SUM(D34:O34)=0,"0",AVERAGEIF(D34:O34,"<>0",D34:O34))
A35: 33 | B35: 山东 | C35: 代理购电价格 | D35: ='分表1-2026电网代购价'!D14 | E35: ='分表1-2026电网代购价'!E14 | F35: ='分表1-2026电网代购价'!F14 | G35: ='分表1-2026电网代购价'!G14 | H35: ='分表1-2026电网代购价'!H14 | P35: =IF(SUM(D35:O35)=0,"0",AVERAGEIF(D35:O35,"<>0",D35:O35))
A36: 34 | B36: 山东 | C36: 上网环节线损电价 | D36: ='分表2-2026上网环节线损'!C6 | E36: ='分表2-2026上网环节线损'!D6 | F36: ='分表2-2026上网环节线损'!E6 | G36: ='分表2-2026上网环节线损'!F6 | H36: ='分表2-2026上网环节线损'!G6 | P36: =IF(SUM(D36:O36)=0,"0",AVERAGEIF(D36:O36,"<>0",D36:O36))
A37: 35 | B37: 山东 | C37: 电度输配电价 | D37: {=_xlfn.XLOOKUP($C$1,'分表4-电度输配电价'!$C34：'分表4-电度输配电价'!$C41&'分表4-电度输配电价'!$D34：'分表4-电度输配电价'!$D41,'分表4-电度输配电价'!$E34：'分表4-电度输配电价'!$E41)} | E37: {=_xlfn.XLOOKUP($C$1,'分表4-电度输配电价'!$C34：'分表4-电度输配电价'!$C41&'分表4-电度输配电价'!$D34：'分表4-电度输配电价'!$D41,'分表4-电度输配电价'!$E34：'分表4-电度输配电价'!$E41)} | F37: {=_xlfn.XLOOKUP($C$1,'分表4-电度输配电价'!$C34：'分表4-电度输配电价'!$C41&'分表4-电度输配电价'!$D34：'分表4-电度输配电价'!$D41,'分表4-电度输配电价'!$E34：'分表4-电度输配电价'!$E41)} | G37: {=_xlfn.XLOOKUP($C$1,'分表4-电度输配电价'!$C34：'分表4-电度输配电价'!$C41&'分表4-电度输配电价'!$D34：'分表4-电度输配电价'!$D41,'分表4-电度输配电价'!$E34：'分表4-电度输配电价'!$E41)} | H37: {=_xlfn.XLOOKUP($C$1,'分表4-电度输配电价'!$C34：'分表4-电度输配电价'!$C41&'分表4-电度输配电价'!$D34：'分表4-电度输配电价'!$D41,'分表4-电度输配电价'!$E34：'分表4-电度输配电价'!$E41)} | P37: =IF(SUM(D37:O37)=0,"0",AVERAGEIF(D37:O37,"<>0",D37:O37))
A38: 36 | B38: 山东 | C38: 政府性基金及附加 | D38: {=_xlfn.XLOOKUP($B$38,'分表5-政府性基金及附加'!$B$2：'分表5-政府性基金及附加'!$B$199,'分表5-政府性基金及附加'!$D$2：'分表5-政府性基金及附加'!$D$199)} | E38: {=_xlfn.XLOOKUP($B$38,'分表5-政府性基金及附加'!$B$2：'分表5-政府性基金及附加'!$B$199,'分表5-政府性基金及附加'!$D$2：'分表5-政府性基金及附加'!$D$199)} | F38: {=_xlfn.XLOOKUP($B$38,'分表5-政府性基金及附加'!$B$2：'分表5-政府性基金及附加'!$B$199,'分表5-政府性基金及附加'!$D$2：'分表5-政府性基金及附加'!$D$199)} | G38: {=_xlfn.XLOOKUP($B$38,'分表5-政府性基金及附加'!$B$2：'分表5-政府性基金及附加'!$B$199,'分表5-政府性基金及附加'!$D$2：'分表5-政府性基金及附加'!$D$199)} | H38: {=_xlfn.XLOOKUP($B$38,'分表5-政府性基金及附加'!$B$2：'分表5-政府性基金及附加'!$B$199,'分表5-政府性基金及附加'!$D$2：'分表5-政府性基金及附加'!$D$199)} | P38: =IF(SUM(D38:O38)=0,"0",AVERAGEIF(D38:O38,"<>0",D38:O38))
A39: 37 | B39: 山东 | C39: 系统运行费折价 | D39: ='分表3-2026系统运行费'!BD2 | E39: ='分表3-2026系统运行费'!BE2 | F39: ='分表3-2026系统运行费'!BF2 | G39: ='分表3-2026系统运行费'!BG2 | H39: ='分表3-2026系统运行费'!BH2 | P39: =IF(SUM(D39:O39)=0,"0",AVERAGEIF(D39:O39,"<>0",D39:O39))
A40: 38 | B40: 山东 | C40: 综合平段电价--电网代购 | D40: =IF(D37="/","/",SUM(D35:D39)) | E40: =IF(E37="/","/",SUM(E35:E39)) | F40: =IF(F37="/","/",SUM(F35:F39)) | G40: =IF(G37="/","/",SUM(G35:G39)) | H40: =IF(H37="/","/",SUM(H35:H39)) | P40: =IF(SUM(D40:O40)=0,"0",AVERAGEIF(D40:O40,"<>0",D40:O40))
A41: 39 | B41: 山东 | C41: 入市交易购电价格 | D41: ='分表7-2026交易价格'!D6 | E41: ='分表7-2026交易价格'!E6 | F41: ='分表7-2026交易价格'!F6 | G41: ='分表7-2026交易价格'!G6 | H41: ='分表7-2026交易价格'!H6 | P41: =IF(SUM(D41:O41)=0,"0",AVERAGEIF(D41:O41,"<>0",D41:O41))
A42: 40 | B42: 山东 | C42: 综合平段电价--入市交易 | D42: =IF(D37="/","/",IF(D41>0,D41+SUM(D36:D39),"/")) | E42: =IF(E37="/","/",IF(E41>0,E41+SUM(E36:E39),"/")) | F42: =IF(F37="/","/",IF(F41>0,F41+SUM(F36:F39),"/")) | G42: =IF(G37="/","/",IF(G41>0,G41+SUM(G36:G39),"/")) | H42: =IF(H37="/","/",IF(H41>0,H41+SUM(H36:H39),"/")) | P42: =IF(SUM(D42:O42)=0,"0",AVERAGEIF(D42:O42,"<>0",D42:O42))
A43: 41 | B43: 山西 | C43: 代理购电价格 | D43: ='分表1-2026电网代购价'!D18 | E43: ='分表1-2026电网代购价'!E18 | F43: ='分表1-2026电网代购价'!F18 | G43: ='分表1-2026电网代购价'!G18 | H43: ='分表1-2026电网代购价'!H18 | P43: =IF(SUM(D43:O43)=0,"0",AVERAGEIF(D43:O43,"<>0",D43:O43))
A44: 42 | B44: 山西 | C44: 上网环节线损电价 | D44: ='分表2-2026上网环节线损'!C7 | E44: ='分表2-2026上网环节线损'!D7 | F44: ='分表2-2026上网环节线损'!E7 | G44: ='分表2-2026上网环节线损'!F7 | H44: ='分表2-2026上网环节线损'!G7 | P44: =IF(SUM(D44:O44)=0,"0",AVERAGEIF(D44:O44,"<>0",D44:O44))
A45: 43 | B45: 山西 | C45: 电度输配电价 | D45: {=_xlfn.XLOOKUP($C$1,'分表4-电度输配电价'!$C42：'分表4-电度输配电价'!$C49&'分表4-电度输配电价'!$D42：'分表4-电度输配电价'!$D49,'分表4-电度输配电价'!$E42：'分表4-电度输配电价'!$E49)} | E45: {=_xlfn.XLOOKUP($C$1,'分表4-电度输配电价'!$C42：'分表4-电度输配电价'!$C49&'分表4-电度输配电价'!$D42：'分表4-电度输配电价'!$D49,'分表4-电度输配电价'!$E42：'分表4-电度输配电价'!$E49)} | F45: {=_xlfn.XLOOKUP($C$1,'分表4-电度输配电价'!$C42：'分表4-电度输配电价'!$C49&'分表4-电度输配电价'!$D42：'分表4-电度输配电价'!$D49,'分表4-电度输配电价'!$E42：'分表4-电度输配电价'!$E49)} | G45: {=_xlfn.XLOOKUP($C$1,'分表4-电度输配电价'!$C42：'分表4-电度输配电价'!$C49&'分表4-电度输配电价'!$D42：'分表4-电度输配电价'!$D49,'分表4-电度输配电价'!$E42：'分表4-电度输配电价'!$E49)} | H45: {=_xlfn.XLOOKUP($C$1,'分表4-电度输配电价'!$C42：'分表4-电度输配电价'!$C49&'分表4-电度输配电价'!$D42：'分表4-电度输配电价'!$D49,'分表4-电度输配电价'!$E42：'分表4-电度输配电价'!$E49)} | P45: =IF(SUM(D45:O45)=0,"0",AVERAGEIF(D45:O45,"<>0",D45:O45))
A46: 44 | B46: 山西 | C46: 政府性基金及附加 | D46: {=_xlfn.XLOOKUP($B$46,'分表5-政府性基金及附加'!$B$2：'分表5-政府性基金及附加'!$B$199,'分表5-政府性基金及附加'!$D$2：'分表5-政府性基金及附加'!$D$199)} | E46: {=_xlfn.XLOOKUP($B$46,'分表5-政府性基金及附加'!$B$2：'分表5-政府性基金及附加'!$B$199,'分表5-政府性基金及附加'!$D$2：'分表5-政府性基金及附加'!$D$199)} | F46: {=_xlfn.XLOOKUP($B$46,'分表5-政府性基金及附加'!$B$2：'分表5-政府性基金及附加'!$B$199,'分表5-政府性基金及附加'!$D$2：'分表5-政府性基金及附加'!$D$199)} | G46: {=_xlfn.XLOOKUP($B$46,'分表5-政府性基金及附加'!$B$2：'分表5-政府性基金及附加'!$B$199,'分表5-政府性基金及附加'!$D$2：'分表5-政府性基金及附加'!$D$199)} | H46: {=_xlfn.XLOOKUP($B$46,'分表5-政府性基金及附加'!$B$2：'分表5-政府性基金及附加'!$B$199,'分表5-政府性基金及附加'!$D$2：'分表5-政府性基金及附加'!$D$199)} | P46: =IF(SUM(D46:O46)=0,"0",AVERAGEIF(D46:O46,"<>0",D46:O46))
A47: 45 | B47: 山西 | C47: 系统运行费折价 | D47: ='分表3-2026系统运行费'!BQ2 | E47: ='分表3-2026系统运行费'!BR2 | F47: ='分表3-2026系统运行费'!BS2 | G47: ='分表3-2026系统运行费'!BT2 | H47: ='分表3-2026系统运行费'!BU2 | P47: =IF(SUM(D47:O47)=0,"0",AVERAGEIF(D47:O47,"<>0",D47:O47))
A48: 46 | B48: 山西 | C48: 综合平段电价--电网代购 | D48: =IF(D45="/","/",SUM(D43:D47)) | E48: =IF(E45="/","/",SUM(E43:E47)) | F48: =IF(F45="/","/",SUM(F43:F47)) | G48: =IF(G45="/","/",SUM(G43:G47)) | H48: =IF(H45="/","/",SUM(H43:H47)) | P48: =IF(SUM(D48:O48)=0,"0",AVERAGEIF(D48:O48,"<>0",D48:O48))
A49: 47 | B49: 山西 | C49: 入市交易购电价格 | D49: ='分表7-2026交易价格'!D7 | E49: ='分表7-2026交易价格'!E7 | F49: ='分表7-2026交易价格'!F7 | G49: ='分表7-2026交易价格'!G7 | H49: ='分表7-2026交易价格'!H7 | P49: =IF(SUM(D49:O49)=0,"0",AVERAGEIF(D49:O49,"<>0",D49:O49))
A50: 48 | B50: 山西 | C50: 综合平段电价--入市交易 | D50: =IF(D45="/","/",IF(D49>0,D49+SUM(D44:D47),"/")) | E50: =IF(E45="/","/",IF(E49>0,E49+SUM(E44:E47),"/")) | F50: =IF(F45="/","/",IF(F49>0,F49+SUM(F44:F47),"/")) | G50: =IF(G45="/","/",IF(G49>0,G49+SUM(G44:G47),"/")) | H50: =IF(H45="/","/",IF(H49>0,H49+SUM(H44:H47),"/")) | P50: =IF(SUM(D50:O50)=0,"0",AVERAGEIF(D50:O50,"<>0",D50:O50))
A51: 49 | B51: 蒙西 | C51: 代理购电价格 | D51: ='分表1-2026电网代购价'!D21 | E51: ='分表1-2026电网代购价'!E21 | F51: ='分表1-2026电网代购价'!F21 | G51: ='分表1-2026电网代购价'!G21 | H51: ='分表1-2026电网代购价'!H21 | P51: =IF(SUM(D51:O51)=0,"0",AVERAGEIF(D51:O51,"<>0",D51:O51))
A52: 50 | B52: 蒙西 | C52: 上网环节线损电价 | D52: ='分表2-2026上网环节线损'!C8 | E52: ='分表2-2026上网环节线损'!D8 | F52: ='分表2-2026上网环节线损'!E8 | G52: ='分表2-2026上网环节线损'!F8 | H52: ='分表2-2026上网环节线损'!G8 | P52: =IF(SUM(D52:O52)=0,"0",AVERAGEIF(D52:O52,"<>0",D52:O52))
A53: 51 | B53: 蒙西 | C53: 电度输配电价 | D53: {=_xlfn.XLOOKUP($C$1,'分表4-电度输配电价'!$C50：'分表4-电度输配电价'!$C57&'分表4-电度输配电价'!$D50：'分表4-电度输配电价'!$D57,'分表4-电度输配电价'!$E50：'分表4-电度输配电价'!$E57)} | E53: {=_xlfn.XLOOKUP($C$1,'分表4-电度输配电价'!$C50：'分表4-电度输配电价'!$C57&'分表4-电度输配电价'!$D50：'分表4-电度输配电价'!$D57,'分表4-电度输配电价'!$E50：'分表4-电度输配电价'!$E57)} | F53: {=_xlfn.XLOOKUP($C$1,'分表4-电度输配电价'!$C50：'分表4-电度输配电价'!$C57&'分表4-电度输配电价'!$D50：'分表4-电度输配电价'!$D57,'分表4-电度输配电价'!$E50：'分表4-电度输配电价'!$E57)} | G53: {=_xlfn.XLOOKUP($C$1,'分表4-电度输配电价'!$C50：'分表4-电度输配电价'!$C57&'分表4-电度输配电价'!$D50：'分表4-电度输配电价'!$D57,'分表4-电度输配电价'!$E50：'分表4-电度输配电价'!$E57)} | H53: {=_xlfn.XLOOKUP($C$1,'分表4-电度输配电价'!$C50：'分表4-电度输配电价'!$C57&'分表4-电度输配电价'!$D50：'分表4-电度输配电价'!$D57,'分表4-电度输配电价'!$E50：'分表4-电度输配电价'!$E57)} | P53: =IF(SUM(D53:O53)=0,"0",AVERAGEIF(D53:O53,"<>0",D53:O53))
A54: 52 | B54: 蒙西 | C54: 政府性基金及附加 | D54: {=_xlfn.XLOOKUP($B$54,'分表5-政府性基金及附加'!$B$2：'分表5-政府性基金及附加'!$B$199,'分表5-政府性基金及附加'!$D$2：'分表5-政府性基金及附加'!$D$199)} | E54: {=_xlfn.XLOOKUP($B$54,'分表5-政府性基金及附加'!$B$2：'分表5-政府性基金及附加'!$B$199,'分表5-政府性基金及附加'!$D$2：'分表5-政府性基金及附加'!$D$199)} | F54: {=_xlfn.XLOOKUP($B$54,'分表5-政府性基金及附加'!$B$2：'分表5-政府性基金及附加'!$B$199,'分表5-政府性基金及附加'!$D$2：'分表5-政府性基金及附加'!$D$199)} | G54: {=_xlfn.XLOOKUP($B$54,'分表5-政府性基金及附加'!$B$2：'分表5-政府性基金及附加'!$B$199,'分表5-政府性基金及附加'!$D$2：'分表5-政府性基金及附加'!$D$199)} | H54: {=_xlfn.XLOOKUP($B$54,'分表5-政府性基金及附加'!$B$2：'分表5-政府性基金及附加'!$B$199,'分表5-政府性基金及附加'!$D$2：'分表5-政府性基金及附加'!$D$199)} | P54: =IF(SUM(D54:O54)=0,"0",AVERAGEIF(D54:O54,"<>0",D54:O54))
A55: 53 | B55: 蒙西 | C55: 系统运行费折价 | D55: ='分表3-2026系统运行费'!CD2 | E55: ='分表3-2026系统运行费'!CE2 | F55: ='分表3-2026系统运行费'!CF2 | G55: ='分表3-2026系统运行费'!CG2 | H55: ='分表3-2026系统运行费'!CH2 | P55: =IF(SUM(D55:O55)=0,"0",AVERAGEIF(D55:O55,"<>0",D55:O55))
A56: 54 | B56: 蒙西 | C56: 综合平段电价--电网代购 | D56: =IF(D53="/","/",SUM(D51:D55)) | E56: =IF(E53="/","/",SUM(E51:E55)) | F56: =IF(F53="/","/",SUM(F51:F55)) | G56: =IF(G53="/","/",SUM(G51:G55)) | H56: =IF(H53="/","/",SUM(H51:H55)) | P56: =IF(SUM(D56:O56)=0,"0",AVERAGEIF(D56:O56,"<>0",D56:O56))
A57: 55 | B57: 蒙西 | C57: 入市交易购电价格 | D57: ='分表7-2026交易价格'!D8 | E57: ='分表7-2026交易价格'!E8 | F57: ='分表7-2026交易价格'!F8 | G57: ='分表7-2026交易价格'!G8 | H57: ='分表7-2026交易价格'!H8 | P57: =IF(SUM(D57:O57)=0,"0",AVERAGEIF(D57:O57,"<>0",D57:O57))
A58: 56 | B58: 蒙西 | C58: 综合平段电价--入市交易 | D58: =IF(D53="/","/",IF(D57>0,D57+SUM(D52:D55),"/")) | E58: =IF(E53="/","/",IF(E57>0,E57+SUM(E52:E55),"/")) | F58: =IF(F53="/","/",IF(F57>0,F57+SUM(F52:F55),"/")) | G58: =IF(G53="/","/",IF(G57>0,G57+SUM(G52:G55),"/")) | H58: =IF(H53="/","/",IF(H57>0,H57+SUM(H52:H55),"/")) | P58: =IF(SUM(D58:O58)=0,"0",AVERAGEIF(D58:O58,"<>0",D58:O58))
A59: 57 | B59: 上海 | C59: 代理购电价格 | D59: ='分表1-2026电网代购价'!D24 | E59: ='分表1-2026电网代购价'!E24 | F59: ='分表1-2026电网代购价'!F24 | G59: ='分表1-2026电网代购价'!G24 | H59: ='分表1-2026电网代购价'!H24 | P59: =IF(SUM(D59:O59)=0,"0",AVERAGEIF(D59:O59,"<>0",D59:O59))
A60: 58 | B60: 上海 | C60: 上网环节线损电价 | D60: ='分表2-2026上网环节线损'!C9 | E60: ='分表2-2026上网环节线损'!D9 | F60: ='分表2-2026上网环节线损'!E9 | G60: ='分表2-2026上网环节线损'!F9 | H60: ='分表2-2026上网环节线损'!G9 | P60: =IF(SUM(D60:O60)=0,"0",AVERAGEIF(D60:O60,"<>0",D60:O60))
A61: 59 | B61: 上海 | C61: 电度输配电价 | D61: {=_xlfn.XLOOKUP($C$1,'分表4-电度输配电价'!$C58：'分表4-电度输配电价'!$C65&'分表4-电度输配电价'!$D58：'分表4-电度输配电价'!$D65,'分表4-电度输配电价'!$E58：'分表4-电度输配电价'!$E65)} | E61: {=_xlfn.XLOOKUP($C$1,'分表4-电度输配电价'!$C58：'分表4-电度输配电价'!$C65&'分表4-电度输配电价'!$D58：'分表4-电度输配电价'!$D65,'分表4-电度输配电价'!$E58：'分表4-电度输配电价'!$E65)} | F61: {=_xlfn.XLOOKUP($C$1,'分表4-电度输配电价'!$C58：'分表4-电度输配电价'!$C65&'分表4-电度输配电价'!$D58：'分表4-电度输配电价'!$D65,'分表4-电度输配电价'!$E58：'分表4-电度输配电价'!$E65)} | G61: {=_xlfn.XLOOKUP($C$1,'分表4-电度输配电价'!$C58：'分表4-电度输配电价'!$C65&'分表4-电度输配电价'!$D58：'分表4-电度输配电价'!$D65,'分表4-电度输配电价'!$E58：'分表4-电度输配电价'!$E65)} | H61: {=_xlfn.XLOOKUP($C$1,'分表4-电度输配电价'!$C58：'分表4-电度输配电价'!$C65&'分表4-电度输配电价'!$D58：'分表4-电度输配电价'!$D65,'分表4-电度输配电价'!$E58：'分表4-电度输配电价'!$E65)} | P61: =IF(SUM(D61:O61)=0,"0",AVERAGEIF(D61:O61,"<>0",D61:O61))
A62: 60 | B62: 上海 | C62: 政府性基金及附加 | D62: {=_xlfn.XLOOKUP($B$62,'分表5-政府性基金及附加'!$B$2：'分表5-政府性基金及附加'!$B$199,'分表5-政府性基金及附加'!$D$2：'分表5-政府性基金及附加'!$D$199)} | E62: {=_xlfn.XLOOKUP($B$62,'分表5-政府性基金及附加'!$B$2：'分表5-政府性基金及附加'!$B$199,'分表5-政府性基金及附加'!$D$2：'分表5-政府性基金及附加'!$D$199)} | F62: {=_xlfn.XLOOKUP($B$62,'分表5-政府性基金及附加'!$B$2：'分表5-政府性基金及附加'!$B$199,'分表5-政府性基金及附加'!$D$2：'分表5-政府性基金及附加'!$D$199)} | G62: {=_xlfn.XLOOKUP($B$62,'分表5-政府性基金及附加'!$B$2：'分表5-政府性基金及附加'!$B$199,'分表5-政府性基金及附加'!$D$2：'分表5-政府性基金及附加'!$D$199)} | H62: {=_xlfn.XLOOKUP($B$62,'分表5-政府性基金及附加'!$B$2：'分表5-政府性基金及附加'!$B$199,'分表5-政府性基金及附加'!$D$2：'分表5-政府性基金及附加'!$D$199)} | P62: =IF(SUM(D62:O62)=0,"0",AVERAGEIF(D62:O62,"<>0",D62:O62))
A63: 61 | B63: 上海 | C63: 系统运行费折价 | D63: ='分表3-2026系统运行费'!CQ2 | E63: ='分表3-2026系统运行费'!CR2 | F63: ='分表3-2026系统运行费'!CS2 | G63: ='分表3-2026系统运行费'!CT2 | H63: ='分表3-2026系统运行费'!CU2 | P63: =IF(SUM(D63:O63)=0,"0",AVERAGEIF(D63:O63,"<>0",D63:O63))
A64: 62 | B64: 上海 | C64: 综合平段电价--电网代购 | D64: =IF(D61="/","/",SUM(D59:D63)) | E64: =IF(E61="/","/",SUM(E59:E63)) | F64: =IF(F61="/","/",SUM(F59:F63)) | G64: =IF(G61="/","/",SUM(G59:G63)) | H64: =IF(H61="/","/",SUM(H59:H63)) | P64: =IF(SUM(D64:O64)=0,"0",AVERAGEIF(D64:O64,"<>0",D64:O64))
A65: 63 | B65: 上海 | C65: 入市交易购电价格 | D65: ='分表7-2026交易价格'!D9 | E65: ='分表7-2026交易价格'!E9 | F65: ='分表7-2026交易价格'!F9 | G65: ='分表7-2026交易价格'!G9 | H65: ='分表7-2026交易价格'!H9 | P65: =IF(SUM(D65:O65)=0,"0",AVERAGEIF(D65:O65,"<>0",D65:O65))
A66: 64 | B66: 上海 | C66: 综合平段电价--入市交易 | D66: =IF(D61="/","/",IF(D65>0,D65+SUM(D60:D63),"/")) | E66: =IF(E61="/","/",IF(E65>0,E65+SUM(E60:E63),"/")) | F66: =IF(F61="/","/",IF(F65>0,F65+SUM(F60:F63),"/")) | G66: =IF(G61="/","/",IF(G65>0,G65+SUM(G60:G63),"/")) | H66: =IF(H61="/","/",IF(H65>0,H65+SUM(H60:H63),"/")) | P66: =IF(SUM(D66:O66)=0,"0",AVERAGEIF(D66:O66,"<>0",D66:O66))
A67: 65 | B67: 江苏 | C67: 代理购电价格 | D67: ='分表1-2026电网代购价'!D27 | E67: ='分表1-2026电网代购价'!E27 | F67: ='分表1-2026电网代购价'!F27 | G67: ='分表1-2026电网代购价'!G27 | H67: ='分表1-2026电网代购价'!H27 | P67: =IF(SUM(D67:O67)=0,"0",AVERAGEIF(D67:O67,"<>0",D67:O67))
A68: 66 | B68: 江苏 | C68: 上网环节线损电价 | D68: ='分表2-2026上网环节线损'!C10 | E68: ='分表2-2026上网环节线损'!D10 | F68: ='分表2-2026上网环节线损'!E10 | G68: ='分表2-2026上网环节线损'!F10 | H68: ='分表2-2026上网环节线损'!G10 | P68: =IF(SUM(D68:O68)=0,"0",AVERAGEIF(D68:O68,"<>0",D68:O68))
A69: 67 | B69: 江苏 | C69: 电度输配电价 | D69: {=_xlfn.XLOOKUP($C$1,'分表4-电度输配电价'!$C66：'分表4-电度输配电价'!$C73&'分表4-电度输配电价'!$D66：'分表4-电度输配电价'!$D73,'分表4-电度输配电价'!$E66：'分表4-电度输配电价'!$E73)} | E69: {=_xlfn.XLOOKUP($C$1,'分表4-电度输配电价'!$C66：'分表4-电度输配电价'!$C73&'分表4-电度输配电价'!$D66：'分表4-电度输配电价'!$D73,'分表4-电度输配电价'!$E66：'分表4-电度输配电价'!$E73)} | F69: {=_xlfn.XLOOKUP($C$1,'分表4-电度输配电价'!$C66：'分表4-电度输配电价'!$C73&'分表4-电度输配电价'!$D66：'分表4-电度输配电价'!$D73,'分表4-电度输配电价'!$E66：'分表4-电度输配电价'!$E73)} | G69: {=_xlfn.XLOOKUP($C$1,'分表4-电度输配电价'!$C66：'分表4-电度输配电价'!$C73&'分表4-电度输配电价'!$D66：'分表4-电度输配电价'!$D73,'分表4-电度输配电价'!$E66：'分表4-电度输配电价'!$E73)} | H69: {=_xlfn.XLOOKUP($C$1,'分表4-电度输配电价'!$C66：'分表4-电度输配电价'!$C73&'分表4-电度输配电价'!$D66：'分表4-电度输配电价'!$D73,'分表4-电度输配电价'!$E66：'分表4-电度输配电价'!$E73)} | P69: =IF(SUM(D69:O69)=0,"0",AVERAGEIF(D69:O69,"<>0",D69:O69))
A70: 68 | B70: 江苏 | C70: 政府性基金及附加 | D70: {=_xlfn.XLOOKUP($B$70,'分表5-政府性基金及附加'!$B$2：'分表5-政府性基金及附加'!$B$199,'分表5-政府性基金及附加'!$D$2：'分表5-政府性基金及附加'!$D$199)} | E70: {=_xlfn.XLOOKUP($B$70,'分表5-政府性基金及附加'!$B$2：'分表5-政府性基金及附加'!$B$199,'分表5-政府性基金及附加'!$D$2：'分表5-政府性基金及附加'!$D$199)} | F70: {=_xlfn.XLOOKUP($B$70,'分表5-政府性基金及附加'!$B$2：'分表5-政府性基金及附加'!$B$199,'分表5-政府性基金及附加'!$D$2：'分表5-政府性基金及附加'!$D$199)} | G70: {=_xlfn.XLOOKUP($B$70,'分表5-政府性基金及附加'!$B$2：'分表5-政府性基金及附加'!$B$199,'分表5-政府性基金及附加'!$D$2：'分表5-政府性基金及附加'!$D$199)} | H70: {=_xlfn.XLOOKUP($B$70,'分表5-政府性基金及附加'!$B$2：'分表5-政府性基金及附加'!$B$199,'分表5-政府性基金及附加'!$D$2：'分表5-政府性基金及附加'!$D$199)} | P70: =IF(SUM(D70:O70)=0,"0",AVERAGEIF(D70:O70,"<>0",D70:O70))
A71: 69 | B71: 江苏 | C71: 系统运行费折价 | D71: ='分表3-2026系统运行费'!DD2 | E71: ='分表3-2026系统运行费'!DE2 | F71: ='分表3-2026系统运行费'!DF2 | G71: ='分表3-2026系统运行费'!DG2 | H71: ='分表3-2026系统运行费'!DH2 | P71: =IF(SUM(D71:O71)=0,"0",AVERAGEIF(D71:O71,"<>0",D71:O71))
A72: 70 | B72: 江苏 | C72: 综合平段电价--电网代购 | D72: =IF(D69="/","/",SUM(D67:D71)) | E72: =IF(E69="/","/",SUM(E67:E71)) | F72: =IF(F69="/","/",SUM(F67:F71)) | G72: =IF(G69="/","/",SUM(G67:G71)) | H72: =IF(H69="/","/",SUM(H67:H71)) | P72: =IF(SUM(D72:O72)=0,"0",AVERAGEIF(D72:O72,"<>0",D72:O72))
A73: 71 | B73: 江苏 | C73: 入市交易购电价格 | D73: ='分表7-2026交易价格'!D10 | E73: ='分表7-2026交易价格'!E10 | F73: ='分表7-2026交易价格'!F10 | G73: ='分表7-2026交易价格'!G10 | H73: ='分表7-2026交易价格'!H10 | P73: =IF(SUM(D73:O73)=0,"0",AVERAGEIF(D73:O73,"<>0",D73:O73))
A74: 72 | B74: 江苏 | C74: 综合平段电价--入市交易 | D74: =IF(D69="/","/",IF(D73>0,D73+SUM(D68:D71),"/")) | E74: =IF(E69="/","/",IF(E73>0,E73+SUM(E68:E71),"/")) | F74: =IF(F69="/","/",IF(F73>0,F73+SUM(F68:F71),"/")) | G74: =IF(G69="/","/",IF(G73>0,G73+SUM(G68:G71),"/")) | H74: =IF(H69="/","/",IF(H73>0,H73+SUM(H68:H71),"/")) | P74: =IF(SUM(D74:O74)=0,"0",AVERAGEIF(D74:O74,"<>0",D74:O74))
A75: 73 | B75: 浙江 | C75: 代理购电价格 | D75: ='分表1-2026电网代购价'!D30 | E75: ='分表1-2026电网代购价'!E30 | F75: ='分表1-2026电网代购价'!F30 | G75: ='分表1-2026电网代购价'!G30 | H75: ='分表1-2026电网代购价'!H30 | P75: =IF(SUM(D75:O75)=0,"0",AVERAGEIF(D75:O75,"<>0",D75:O75))
A76: 74 | B76: 浙江 | C76: 上网环节线损电价 | D76: ='分表2-2026上网环节线损'!C11 | E76: ='分表2-2026上网环节线损'!D11 | F76: ='分表2-2026上网环节线损'!E11 | G76: ='分表2-2026上网环节线损'!F11 | H76: ='分表2-2026上网环节线损'!G11 | P76: =IF(SUM(D76:O76)=0,"0",AVERAGEIF(D76:O76,"<>0",D76:O76))
A77: 75 | B77: 浙江 | C77: 电度输配电价 | D77: {=_xlfn.XLOOKUP($C$1,'分表4-电度输配电价'!$C74：'分表4-电度输配电价'!$C81&'分表4-电度输配电价'!$D74：'分表4-电度输配电价'!$D81,'分表4-电度输配电价'!$E74：'分表4-电度输配电价'!$E81)} | E77: {=_xlfn.XLOOKUP($C$1,'分表4-电度输配电价'!$C74：'分表4-电度输配电价'!$C81&'分表4-电度输配电价'!$D74：'分表4-电度输配电价'!$D81,'分表4-电度输配电价'!$E74：'分表4-电度输配电价'!$E81)} | F77: {=_xlfn.XLOOKUP($C$1,'分表4-电度输配电价'!$C74：'分表4-电度输配电价'!$C81&'分表4-电度输配电价'!$D74：'分表4-电度输配电价'!$D81,'分表4-电度输配电价'!$E74：'分表4-电度输配电价'!$E81)} | G77: {=_xlfn.XLOOKUP($C$1,'分表4-电度输配电价'!$C74：'分表4-电度输配电价'!$C81&'分表4-电度输配电价'!$D74：'分表4-电度输配电价'!$D81,'分表4-电度输配电价'!$E74：'分表4-电度输配电价'!$E81)} | H77: {=_xlfn.XLOOKUP($C$1,'分表4-电度输配电价'!$C74：'分表4-电度输配电价'!$C81&'分表4-电度输配电价'!$D74：'分表4-电度输配电价'!$D81,'分表4-电度输配电价'!$E74：'分表4-电度输配电价'!$E81)} | P77: =IF(SUM(D77:O77)=0,"0",AVERAGEIF(D77:O77,"<>0",D77:O77))
A78: 76 | B78: 浙江 | C78: 政府性基金及附加 | D78: {=_xlfn.XLOOKUP($B$78,'分表5-政府性基金及附加'!$B$2：'分表5-政府性基金及附加'!$B$199,'分表5-政府性基金及附加'!$D$2：'分表5-政府性基金及附加'!$D$199)} | E78: {=_xlfn.XLOOKUP($B$78,'分表5-政府性基金及附加'!$B$2：'分表5-政府性基金及附加'!$B$199,'分表5-政府性基金及附加'!$D$2：'分表5-政府性基金及附加'!$D$199)} | F78: {=_xlfn.XLOOKUP($B$78,'分表5-政府性基金及附加'!$B$2：'分表5-政府性基金及附加'!$B$199,'分表5-政府性基金及附加'!$D$2：'分表5-政府性基金及附加'!$D$199)} | G78: {=_xlfn.XLOOKUP($B$78,'分表5-政府性基金及附加'!$B$2：'分表5-政府性基金及附加'!$B$199,'分表5-政府性基金及附加'!$D$2：'分表5-政府性基金及附加'!$D$199)} | H78: {=_xlfn.XLOOKUP($B$78,'分表5-政府性基金及附加'!$B$2：'分表5-政府性基金及附加'!$B$199,'分表5-政府性基金及附加'!$D$2：'分表5-政府性基金及附加'!$D$199)} | P78: =IF(SUM(D78:O78)=0,"0",AVERAGEIF(D78:O78,"<>0",D78:O78))
A79: 77 | B79: 浙江 | C79: 系统运行费折价 | D79: ='分表3-2026系统运行费'!DQ2 | E79: ='分表3-2026系统运行费'!DR2 | F79: ='分表3-2026系统运行费'!DS2 | G79: ='分表3-2026系统运行费'!DT2 | H79: ='分表3-2026系统运行费'!DU2 | P79: =IF(SUM(D79:O79)=0,"0",AVERAGEIF(D79:O79,"<>0",D79:O79))
A80: 78 | B80: 浙江 | C80: 综合平段电价--电网代购 | D80: =IF(D77="/","/",SUM(D75:D79)) | E80: =IF(E77="/","/",SUM(E75:E79)) | F80: =IF(F77="/","/",SUM(F75:F79)) | G80: =IF(G77="/","/",SUM(G75:G79)) | H80: =IF(H77="/","/",SUM(H75:H79)) | P80: =IF(SUM(D80:O80)=0,"0",AVERAGEIF(D80:O80,"<>0",D80:O80))
A81: 79 | B81: 浙江 | C81: 入市交易购电价格 | D81: ='分表7-2026交易价格'!D11 | E81: ='分表7-2026交易价格'!E11 | F81: ='分表7-2026交易价格'!F11 | G81: ='分表7-2026交易价格'!G11 | H81: ='分表7-2026交易价格'!H11 | P81: =IF(SUM(D81:O81)=0,"0",AVERAGEIF(D81:O81,"<>0",D81:O81))
A82: 80 | B82: 浙江 | C82: 综合平段电价--入市交易 | D82: =IF(D77="/","/",IF(D81>0,D81+SUM(D76:D79),"/")) | E82: =IF(E77="/","/",IF(E81>0,E81+SUM(E76:E79),"/")) | F82: =IF(F77="/","/",IF(F81>0,F81+SUM(F76:F79),"/")) | G82: =IF(G77="/","/",IF(G81>0,G81+SUM(G76:G79),"/")) | H82: =IF(H77="/","/",IF(H81>0,H81+SUM(H76:H79),"/")) | P82: =IF(SUM(D82:O82)=0,"0",AVERAGEIF(D82:O82,"<>0",D82:O82))
A83: 81 | B83: 安徽 | C83: 代理购电价格 | D83: ='分表1-2026电网代购价'!D33 | E83: ='分表1-2026电网代购价'!E33 | F83: ='分表1-2026电网代购价'!F33 | G83: ='分表1-2026电网代购价'!G33 | H83: ='分表1-2026电网代购价'!H33 | P83: =IF(SUM(D83:O83)=0,"0",AVERAGEIF(D83:O83,"<>0",D83:O83))
A84: 82 | B84: 安徽 | C84: 上网环节线损电价 | D84: ='分表2-2026上网环节线损'!C12 | E84: ='分表2-2026上网环节线损'!D12 | F84: ='分表2-2026上网环节线损'!E12 | G84: ='分表2-2026上网环节线损'!F12 | H84: ='分表2-2026上网环节线损'!G12 | P84: =IF(SUM(D84:O84)=0,"0",AVERAGEIF(D84:O84,"<>0",D84:O84))
A85: 83 | B85: 安徽 | C85: 电度输配电价 | D85: {=_xlfn.XLOOKUP($C$1,'分表4-电度输配电价'!$C82：'分表4-电度输配电价'!$C89&'分表4-电度输配电价'!$D82：'分表4-电度输配电价'!$D89,'分表4-电度输配电价'!$E82：'分表4-电度输配电价'!$E89)} | E85: {=_xlfn.XLOOKUP($C$1,'分表4-电度输配电价'!$C82：'分表4-电度输配电价'!$C89&'分表4-电度输配电价'!$D82：'分表4-电度输配电价'!$D89,'分表4-电度输配电价'!$E82：'分表4-电度输配电价'!$E89)} | F85: {=_xlfn.XLOOKUP($C$1,'分表4-电度输配电价'!$C82：'分表4-电度输配电价'!$C89&'分表4-电度输配电价'!$D82：'分表4-电度输配电价'!$D89,'分表4-电度输配电价'!$E82：'分表4-电度输配电价'!$E89)} | G85: {=_xlfn.XLOOKUP($C$1,'分表4-电度输配电价'!$C82：'分表4-电度输配电价'!$C89&'分表4-电度输配电价'!$D82：'分表4-电度输配电价'!$D89,'分表4-电度输配电价'!$E82：'分表4-电度输配电价'!$E89)} | H85: {=_xlfn.XLOOKUP($C$1,'分表4-电度输配电价'!$C82：'分表4-电度输配电价'!$C89&'分表4-电度输配电价'!$D82：'分表4-电度输配电价'!$D89,'分表4-电度输配电价'!$E82：'分表4-电度输配电价'!$E89)} | P85: =IF(SUM(D85:O85)=0,"0",AVERAGEIF(D85:O85,"<>0",D85:O85))
A86: 84 | B86: 安徽 | C86: 政府性基金及附加 | D86: {=_xlfn.XLOOKUP($B$86,'分表5-政府性基金及附加'!$B$2：'分表5-政府性基金及附加'!$B$199,'分表5-政府性基金及附加'!$D$2：'分表5-政府性基金及附加'!$D$199)} | E86: {=_xlfn.XLOOKUP($B$86,'分表5-政府性基金及附加'!$B$2：'分表5-政府性基金及附加'!$B$199,'分表5-政府性基金及附加'!$D$2：'分表5-政府性基金及附加'!$D$199)} | F86: {=_xlfn.XLOOKUP($B$86,'分表5-政府性基金及附加'!$B$2：'分表5-政府性基金及附加'!$B$199,'分表5-政府性基金及附加'!$D$2：'分表5-政府性基金及附加'!$D$199)} | G86: {=_xlfn.XLOOKUP($B$86,'分表5-政府性基金及附加'!$B$2：'分表5-政府性基金及附加'!$B$199,'分表5-政府性基金及附加'!$D$2：'分表5-政府性基金及附加'!$D$199)} | H86: {=_xlfn.XLOOKUP($B$86,'分表5-政府性基金及附加'!$B$2：'分表5-政府性基金及附加'!$B$199,'分表5-政府性基金及附加'!$D$2：'分表5-政府性基金及附加'!$D$199)} | P86: =IF(SUM(D86:O86)=0,"0",AVERAGEIF(D86:O86,"<>0",D86:O86))
A87: 85 | B87: 安徽 | C87: 系统运行费折价 | D87: ='分表3-2026系统运行费'!ED2 | E87: ='分表3-2026系统运行费'!EE2 | F87: ='分表3-2026系统运行费'!EF2 | G87: ='分表3-2026系统运行费'!EG2 | H87: ='分表3-2026系统运行费'!EH2 | P87: =IF(SUM(D87:O87)=0,"0",AVERAGEIF(D87:O87,"<>0",D87:O87))
A88: 86 | B88: 安徽 | C88: 综合平段电价--电网代购 | D88: =IF(D85="/","/",SUM(D83:D87)) | E88: =IF(E85="/","/",SUM(E83:E87)) | F88: =IF(F85="/","/",SUM(F83:F87)) | G88: =IF(G85="/","/",SUM(G83:G87)) | H88: =IF(H85="/","/",SUM(H83:H87)) | P88: =IF(SUM(D88:O88)=0,"0",AVERAGEIF(D88:O88,"<>0",D88:O88))
A89: 87 | B89: 安徽 | C89: 入市交易购电价格 | D89: ='分表7-2026交易价格'!D12 | E89: ='分表7-2026交易价格'!E12 | F89: ='分表7-2026交易价格'!F12 | G89: ='分表7-2026交易价格'!G12 | H89: ='分表7-2026交易价格'!H12 | P89: =IF(SUM(D89:O89)=0,"0",AVERAGEIF(D89:O89,"<>0",D89:O89))
A90: 88 | B90: 安徽 | C90: 综合平段电价--入市交易 | D90: =IF(D85="/","/",IF(D89>0,D89+SUM(D84:D87),"/")) | E90: =IF(E85="/","/",IF(E89>0,E89+SUM(E84:E87),"/")) | F90: =IF(F85="/","/",IF(F89>0,F89+SUM(F84:F87),"/")) | G90: =IF(G85="/","/",IF(G89>0,G89+SUM(G84:G87),"/")) | H90: =IF(H85="/","/",IF(H89>0,H89+SUM(H84:H87),"/")) | P90: =IF(SUM(D90:O90)=0,"0",AVERAGEIF(D90:O90,"<>0",D90:O90))
A91: 89 | B91: 福建 | C91: 代理购电价格 | D91: ='分表1-2026电网代购价'!D36 | E91: ='分表1-2026电网代购价'!E36 | F91: ='分表1-2026电网代购价'!F36 | G91: ='分表1-2026电网代购价'!G36 | H91: ='分表1-2026电网代购价'!H36 | P91: =IF(SUM(D91:O91)=0,"0",AVERAGEIF(D91:O91,"<>0",D91:O91))
A92: 90 | B92: 福建 | C92: 上网环节线损电价 | D92: ='分表2-2026上网环节线损'!C13 | E92: ='分表2-2026上网环节线损'!D13 | F92: ='分表2-2026上网环节线损'!E13 | G92: ='分表2-2026上网环节线损'!F13 | H92: ='分表2-2026上网环节线损'!G13 | P92: =IF(SUM(D92:O92)=0,"0",AVERAGEIF(D92:O92,"<>0",D92:O92))
A93: 91 | B93: 福建 | C93: 电度输配电价 | D93: {=_xlfn.XLOOKUP($C$1,'分表4-电度输配电价'!$C90：'分表4-电度输配电价'!$C97&'分表4-电度输配电价'!$D90：'分表4-电度输配电价'!$D97,'分表4-电度输配电价'!$E90：'分表4-电度输配电价'!$E97)} | E93: {=_xlfn.XLOOKUP($C$1,'分表4-电度输配电价'!$C90：'分表4-电度输配电价'!$C97&'分表4-电度输配电价'!$D90：'分表4-电度输配电价'!$D97,'分表4-电度输配电价'!$E90：'分表4-电度输配电价'!$E97)} | F93: {=_xlfn.XLOOKUP($C$1,'分表4-电度输配电价'!$C90：'分表4-电度输配电价'!$C97&'分表4-电度输配电价'!$D90：'分表4-电度输配电价'!$D97,'分表4-电度输配电价'!$E90：'分表4-电度输配电价'!$E97)} | G93: {=_xlfn.XLOOKUP($C$1,'分表4-电度输配电价'!$C90：'分表4-电度输配电价'!$C97&'分表4-电度输配电价'!$D90：'分表4-电度输配电价'!$D97,'分表4-电度输配电价'!$E90：'分表4-电度输配电价'!$E97)} | H93: {=_xlfn.XLOOKUP($C$1,'分表4-电度输配电价'!$C90：'分表4-电度输配电价'!$C97&'分表4-电度输配电价'!$D90：'分表4-电度输配电价'!$D97,'分表4-电度输配电价'!$E90：'分表4-电度输配电价'!$E97)} | P93: =IF(SUM(D93:O93)=0,"0",AVERAGEIF(D93:O93,"<>0",D93:O93))
A94: 92 | B94: 福建 | C94: 政府性基金及附加 | D94: {=_xlfn.XLOOKUP($B$94,'分表5-政府性基金及附加'!$B$2：'分表5-政府性基金及附加'!$B$199,'分表5-政府性基金及附加'!$D$2：'分表5-政府性基金及附加'!$D$199)} | E94: {=_xlfn.XLOOKUP($B$94,'分表5-政府性基金及附加'!$B$2：'分表5-政府性基金及附加'!$B$199,'分表5-政府性基金及附加'!$D$2：'分表5-政府性基金及附加'!$D$199)} | F94: {=_xlfn.XLOOKUP($B$94,'分表5-政府性基金及附加'!$B$2：'分表5-政府性基金及附加'!$B$199,'分表5-政府性基金及附加'!$D$2：'分表5-政府性基金及附加'!$D$199)} | G94: {=_xlfn.XLOOKUP($B$94,'分表5-政府性基金及附加'!$B$2：'分表5-政府性基金及附加'!$B$199,'分表5-政府性基金及附加'!$D$2：'分表5-政府性基金及附加'!$D$199)} | H94: {=_xlfn.XLOOKUP($B$94,'分表5-政府性基金及附加'!$B$2：'分表5-政府性基金及附加'!$B$199,'分表5-政府性基金及附加'!$D$2：'分表5-政府性基金及附加'!$D$199)} | P94: =IF(SUM(D94:O94)=0,"0",AVERAGEIF(D94:O94,"<>0",D94:O94))
A95: 93 | B95: 福建 | C95: 系统运行费折价 | D95: ='分表3-2026系统运行费'!EQ2 | E95: ='分表3-2026系统运行费'!ER2 | F95: ='分表3-2026系统运行费'!ES2 | G95: ='分表3-2026系统运行费'!ET2 | H95: ='分表3-2026系统运行费'!EU2 | P95: =IF(SUM(D95:O95)=0,"0",AVERAGEIF(D95:O95,"<>0",D95:O95))
A96: 94 | B96: 福建 | C96: 综合平段电价--电网代购 | D96: =IF(D93="/","/",SUM(D91:D95)) | E96: =IF(E93="/","/",SUM(E91:E95)) | F96: =IF(F93="/","/",SUM(F91:F95)) | G96: =IF(G93="/","/",SUM(G91:G95)) | H96: =IF(H93="/","/",SUM(H91:H95)) | P96: =IF(SUM(D96:O96)=0,"0",AVERAGEIF(D96:O96,"<>0",D96:O96))
A97: 95 | B97: 福建 | C97: 入市交易购电价格 | D97: ='分表7-2026交易价格'!D13 | E97: ='分表7-2026交易价格'!E13 | F97: ='分表7-2026交易价格'!F13 | G97: ='分表7-2026交易价格'!G13 | H97: ='分表7-2026交易价格'!H13 | P97: =IF(SUM(D97:O97)=0,"0",AVERAGEIF(D97:O97,"<>0",D97:O97))
A98: 96 | B98: 福建 | C98: 综合平段电价--入市交易 | D98: =IF(D93="/","/",IF(D97>0,D97+SUM(D92:D95),"/")) | E98: =IF(E93="/","/",IF(E97>0,E97+SUM(E92:E95),"/")) | F98: =IF(F93="/","/",IF(F97>0,F97+SUM(F92:F95),"/")) | G98: =IF(G93="/","/",IF(G97>0,G97+SUM(G92:G95),"/")) | H98: =IF(H93="/","/",IF(H97>0,H97+SUM(H92:H95),"/")) | P98: =IF(SUM(D98:O98)=0,"0",AVERAGEIF(D98:O98,"<>0",D98:O98))
A99: 97 | B99: 湖北 | C99: 代理购电价格 | D99: ='分表1-2026电网代购价'!D39 | E99: ='分表1-2026电网代购价'!E39 | F99: ='分表1-2026电网代购价'!F39 | G99: ='分表1-2026电网代购价'!G39 | H99: ='分表1-2026电网代购价'!H39 | P99: =IF(SUM(D99:O99)=0,"0",AVERAGEIF(D99:O99,"<>0",D99:O99))
A100: 98 | B100: 湖北 | C100: 上网环节线损电价 | D100: ='分表2-2026上网环节线损'!C14 | E100: ='分表2-2026上网环节线损'!D14 | F100: ='分表2-2026上网环节线损'!E14 | G100: ='分表2-2026上网环节线损'!F14 | H100: ='分表2-2026上网环节线损'!G14 | P100: =IF(SUM(D100:O100)=0,"0",AVERAGEIF(D100:O100,"<>0",D100:O100))
...

Sheet 分表1-2026电网代购价
A1: 序号 | B1: 2026年代理购电价格 | C1: 省份 | D1: 1月 | E1: 2月 | F1: 3月 | G1: 4月 | H1: 5月 | I1: 6月 | J1: 7月 | K1: 8月 | L1: 9月 | M1: 10月 | N1: 11月 | O1: 12月 | P1: 年均 | Q1: 趋势图
A2: 1 | B2: 代理工商业购电价格 | C2: 北京 | D2: =D3+D4 | E2: =E3+E4 | F2: =F3+F4 | G2: =G3+G4 | H2: =H3+H4 | I2: =I3+I4 | J2: =J3+J4 | K2: =K3+K4 | ... O2: =O3+O4 | P2: =IF(SUM(D2:O2)=0,"0",AVERAGEIF(D2:O2,"<>0",D2:O2))
A3: 2 | B3: （1）当月平均购电价格 | C3: 北京 | D3: 0.387359 | E3: 0.386753 | F3: 0.388485 | G3: 0.389043 | H3: 0.387025 | P3: =IF(SUM(D3:O3)=0,"0",AVERAGEIF(D3:O3,"<>0",D3:O3))
A4: 3 | B4: （2）历史偏差电费折价 | C4: 北京 | D4: -0.004021 | E4: -0.005949 | F4: 0.000221 | G4: -0.005019 | H4: 0.011688 | P4: =IF(SUM(D4:O4)=0,"0",AVERAGEIF(D4:O4,"<>0",D4:O4))
A5: 4 | B5: 代理工商业购电价格 | C5: 天津 | D5: =D6+D7 | E5: =E6+E7 | F5: =F6+F7 | G5: =G6+G7 | H5: =H6+H7 | I5: =I6+I7 | J5: =J6+J7 | K5: =K6+K7 | ... O5: =O6+O7 | P5: =IF(SUM(D5:O5)=0,"0",AVERAGEIF(D5:O5,"<>0",D5:O5))
A6: 5 | B6: （1）当月平均购电价格 | C6: 天津 | D6: 0.383083 | E6: 0.382515 | F6: 0.382257 | G6: 0.386076 | H6: 0.383864 | P6: =IF(SUM(D6:O6)=0,"0",AVERAGEIF(D6:O6,"<>0",D6:O6))
A7: 6 | B7: （2）历史偏差电费折价 | C7: 天津 | D7: -0.016602 | E7: 0.012244 | F7: 0.011614 | G7: 0.008519 | H7: 0.004914 | P7: =IF(SUM(D7:O7)=0,"0",AVERAGEIF(D7:O7,"<>0",D7:O7))
A8: 7 | B8: 代理工商业购电价格 | C8: 河北南网 | D8: =D9+D10 | E8: =E9+E10 | F8: =F9+F10 | G8: =G9+G10 | H8: =H9+H10 | I8: =I9+I10 | J8: =J9+J10 | K8: =K9+K10 | ... O8: =O9+O10 | P8: =IF(SUM(D8:O8)=0,"0",AVERAGEIF(D8:O8,"<>0",D8:O8))
A9: 8 | B9: （1）当月平均购电价格 | C9: 河北南网 | D9: 0.40765 | E9: 0.403833 | F9: 0.39112 | G9: 0.383888 | H9: 0.377996 | P9: =IF(SUM(D9:O9)=0,"0",AVERAGEIF(D9:O9,"<>0",D9:O9))
A10: 9 | B10: （2）历史偏差电费折价 | C10: 河北南网 | D10: 0.016791 | E10: 0.007077 | F10: 0.006872 | G10: 0.010217 | H10: 0.024821 | P10: =IF(SUM(D10:O10)=0,"0",AVERAGEIF(D10:O10,"<>0",D10:O10))
A11: 10 | B11: 代理工商业购电价格 | C11: 冀北 | D11: =D12+D13 | E11: =E12+E13 | F11: =F12+F13 | G11: =G12+G13 | H11: =H12+H13 | I11: =I12+I13 | J11: =J12+J13 | K11: =K12+K13 | ... O11: =O12+O13 | P11: =IF(SUM(D11:O11)=0,"0",AVERAGEIF(D11:O11,"<>0",D11:O11))
A12: 11 | B12: （1）当月平均购电价格 | C12: 冀北 | D12: 0.394392 | E12: 0.393721 | F12: 0.394591 | G12: 0.39631 | H12: 0.396508 | P12: =IF(SUM(D12:O12)=0,"0",AVERAGEIF(D12:O12,"<>0",D12:O12))
A13: 12 | B13: （2）历史偏差电费折价 | C13: 冀北 | D13: -0.016618 | E13: -0.00083 | F13: 0.014418 | G13: 0.020997 | H13: 0.027731 | P13: =IF(SUM(D13:O13)=0,"0",AVERAGEIF(D13:O13,"<>0",D13:O13))
A14: 13 | B14: 代理工商业购电价格 | C14: 山东 | D14: =D15+D16+D17 | E14: =E15+E16+E17 | F14: =F15+F16+F17 | G14: =G15+G16+G17 | H14: =H15+H16+H17 | I14: =I15+I16+I17 | J14: =J15+J16+J17 | K14: =K15+K16+K17 | ... O14: =O15+O16+O17 | P14: =IF(SUM(D14:O14)=0,"0",AVERAGEIF(D14:O14,"<>0",D14:O14))
A15: 14 | B15: （1）当月平均购电价格 | C15: 山东 | D15: 0.3767 | E15: 0.3431 | F15: 0.3004 | G15: 0.2862 | H15: 0.2993 | P15: =IF(SUM(D15:O15)=0,"0",AVERAGEIF(D15:O15,"<>0",D15:O15))
A16: 15 | B16: （2）容量补偿电价 | C16: 山东 | D16: =0.0705 | E16: 0.0705 | F16: 0.0705 | G16: 0.0705 | H16: 0.0705 | P16: =IF(SUM(D16:O16)=0,"0",AVERAGEIF(D16:O16,"<>0",D16:O16))
A17: 16 | B17: （3）历史偏差电费折价 | C17: 山东 | D17: -0.0112 | E17: -0.0247 | F17: -0.0334 | G17: -0.0452 | H17: -0.016 | P17: =IF(SUM(D17:O17)=0,"0",AVERAGEIF(D17:O17,"<>0",D17:O17))
A18: 17 | B18: 代理工商业购电价格 | C18: 山西 | D18: =D19+D20 | E18: =E19+E20 | F18: =F19+F20 | G18: =G19+G20 | H18: =H19+H20 | I18: =I19+I20 | J18: =J19+J20 | K18: =K19+K20 | ... O18: =O19+O20 | P18: =IF(SUM(D18:O18)=0,"0",AVERAGEIF(D18:O18,"<>0",D18:O18))
A19: 18 | B19: （1）当月平均购电价格 | C19: 山西 | D19: 0.3041 | E19: 0.29125 | F19: 0.283758 | G19: 0.291545 | H19: 0.279485 | P19: =IF(SUM(D19:O19)=0,"0",AVERAGEIF(D19:O19,"<>0",D19:O19))
A20: 19 | B20: （2）历史偏差电费折价 | C20: 山西 | D20: -0.008232 | E20: 0.014146 | F20: 0.005836 | G20: 0.031408 | H20: -0.006153 | P20: =IF(SUM(D20:O20)=0,"0",AVERAGEIF(D20:O20,"<>0",D20:O20))
A21: 20 | B21: 代理工商业购电价格 | C21: 蒙西 | D21: =D22+D23 | E21: =E22+E23 | F21: =F22+F23 | G21: =G22+G23 | H21: =H22+H23 | I21: =I22+I23 | J21: =J22+J23 | K21: =K22+K23 | ... O21: =O22+O23 | P21: =IF(SUM(D21:O21)=0,"0",AVERAGEIF(D21:O21,"<>0",D21:O21))
A22: 21 | B22: （1）当月平均购电价格 | C22: 蒙西 | D22: 0.2863 | E22: 0.2815 | F22: 0.2834 | G22: 0.2788 | H22: 0.2732 | P22: =IF(SUM(D22:O22)=0,"0",AVERAGEIF(D22:O22,"<>0",D22:O22))
A23: 22 | B23: （2）历史偏差电费折价 | C23: 蒙西 | D23: 0.0339 | E23: 0.0442 | F23: 0.0294 | G23: 0.0429 | H23: 0.0562 | P23: =IF(SUM(D23:O23)=0,"0",AVERAGEIF(D23:O23,"<>0",D23:O23))
A24: 23 | B24: 代理工商业购电价格 | C24: 上海 | D24: =D25+D26 | E24: =E25+E26 | F24: =F25+F26 | G24: =G25+G26 | H24: =H25+H26 | I24: =I25+I26 | J24: =J25+J26 | K24: =K25+K26 | ... O24: =O25+O26 | P24: =IF(SUM(D24:O24)=0,"0",AVERAGEIF(D24:O24,"<>0",D24:O24))
A25: 24 | B25: （1）当月平均购电价格 | C25: 上海 | D25: 0.4773 | E25: 0.475275 | F25: 0.453585 | G25: 0.447219 | H25: 0.459464 | P25: =IF(SUM(D25:O25)=0,"0",AVERAGEIF(D25:O25,"<>0",D25:O25))
A26: 25 | B26: （2）历史偏差电费折价 | C26: 上海 | D26: -0.0448 | E26: -0.045009 | F26: -0.014508 | G26: -0.038055 | H26: -0.033421 | P26: =IF(SUM(D26:O26)=0,"0",AVERAGEIF(D26:O26,"<>0",D26:O26))
A27: 26 | B27: 代理工商业购电价格 | C27: 江苏 | D27: =D28+D29 | E27: =E28+E29 | F27: =F28+F29 | G27: =G28+G29 | H27: =H28+H29 | I27: =I28+I29 | J27: =J28+J29 | K27: =K28+K29 | ... O27: =O28+O29 | P27: =IF(SUM(D27:O27)=0,"0",AVERAGEIF(D27:O27,"<>0",D27:O27))
A28: 27 | B28: （1）当月平均购电价格 | C28: 江苏 | D28: 0.3959 | E28: 0.3153 | F28: 0.3698 | G28: 0.3746 | H28: 0.366 | P28: =IF(SUM(D28:O28)=0,"0",AVERAGEIF(D28:O28,"<>0",D28:O28))
A29: 28 | B29: （2）历史偏差电费折价 | C29: 江苏 | D29: -0.0022 | E29: -0.0051 | F29: -0.024 | G29: -0.0031 | H29: -0.0131 | P29: =IF(SUM(D29:O29)=0,"0",AVERAGEIF(D29:O29,"<>0",D29:O29))
A30: 29 | B30: 代理工商业购电价格 | C30: 浙江 | D30: =D31+D32 | E30: =E31+E32 | F30: =F31+F32 | G30: =G31+G32 | H30: =H31+H32 | I30: =I31+I32 | J30: =J31+J32 | K30: =K31+K32 | ... O30: =O31+O32 | P30: =IF(SUM(D30:O30)=0,"0",AVERAGEIF(D30:O30,"<>0",D30:O30))
A31: 30 | B31: （1）当月平均购电价格 | C31: 浙江 | D31: 0.369526 | E31: 0.348541 | F31: 0.367624 | G31: 0.353313 | H31: 0.363202 | P31: =IF(SUM(D31:O31)=0,"0",AVERAGEIF(D31:O31,"<>0",D31:O31))
A32: 31 | B32: （2）历史偏差电费折价 | C32: 浙江 | D32: 0.03906 | E32: 0.038114 | F32: 0.00433 | G32: -0.000655 | H32: 0.008665 | P32: =IF(SUM(D32:O32)=0,"0",AVERAGEIF(D32:O32,"<>0",D32:O32))
A33: 32 | B33: 代理工商业购电价格 | C33: 安徽 | D33: =D34+D35 | E33: =E34+E35 | F33: =F34+F35 | G33: =G34+G35 | H33: =H34+H35 | I33: =I34+I35 | J33: =J34+J35 | K33: =K34+K35 | ... O33: =O34+O35 | P33: =IF(SUM(D33:O33)=0,"0",AVERAGEIF(D33:O33,"<>0",D33:O33))
A34: 33 | B34: （1）当月平均购电价格 | C34: 安徽 | D34: 0.35766 | E34: 0.34625 | F34: 0.34747 | G34: 0.35533 | H34: 0.36176 | P34: =IF(SUM(D34:O34)=0,"0",AVERAGEIF(D34:O34,"<>0",D34:O34))
A35: 34 | B35: （2）历史偏差电费折价 | C35: 安徽 | D35: -0.0098 | E35: 0.0132 | F35: -0.0105 | G35: -0.0108 | H35: -0.0163 | P35: =IF(SUM(D35:O35)=0,"0",AVERAGEIF(D35:O35,"<>0",D35:O35))
A36: 35 | B36: 代理工商业购电价格 | C36: 福建 | D36: =D37+D38 | E36: =E37+E38 | F36: =F37+F38 | G36: =G37+G38 | H36: =H37+H38 | I36: =I37+I38 | J36: =J37+J38 | K36: =K37+K38 | ... O36: =O37+O38 | P36: =IF(SUM(D36:O36)=0,"0",AVERAGEIF(D36:O36,"<>0",D36:O36))
A37: 36 | B37: （1）当月平均购电价格 | C37: 福建 | D37: 0.369438 | E37: 0.368022 | F37: 0.366422 | G37: 0.370391 | H37: 0.371386 | P37: =IF(SUM(D37:O37)=0,"0",AVERAGEIF(D37:O37,"<>0",D37:O37))
A38: 37 | B38: （2）历史偏差电费折价 | C38: 福建 | D38: 0.017317 | E38: 0.011468 | F38: 0.00041 | G38: -0.004775 | H38: -0.000847 | P38: =IF(SUM(D38:O38)=0,"0",AVERAGEIF(D38:O38,"<>0",D38:O38))
A39: 38 | B39: 代理工商业购电价格 | C39: 湖北 | D39: =D40+D41 | E39: =E40+E41 | F39: =F40+F41 | G39: =G40+G41 | H39: =H40+H41 | I39: =I40+I41 | J39: =J40+J41 | K39: =K40+K41 | ... O39: =O40+O41 | P39: =IF(SUM(D39:O39)=0,"0",AVERAGEIF(D39:O39,"<>0",D39:O39))
A40: 39 | B40: （1）当月平均购电价格 | C40: 湖北 | D40: 0.38809 | E40: 0.39113 | F40: 0.39006 | G40: 0.40092 | H40: 0.39838 | P40: =IF(SUM(D40:O40)=0,"0",AVERAGEIF(D40:O40,"<>0",D40:O40))
A41: 40 | B41: （2）历史偏差电费折价 | C41: 湖北 | D41: -0.00362 | E41: -0.045968 | F41: -0.017103 | G41: -0.022064 | H41: -0.038309 | P41: =IF(SUM(D41:O41)=0,"0",AVERAGEIF(D41:O41,"<>0",D41:O41))
A42: 41 | B42: 代理工商业购电价格 | C42: 河南 | D42: =D43+D44 | E42: =E43+E44 | F42: =F43+F44 | G42: =G43+G44 | H42: =H43+H44 | I42: =I43+I44 | J42: =J43+J44 | K42: =K43+K44 | ... O42: =O43+O44 | P42: =IF(SUM(D42:O42)=0,"0",AVERAGEIF(D42:O42,"<>0",D42:O42))
A43: 42 | B43: （1）当月平均购电价格 | C43: 河南 | D43: 0.339764 | E43: 0.385249 | F43: 0.32802 | G43: 0.352904 | H43: 0.312235 | P43: =IF(SUM(D43:O43)=0,"0",AVERAGEIF(D43:O43,"<>0",D43:O43))
A44: 43 | B44: （2）历史偏差电费折价 | C44: 河南 | D44: 0 | E44: 0 | F44: 0.065153 | G44: 0 | H44: 0 | P44: =IF(SUM(D44:O44)=0,"0",AVERAGEIF(D44:O44,"<>0",D44:O44))
A45: 44 | B45: 代理工商业购电价格 | C45: 湖南 | D45: =D46+D47+D48 | E45: =E46+E47+E48 | F45: =F46+F47+F48 | G45: =G46+G47+G48 | H45: =H46+H47+H48 | I45: =I46+I47+I48 | J45: =J46+J47+J48 | K45: =K46+K47+K48 | ... O45: =O46+O47+O48 | P45: =IF(SUM(D45:O45)=0,"0",AVERAGEIF(D45:O45,"<>0",D45:O45))
A46: 45 | B46: （1）当月平均购电价格 | C46: 湖南 | D46: 0.441134 | E46: 0.446643 | F46: 0.432185 | G46: 0.372308 | H46: 0.257202 | P46: =IF(SUM(D46:O46)=0,"0",AVERAGEIF(D46:O46,"<>0",D46:O46))
A47: 46 | B47: （2）历史偏差电费折价 | C47: 湖南 | D47: 0.000243 | E47: -0.0221 | F47: -0.013595 | G47: -0.009898 | H47: -0.003878 | P47: =IF(SUM(D47:O47)=0,"0",AVERAGEIF(D47:O47,"<>0",D47:O47))
A48: 47 | B48: （3）购售价差资金折价 | C48: 湖南 | D48: -0.002024 | E48: 0.016991 | F48: 0.018957 | G48: 0.023455 | H48: 0.12163 | P48: =IF(SUM(D48:O48)=0,"0",AVERAGEIF(D48:O48,"<>0",D48:O48))
A49: 48 | B49: 代理工商业购电价格 | C49: 江西 | D49: =D50+D51 | E49: =E50+E51 | F49: =F50+F51 | G49: =G50+G51 | H49: =H50+H51 | I49: =I50+I51 | J49: =J50+J51 | K49: =K50+K51 | ... O49: =O50+O51 | P49: =IF(SUM(D49:O49)=0,"0",AVERAGEIF(D49:O49,"<>0",D49:O49))
A50: 49 | B50: （1）当月平均购电价格 | C50: 江西 | D50: 0.412549 | E50: 0.405745 | F50: 0.405745 | G50: 0.405745 | H50: 0.405744 | P50: =IF(SUM(D50:O50)=0,"0",AVERAGEIF(D50:O50,"<>0",D50:O50))
A51: 50 | B51: （2）历史偏差电费折价 | C51: 江西 | D51: -0.049708 | E51: 0.00887 | F51: 0.004438 | G51: 0.00634 | H51: -0.028745 | P51: =IF(SUM(D51:O51)=0,"0",AVERAGEIF(D51:O51,"<>0",D51:O51))
A52: 51 | B52: 代理工商业购电价格 | C52: 辽宁 | D52: =D53+D54 | E52: =E53+E54 | F52: =F53+F54 | G52: =G53+G54 | H52: =H53+H54 | I52: =I53+I54 | J52: =J53+J54 | K52: =K53+K54 | ... O52: =O53+O54 | P52: =IF(SUM(D52:O52)=0,"0",AVERAGEIF(D52:O52,"<>0",D52:O52))
A53: 52 | B53: （1）当月平均购电价格 | C53: 辽宁 | D53: 0.310821 | E53: 0.308022 | F53: 0.201213 | G53: 0.30071 | H53: 0.289215 | P53: =IF(SUM(D53:O53)=0,"0",AVERAGEIF(D53:O53,"<>0",D53:O53))
A54: 53 | B54: （2）历史偏差电费折价 | C54: 辽宁 | D54: 0.022026 | E54: 0.023194 | F54: -0.002117 | G54: -0.01256 | H54: -0.004584 | P54: =IF(SUM(D54:O54)=0,"0",AVERAGEIF(D54:O54,"<>0",D54:O54))
A55: 54 | B55: 代理工商业购电价格 | C55: 吉林 | D55: =D56+D57 | E55: =E56+E57 | F55: =F56+F57 | G55: =G56+G57 | H55: =H56+H57 | I55: =I56+I57 | J55: =J56+J57 | K55: =K56+K57 | ... O55: =O56+O57 | P55: =IF(SUM(D55:O55)=0,"0",AVERAGEIF(D55:O55,"<>0",D55:O55))
A56: 55 | B56: （1）当月平均购电价格 | C56: 吉林 | D56: 0.3442 | E56: 0.34408 | F56: 0.340756 | G56: 0.33911 | H56: 0.33754 | P56: =IF(SUM(D56:O56)=0,"0",AVERAGEIF(D56:O56,"<>0",D56:O56))
A57: 56 | B57: （2）历史偏差电费折价 | C57: 吉林 | D57: -0.00266 | E57: -0.007273 | F57: -0.000195 | G57: 0.002471 | H57: -0.005662 | P57: =IF(SUM(D57:O57)=0,"0",AVERAGEIF(D57:O57,"<>0",D57:O57))
A58: 57 | B58: 代理工商业购电价格 | C58: 黑龙江 | D58: =D59+D60 | E58: =E59+E60 | F58: =F59+F60 | G58: =G59+G60 | H58: =H59+H60 | I58: =I59+I60 | J58: =J59+J60 | K58: =K59+K60 | ... O58: =O59+O60 | P58: =IF(SUM(D58:O58)=0,"0",AVERAGEIF(D58:O58,"<>0",D58:O58))
A59: 58 | B59: （1）当月平均购电价格 | C59: 黑龙江 | D59: 0.2992 | E59: 0.2992 | F59: 0.2992 | G59: 0.2992 | H59: 0.2992 | P59: =IF(SUM(D59:O59)=0,"0",AVERAGEIF(D59:O59,"<>0",D59:O59))
A60: 59 | B60: （2）历史偏差电费折价 | C60: 黑龙江 | D60: 0.00851 | E60: 0 | F60: 0.007461 | G60: 0.009851 | H60: 0.001674 | P60: =IF(SUM(D60:O60)=0,"0",AVERAGEIF(D60:O60,"<>0",D60:O60))
A61: 60 | B61: 代理工商业购电价格 | C61: 蒙东 | D61: =D62+D63 | E61: =E62+E63 | F61: =F62+F63 | G61: =G62+G63 | H61: =H62+H63 | I61: =I62+I63 | J61: =J62+J63 | K61: =K62+K63 | ... O61: =O62+O63 | P61: =IF(SUM(D61:O61)=0,"0",AVERAGEIF(D61:O61,"<>0",D61:O61))
A62: 61 | B62: （1）当月平均购电价格 | C62: 蒙东 | D62: 0.28 | E62: 0.2031 | F62: 0.20196 | G62: 0.20107 | H62: 0.20477 | P62: =IF(SUM(D62:O62)=0,"0",AVERAGEIF(D62:O62,"<>0",D62:O62))
A63: 62 | B63: （2）历史偏差电费折价 | C63: 蒙东 | D63: -0.031546 | E63: -0.006799 | F63: -0.007013 | G63: -0.031193 | H63: -0.026499 | P63: =IF(SUM(D63:O63)=0,"0",AVERAGEIF(D63:O63,"<>0",D63:O63))
A64: 63 | B64: 代理工商业购电价格 | C64: 陕西 | D64: =D65+D66 | E64: =E65+E66 | F64: =F65+F66 | G64: =G65+G66 | H64: =H65+H66 | I64: =I65+I66 | J64: =J65+J66 | K64: =K65+K66 | ... O64: =O65+O66 | P64: =IF(SUM(D64:O64)=0,"0",AVERAGEIF(D64:O64,"<>0",D64:O64))
A65: 64 | B65: （1）当月平均购电价格 | C65: 陕西 | D65: 0.3257 | E65: 0.3267 | F65: 0.313 | G65: 0.2876 | H65: 0.2863 | P65: =IF(SUM(D65:O65)=0,"0",AVERAGEIF(D65:O65,"<>0",D65:O65))
A66: 65 | B66: （2）历史偏差电费折价 | C66: 陕西 | D66: 0.0556 | E66: 0.072 | F66: 0.0246 | G66: 0.0356 | H66: 0.0013 | P66: =IF(SUM(D66:O66)=0,"0",AVERAGEIF(D66:O66,"<>0",D66:O66))
A67: 66 | B67: 代理工商业购电价格 | C67: 甘肃 | D67: =D68+D69+D70 | E67: =E68+E69+E70 | F67: =F68+F69+F70 | G67: =G68+G69+G70 | H67: =H68+H69+H70 | I67: =I68+I69+I70 | J67: =J68+J69+J70 | K67: =K68+K69+K70 | ... O67: =O68+O69+O70 | P67: =IF(SUM(D67:O67)=0,"0",AVERAGEIF(D67:O67,"<>0",D67:O67))
A68: 67 | B68: （1）当月平均购电价格 | C68: 甘肃 | D68: 0.249928 | E68: 0.244792 | F68: 0.2537 | G68: 0.174365 | H68: 0.144591 | P68: =IF(SUM(D68:O68)=0,"0",AVERAGEIF(D68:O68,"<>0",D68:O68))
A69: 68 | B69: （2）历史偏差电费折价 | C69: 甘肃 | D69: 0.001971 | E69: 0.006559 | F69: 0.002782 | G69: 0.02013 | H69: 0.003041 | P69: =IF(SUM(D69:O69)=0,"0",AVERAGEIF(D69:O69,"<>0",D69:O69))
A70: 69 | B70: （3）双轨制资金折价 | C70: 甘肃 | D70: 0.024294 | E70: 0.039016 | F70: 0.005281 | G70: 0.007059 | H70: 0.012595 | P70: =IF(SUM(D70:O70)=0,"0",AVERAGEIF(D70:O70,"<>0",D70:O70))
A71: 70 | B71: 代理工商业购电价格 | C71: 青海 | D71: =D72+D73 | E71: =E72+E73 | F71: =F72+F73 | G71: =G72+G73 | H71: =H72+H73 | I71: =I72+I73 | J71: =J72+J73 | K71: =K72+K73 | ... O71: =O72+O73 | P71: =IF(SUM(D71:O71)=0,"0",AVERAGEIF(D71:O71,"<>0",D71:O71))
A72: 71 | B72: （1）当月平均购电价格 | C72: 青海 | D72: 0.301658 | E72: 0.290996 | F72: 0.317199 | G72: 0.260721 | H72: 0.233747 | P72: =IF(SUM(D72:O72)=0,"0",AVERAGEIF(D72:O72,"<>0",D72:O72))
A73: 72 | B73: （2）历史偏差电费折价 | C73: 青海 | D73: -0.042657 | E73: -0.008088 | F73: -0.033005 | G73: -0.036765 | H73: -0.013917 | P73: =IF(SUM(D73:O73)=0,"0",AVERAGEIF(D73:O73,"<>0",D73:O73))
A74: 73 | B74: 代理工商业购电价格 | C74: 宁夏 | D74: =D75+D76 | E74: =E75+E76 | F74: =F75+F76 | G74: =G75+G76 | H74: =H75+H76 | I74: =I75+I76 | J74: =J75+J76 | K74: =K75+K76 | ... O74: =O75+O76 | P74: =IF(SUM(D74:O74)=0,"0",AVERAGEIF(D74:O74,"<>0",D74:O74))
A75: 74 | B75: （1）当月平均购电价格 | C75: 宁夏 | D75: 0.2555 | E75: 0.2556 | F75: 0.2425 | G75: 0.2385 | H75: 0.2385 | P75: =IF(SUM(D75:O75)=0,"0",AVERAGEIF(D75:O75,"<>0",D75:O75))
A76: 75 | B76: （2）历史偏差电费折价 | C76: 宁夏 | D76: -0.0006 | E76: 0.0063 | F76: 0.0126 | G76: 0.023 | H76: 0.0295 | P76: =IF(SUM(D76:O76)=0,"0",AVERAGEIF(D76:O76,"<>0",D76:O76))
A77: 76 | B77: 代理工商业购电价格 | C77: 新疆 | D77: =D78+D79 | E77: =E78+E79 | F77: =F78+F79 | G77: =G78+G79 | H77: =H78+H79 | I77: =I78+I79 | J77: =J78+J79 | K77: =K78+K79 | ... O77: =O78+O79 | P77: =IF(SUM(D77:O77)=0,"0",AVERAGEIF(D77:O77,"<>0",D77:O77))
A78: 77 | B78: （1）当月平均购电价格 | C78: 新疆 | D78: 0.232171 | E78: 0.226804 | F78: 0.25589 | G78: 0.173007 | H78: 0.170183 | P78: =IF(SUM(D78:O78)=0,"0",AVERAGEIF(D78:O78,"<>0",D78:O78))
A79: 78 | B79: （2）历史偏差电费折价 | C79: 新疆 | D79: 0.003881 | E79: 0.054162 | F79: 0.066024 | G79: 0.055714 | H79: 0.067463 | P79: =IF(SUM(D79:O79)=0,"0",AVERAGEIF(D79:O79,"<>0",D79:O79))
A80: 79 | B80: 代理工商业购电价格 | C80: 重庆 | D80: =D81+D82 | E80: =E81+E82 | F80: =F81+F82 | G80: =G81+G82 | H80: =H81+H82 | I80: =I81+I82 | J80: =J81+J82 | K80: =K81+K82 | ... O80: =O81+O82 | P80: =IF(SUM(D80:O80)=0,"0",AVERAGEIF(D80:O80,"<>0",D80:O80))
A81: 80 | B81: （1）当月平均购电价格 | C81: 重庆 | D81: 0.431551 | E81: 0.453163 | F81: 0.437647 | G81: 0.444074 | H81: 0.437098 | P81: =IF(SUM(D81:O81)=0,"0",AVERAGEIF(D81:O81,"<>0",D81:O81))
A82: 81 | B82: （2）历史偏差电费折价 | C82: 重庆 | D82: 0.000368 | E82: 0.016366 | F82: 0.014095 | G82: -0.000796 | H82: 0.026401 | P82: =IF(SUM(D82:O82)=0,"0",AVERAGEIF(D82:O82,"<>0",D82:O82))
A83: 82 | B83: 代理工商业购电价格 | C83: 四川 | D83: =D84+D85 | E83: =E84+E85 | F83: =F84+F85 | G83: =G84+G85 | H83: =H84+H85 | I83: =I84+I85 | J83: =J84+J85 | K83: =K84+K85 | ... O83: =O84+O85 | P83: =IF(SUM(D83:O83)=0,"0",AVERAGEIF(D83:O83,"<>0",D83:O83))
A84: 83 | B84: （1）当月平均购电价格 | C84: 四川 | D84: 0.422843 | E84: 0.4126 | F84: 0.420719 | G84: 0.409366 | H84: 0.34624 | P84: =IF(SUM(D84:O84)=0,"0",AVERAGEIF(D84:O84,"<>0",D84:O84))
A85: 84 | B85: （2）历史偏差电费折价 | C85: 四川 | D85: 0 | E85: 0.001306 | F85: 0 | G85: -0.020501 | H85: -0.011064 | P85: =IF(SUM(D85:O85)=0,"0",AVERAGEIF(D85:O85,"<>0",D85:O85))
A86: 85 | B86: 代理工商业购电价格 | C86: 广东 | D86: =D87+D88 | E86: =E87+E88 | F86: =F87+F88 | G86: =G87+G88 | H86: =H87+H88 | I86: =I87+I88 | J86: =J87+J88 | K86: =K87+K88 | ... O86: =O87+O88 | P86: =IF(SUM(D86:O86)=0,"0",AVERAGEIF(D86:O86,"<>0",D86:O86))
A87: 86 | B87: （1）当月平均购电价格 | C87: 广东 | D87: 0.3687 | E87: 0.3745 | F87: 0.3827 | G87: 0.3808 | H87: 0.4249 | P87: =IF(SUM(D87:O87)=0,"0",AVERAGEIF(D87:O87,"<>0",D87:O87))
A88: 87 | B88: （2）历史偏差电费折价 | C88: 广东 | D88: 0.0102 | E88: 0.0383 | F88: 0.0351 | G88: 0.0235 | H88: 0.0208 | P88: =IF(SUM(D88:O88)=0,"0",AVERAGEIF(D88:O88,"<>0",D88:O88))
A89: 88 | B89: 代理工商业购电价格 | C89: 广西 | D89: =D90+D91 | E89: =E90+E91 | F89: =F90+F91 | G89: =G90+G91 | H89: =H90+H91 | I89: =I90+I91 | J89: =J90+J91 | K89: =K90+K91 | ... O89: =O90+O91 | P89: =IF(SUM(D89:O89)=0,"0",AVERAGEIF(D89:O89,"<>0",D89:O89))
A90: 89 | B90: （1）当月平均购电价格 | C90: 广西 | D90: 0.342563 | E90: 0.35865 | F90: 0.337625 | G90: 0.346905 | H90: 0.33699 | P90: =IF(SUM(D90:O90)=0,"0",AVERAGEIF(D90:O90,"<>0",D90:O90))
A91: 90 | B91: （2）历史偏差电费折价 | C91: 广西 | D91: 0.017614 | E91: 0.01984 | F91: -0.024239 | G91: -0.012229 | H91: -0.002929 | P91: =IF(SUM(D91:O91)=0,"0",AVERAGEIF(D91:O91,"<>0",D91:O91))
A92: 91 | B92: 代理工商业购电价格 | C92: 云南 | D92: =D93+D94 | E92: =E93+E94 | F92: =F93+F94 | G92: =G93+G94 | H92: =H93+H94 | I92: =I93+I94 | J92: =J93+J94 | K92: =K93+K94 | ... O92: =O93+O94 | P92: =IF(SUM(D92:O92)=0,"0",AVERAGEIF(D92:O92,"<>0",D92:O92))
A93: 92 | B93: （1）当月平均购电价格 | C93: 云南 | D93: 0.26506 | E93: 0.262856 | F93: 0.264539 | G93: 0.267327 | H93: 0.257092 | P93: =IF(SUM(D93:O93)=0,"0",AVERAGEIF(D93:O93,"<>0",D93:O93))
A94: 93 | B94: （2）历史偏差电费折价 | C94: 云南 | D94: -0.021183 | E94: -0.007665 | F94: 0.023733 | G94: 0.033021 | H94: 0.022255 | P94: =IF(SUM(D94:O94)=0,"0",AVERAGEIF(D94:O94,"<>0",D94:O94))
A95: 94 | B95: 代理工商业购电价格 | C95: 贵州 | D95: =D96+D97 | E95: =E96+E97 | F95: =F96+F97 | G95: =G96+G97 | H95: =H96+H97 | I95: =I96+I97 | J95: =J96+J97 | K95: =K96+K97 | ... O95: =O96+O97 | P95: =IF(SUM(D95:O95)=0,"0",AVERAGEIF(D95:O95,"<>0",D95:O95))
A96: 95 | B96: （1）当月平均购电价格 | C96: 贵州 | D96: 0.374558 | E96: 0.382894 | F96: 0.383704 | G96: 0.375721 | H96: 0.379745 | P96: =IF(SUM(D96:O96)=0,"0",AVERAGEIF(D96:O96,"<>0",D96:O96))
A97: 96 | B97: （2）历史偏差电费折价 | C97: 贵州 | D97: -0.00104 | E97: 0.009852 | F97: 0.001194 | G97: -0.009337 | H97: 0.004203 | P97: =IF(SUM(D97:O97)=0,"0",AVERAGEIF(D97:O97,"<>0",D97:O97))
A98: 97 | B98: 代理工商业购电价格 | C98: 海南 | D98: =D99+D100 | E98: =E99+E100 | F98: =F99+F100 | G98: =G99+G100 | H98: =H99+H100 | I98: =I99+I100 | J98: =J99+J100 | K98: =K99+K100 | ... O98: =O99+O100 | P98: =IF(SUM(D98:O98)=0,"0",AVERAGEIF(D98:O98,"<>0",D98:O98))
A99: 98 | B99: （1）当月平均购电价格 | C99: 海南 | D99: 0.4298 | E99: 0.379944 | F99: 0.353063 | G99: 0.371881 | H99: 0.417483 | P99: =IF(SUM(D99:O99)=0,"0",AVERAGEIF(D99:O99,"<>0",D99:O99))
A100: 99 | B100: （2）历史偏差电费折价 | C100: 海南 | D100: 0.193445 | E100: 0.059303 | F100: 0.043943 | G100: 0.042775 | H100: 0.035268 | P100: =IF(SUM(D100:O100)=0,"0",AVERAGEIF(D100:O100,"<>0",D100:O100))

Sheet 分表2-2026上网环节线损
A1: 序号 | B1: 2026年上网环节线损费用折价 | C1: 1月 | D1: 2月 | E1: 3月 | F1: 4月 | G1: 5月 | H1: 6月 | I1: 7月 | J1: 8月 | K1: 9月 | L1: 10月 | M1: 11月 | N1: 12月 | O1: 年均 | P1: 趋势图
A2: 1 | B2: 北京 | C2: 0.011414 | D2: 0.011381 | E2: 0.011381 | F2: 0.011381 | G2: 0.011381 | O2: =IF(SUM(C2:N2)=0,"0",AVERAGEIF(C2:N2,"<>0",C2:N2))
A3: 2 | B3: 天津 | C3: 0.016229 | D3: 0.016119 | E3: 0.016134 | F3: 0.016178 | G3: 0.016133 | O3: =IF(SUM(C3:N3)=0,"0",AVERAGEIF(C3:N3,"<>0",C3:N3))
A4: 3 | B4: 河北南网 | C4: 0.022091 | D4: 0.021364 | E4: 0.021081 | F4: 0.024398 | G4: 0.023756 | O4: =IF(SUM(C4:N4)=0,"0",AVERAGEIF(C4:N4,"<>0",C4:N4))
A5: 4 | B5: 冀北 | C5: 0.016433 | D5: 0.016405 | E5: 0.016441 | F5: 0.016513 | G5: 0.016521 | O5: =IF(SUM(C5:N5)=0,"0",AVERAGEIF(C5:N5,"<>0",C5:N5))
A6: 5 | B6: 山东 | C6: 0.0119 | D6: 0.0115 | E6: 0.0116 | F6: 0.0115 | G6: 0.0118 | O6: =IF(SUM(C6:N6)=0,"0",AVERAGEIF(C6:N6,"<>0",C6:N6))
A7: 6 | B7: 山西 | C7: 0.014417 | D7: 0.014205 | E7: 0.014018 | F7: 0.011532 | G7: 0.011205 | O7: =IF(SUM(C7:N7)=0,"0",AVERAGEIF(C7:N7,"<>0",C7:N7))
A8: 7 | B8: 蒙西 | C8: 0.0091 | D8: 0.0089 | E8: 0.009 | F8: 0.0088 | G8: 0.0087 | O8: =IF(SUM(C8:N8)=0,"0",AVERAGEIF(C8:N8,"<>0",C8:N8))
A9: 8 | B9: 上海 | C9: 0.0125 | D9: 0.012437 | E9: 0.011869 | F9: 0.011702 | G9: 0.012023 | O9: =IF(SUM(C9:N9)=0,"0",AVERAGEIF(C9:N9,"<>0",C9:N9))
A10: 9 | B10: 江苏 | C10: 0.013 | D10: 0.0104 | E10: 0.0121 | F10: 0.0123 | G10: 0.012 | O10: =IF(SUM(C10:N10)=0,"0",AVERAGEIF(C10:N10,"<>0",C10:N10))
A11: 10 | B11: 浙江 | C11: 0.013871 | D11: 0.007591 | E11: 0.011512 | F11: 0.014048 | G11: 0.011174 | O11: =IF(SUM(C11:N11)=0,"0",AVERAGEIF(C11:N11,"<>0",C11:N11))
A12: 11 | B12: 安徽 | C12: 0.0145 | D12: 0.0149 | E12: 0.014 | F12: 0.0143 | G12: 0.0144 | O12: =IF(SUM(C12:N12)=0,"0",AVERAGEIF(C12:N12,"<>0",C12:N12))
A13: 12 | B13: 福建 | C13: 0.013796 | D13: 0.013744 | E13: 0.013684 | F13: 0.013832 | G13: 0.013869 | O13: =IF(SUM(C13:N13)=0,"0",AVERAGEIF(C13:N13,"<>0",C13:N13))
... A33: 32 | B33: 海南 | C33: 0.02487 | D33: 0.021986 | E33: 0.02043 | F33: 0.021519 | G33: 0.024158 | O33: =IF(SUM(C33:N33)=0,"0",AVERAGEIF(C33:N33,"<>0",C33:N33))

Sheet 分表3-2026系统运行费
A1: 序号 | B1: 2026年代理购电价格 | C1: 省份 | D1: 1月 | E1: 2月 | F1: 3月 | G1: 4月 | H1: 5月 | I1: 6月 | J1: 7月 | K1: 8月 | L1: 9月 | M1: 10月 | N1: 11月 | O1: 12月 | P1: 省份 | Q1: 1月 | R1: 2月 | S1: 3月 | T1: 4月 | U1: 5月 | V1: 6月 | W1: 7月 | X1: 8月 | Y1: 9月 | Z1: 10月 | AA1: 11月 | AB1: 12月 | AC1: 省份 | AD1: 1月 | AE1: 2月 | AF1: 3月 | AG1: 4月 | AH1: 5月 | AI1: 6月 | AJ1: 7月 | AK1: 8月 | AL1: 9月 | AM1: 10月 | AN1: 11月 | AO1: 12月 | AP1: 省份 | AQ1: 1月 | AR1: 2月 | AS1: 3月 | AT1: 4月 | AU1: 5月 | AV1: 6月 | AW1: 7月 | AX1: 8月 | AY1: 9月 | AZ1: 10月 | BA1: 11月 | BB1: 12月 | BC1: 省份 | BD1: 1月 | BE1: 2月 | BF1: 3月 | BG1: 4月 | BH1: 5月 | BI1: 6月 | BJ1: 7月 | BK1: 8月 | BL1: 9月 | BM1: 10月 | BN1: 11月 | BO1: 12月 | BP1: 省份 | BQ1: 1月 | BR1: 2月 | BS1: 3月 | BT1: 4月 | BU1: 5月 | BV1: 6月 | BW1: 7月 | BX1: 8月 | BY1: 9月 | BZ1: 10月 | CA1: 11月 | CB1: 12月 | CC1: 省份 | CD1: 1月 | CE1: 2月 | CF1: 3月 | CG1: 4月 | CH1: 5月 | CI1: 6月 | CJ1: 7月 | CK1: 8月 | CL1: 9月 | CM1: 10月 | CN1: 11月 | CO1: 12月 | CP1: 省份 | CQ1: 1月 | CR1: 2月 | CS1: 3月 | CT1: 4月 | CU1: 5月 | CV1: 6月 | CW1: 7月 | CX1: 8月 | CY1: 9月 | CZ1: 10月 | DA1: 11月 | DB1: 12月 | DC1: 省份 | DD1: 1月 | DE1: 2月 | DF1: 3月 | DG1: 4月 | DH1: 5月 | DI1: 6月 | DJ1: 7月 | DK1: 8月 | DL1: 9月 | DM1: 10月 | DN1: 11月 | DO1: 12月 | DP1: 省份 | DQ1: 1月 | DR1: 2月 | DS1: 3月 | DT1: 4月 | DU1: 5月 | DV1: 6月 | DW1: 7月 | DX1: 8月 | DY1: 9月 | DZ1: 10月 | EA1: 11月 | EB1: 12月 | EC1: 省份 | ED1: 1月 | EE1: 2月 | EF1: 3月 | EG1: 4月 | EH1: 5月 | EI1: 6月 | EJ1: 7月 | EK1: 8月 | EL1: 9月 | EM1: 10月 | EN1: 11月 | EO1: 12月 | EP1: 省份 | EQ1: 1月 | ER1: 2月 | ES1: 3月 | ET1: 4月 | EU1: 5月 | EV1: 6月 | EW1: 7月 | EX1: 8月 | EY1: 9月 | EZ1: 10月 | FA1: 11月 | FB1: 12月 | FC1: 省份 | FD1: 1月 | FE1: 2月 | FF1: 3月 | FG1: 4月 | FH1: 5月 | FI1: 6月 | FJ1: 7月 | FK1: 8月 | FL1: 9月 | FM1: 10月 | FN1: 11月 | FO1: 12月 | FP1: 省份 | FQ1: 1月 | FR1: 2月 | FS1: 3月 | FT1: 4月 | FU1: 5月 | FV1: 6月 | FW1: 7月 | FX1: 8月 | FY1: 9月 | FZ1: 10月 | GA1: 11月 | GB1: 12月 | GC1: 省份 | GD1: 1月 | GE1: 2月 | GF1: 3月 | GG1: 4月 | GH1: 5月 | GI1: 6月 | GJ1: 7月 | GK1: 8月 | GL1: 9月 | GM1: 10月 | GN1: 11月 | GO1: 12月 | GP1: 省份 | GQ1: 1月 | GR1: 2月 | GS1: 3月 | GT1: 4月 | GU1: 5月 | GV1: 6月 | GW1: 7月 | GX1: 8月 | GY1: 9月 | GZ1: 10月 | HA1: 11月 | HB1: 12月 | HC1: 省份 | HD1: 1月 | HE1: 2月 | HF1: 3月 | HG1: 4月 | HH1: 5月 | HI1: 6月 | HJ1: 7月 | HK1: 8月 | HL1: 9月 | HM1: 10月 | HN1: 11月 | HO1: 12月 | HP1: 省份 | HQ1: 1月 | HR1: 2月 | HS1: 3月 | HT1: 4月 | HU1: 5月 | HV1: 6月 | HW1: 7月 | HX1: 8月 | HY1: 9月 | HZ1: 10月 | IA1: 11月 | IB1: 12月 | IC1: 省份 | ID1: 1月 | IE1: 2月 | IF1: 3月 | IG1: 4月 | IH1: 5月 | II1: 6月 | IJ1: 7月 | IK1: 8月 | IL1: 9月 | IM1: 10月 | IN1: 11月 | IO1: 12月 | IP1: 省份 | IQ1: 1月 | IR1: 2月 | IS1: 3月 | IT1: 4月 | IU1: 5月 | IV1: 6月 | IW1: 7月 | IX1: 8月 | IY1: 9月 | IZ1: 10月 | JA1: 11月 | JB1: 12月 | JC1: 省份 | JD1: 1月 | JE1: 2月 | JF1: 3月 | JG1: 4月 | JH1: 5月 | JI1: 6月 | JJ1: 7月 | JK1: 8月 | JL1: 9月 | JM1: 10月 | JN1: 11月 | JO1: 12月 | JP1: 省份 | JQ1: 1月 | JR1: 2月 | JS1: 3月 | JT1: 4月 | JU1: 5月 | JV1: 6月 | JW1: 7月 | JX1: 8月 | JY1: 9月 | JZ1: 10月 | KA1: 11月 | KB1: 12月 | KC1: 省份 | KD1: 1月 | KE1: 2月 | KF1: 3月 | KG1: 4月 | KH1: 5月 | KI1: 6月 | KJ1: 7月 | KK1: 8月 | KL1: 9月 | KM1: 10月 | KN1: 11月 | KO1: 12月 | KP1: 省份 | KQ1: 1月 | KR1: 2月 | KS1: 3月 | KT1: 4月 | KU1: 5月 | KV1: 6月 | KW1: 7月 | KX1: 8月 | KY1: 9月 | KZ1: 10月 | LA1: 11月 | LB1: 12月 | LC1: 省份 | LD1: 1月 | LE1: 2月 | LF1: 3月 | LG1: 4月 | LH1: 5月 | LI1: 6月 | LJ1: 7月 | LK1: 8月 | LL1: 9月 | LM1: 10月 | LN1: 11月 | LO1: 12月 | LP1: 省份 | LQ1: 1月 | LR1: 2月 | LS1: 3月 | LT1: 4月 | LU1: 5月 | LV1: 6月 | LW1: 7月 | LX1: 8月 | LY1: 9月 | LZ1: 10月 | MA1: 11月 | MB1: 12月 | MC1: 省份 | MD1: 1月 | ME1: 2月 | MF1: 3月 | MG1: 4月 | MH1: 5月 | MI1: 6月 | MJ1: 7月 | MK1: 8月 | ML1: 9月 | MM1: 10月 | MN1: 11月 | MO1: 12月 | MP1: 省份 | MQ1: 1月 | MR1: 2月 | MS1: 3月 | MT1: 4月 | MU1: 5月 | MV1: 6月 | MW1: 7月 | MX1: 8月 | MY1: 9月 | MZ1: 10月 | NA1: 11月 | NB1: 12月 | NC1: 省份 | ND1: 1月 | NE1: 2月 | NF1: 3月 | NG1: 4月 | NH1: 5月 | NI1: 6月 | NJ1: 7月 | NK1: 8月 | NL1: 9月 | NM1: 10月 | NN1: 11月 | NO1: 12月 | NP1: 省份 | NQ1: 1月 | NR1: 2月 | NS1: 3月 | NT1: 4月 | NU1: 5月 | NV1: 6月 | NW1: 7月 | NX1: 8月 | NY1: 9月 | NZ1: 10月 | OA1: 11月 | OB1: 12月 | OC1: 省份 | OD1: 1月 | OE1: 2月 | OF1: 3月 | OG1: 4月 | OH1: 5月 | OI1: 6月 | OJ1: 7月 | OK1: 8月 | OL1: 9月 | OM1: 10月 | ON1: 11月 | OO1: 12月 | OP1: 省份 | OQ1: 1月 | OR1: 2月 | OS1: 3月 | OT1: 4月 | OU1: 5月 | OV1: 6月 | OW1: 7月 | OX1: 8月 | OY1: 9月 | OZ1: 10月 | PA1: 11月 | PB1: 12月
A2: 1 | B2: 系统运行费用折合度电水平 | C2: 北京 | D2: =SUM(D3:D24) | E2: =SUM(E3:E24) | F2: =SUM(F3:F24) | G2: =SUM(G3:G24) | H2: =SUM(H3:H24) | I2: =SUM(I3:I24) | J2: =SUM(J3:J24) | K2: =SUM(K3:K24) | ... O2: =SUM(O3:O24) | P2: 天津 | Q2: =SUM(Q3:Q24) | R2: =SUM(R3:R24) | S2: =SUM(S3:S24) | T2: =SUM(T3:T24) | U2: =SUM(U3:U24) | V2: =SUM(V3:V24) | W2: =SUM(W3:W24) | X2: =SUM(X3:X24) | ... AB2: =SUM(AB3:AB24) | AC2: 河北南网 | AD2: =SUM(AD3:AD24) | AE2: =SUM(AE3:AE24) | AF2: =SUM(AF3:AF24) | AG2: =SUM(AG3:AG24) | AH2: =SUM(AH3:AH24) | AI2: =SUM(AI3:AI24) | AJ2: =SUM(AJ3:AJ24) | AK2: =SUM(AK3:AK24) | ... AO2: =SUM(AO3:AO24) | AP2: 冀北 | AQ2: =SUM(AQ3:AQ24) | AR2: =SUM(AR3:AR24) | AS2: =SUM(AS3:AS24) | AT2: =SUM(AT3:AT24) | AU2: =SUM(AU3:AU24) | AV2: =SUM(AV3:AV24) | AW2: =SUM(AW3:AW24) | AX2: =SUM(AX3:AX24) | ... BB2: =SUM(BB3:BB24) | BC2: 山东 | BD2: =SUM(BD3:BD24) | BE2: =SUM(BE3:BE24) | BF2: =SUM(BF3:BF24) | BG2: =SUM(BG3:BG24) | BH2: =SUM(BH3:BH24) | BI2: =SUM(BI3:BI24) | BJ2: =SUM(BJ3:BJ24) | BK2: =SUM(BK3:BK24) | ... BO2: =SUM(BO3:BO24) | BP2: 山西 | BQ2: =SUM(BQ3:BQ24) | BR2: =SUM(BR3:BR24) | BS2: =SUM(BS3:BS24) | BT2: =SUM(BT3:BT24) | BU2: =SUM(BU3:BU24) | BV2: =SUM(BV3:BV24) | BW2: =SUM(BW3:BW24) | BX2: =SUM(BX3:BX24) | ... CB2: =SUM(CB3:CB24) | CC2: 蒙西 | CD2: =SUM(CD3:CD24) | CE2: =SUM(CE3:CE24) | CF2: =SUM(CF3:CF24) | CG2: =SUM(CG3:CG24) | CH2: =SUM(CH3:CH24) | CI2: =SUM(CI3:CI24) | CJ2: =SUM(CJ3:CJ24) | CK2: =SUM(CK3:CK24) | ... CO2: =SUM(CO3:CO24) | CP2: 上海 | CQ2: =SUM(CQ3:CQ24) | CR2: =SUM(CR3:CR24) | CS2: =SUM(CS3:CS24) | CT2: =SUM(CT3:CT24) | CU2: =SUM(CU3:CU24) | CV2: =SUM(CV3:CV24) | CW2: =SUM(CW3:CW24) | CX2: =SUM(CX3:CX24) | ... DB2: =SUM(DB3:DB24) | DC2: 江苏 | DD2: =SUM(DD3:DD24) | DE2: =SUM(DE3:DE24) | DF2: =SUM(DF3:DF24) | DG2: =SUM(DG3:DG24) | DH2: =SUM(DH3:DH24) | DI2: =SUM(DI3:DI24) | DJ2: =SUM(DJ3:DJ24) | DK2: =SUM(DK3:DK24) | ... DO2: =SUM(DO3:DO24) | DP2: 浙江 | DQ2: =SUM(DQ3:DQ24) | DR2: =SUM(DR3:DR24) | DS2: =SUM(DS3:DS24) | DT2: =SUM(DT3:DT24) | DU2: =SUM(DU3:DU24) | DV2: =SUM(DV3:DV24) | DW2: =SUM(DW3:DW24) | DX2: =SUM(DX3:DX24) | ... EB2: =SUM(EB3:EB24) | EC2: 安徽 | ED2: =SUM(ED3:ED24) | EE2: =SUM(EE3:EE24) | EF2: =SUM(EF3:EF24) | EG2: =SUM(EG3:EG24) | EH2: =SUM(EH3:EH24) | EI2: =SUM(EI3:EI24) | EJ2: =SUM(EJ3:EJ24) | EK2: =SUM(EK3:EK24) | ... EO2: =SUM(EO3:EO24) | EP2: 福建 | EQ2: =SUM(EQ3:EQ24) | ER2: =SUM(ER3:ER24) | ES2: =SUM(ES3:ES24) | ET2: =SUM(ET3:ET24) | EU2: =SUM(EU3:EU24) | EV2: =SUM(EV3:EV24) | EW2: =SUM(EW3:EW24) | EX2: =SUM(EX3:EX24) | ... FB2: =SUM(FB3:FB24) | FC2: 湖北 | FD2: =SUM(FD3:FD24) | FE2: =SUM(FE3:FE24) | FF2: =SUM(FF3:FF24) | FG2: =SUM(FG3:FG24) | FH2: =SUM(FH3:FH24) | FI2: =SUM(FI3:FI24) | FJ2: =SUM(FJ3:FJ24) | FK2: =SUM(FK3:FK24) | ... FO2: =SUM(FO3:FO24) | FP2: 河南 | FQ2: =SUM(FQ3:FQ24) | FR2: =SUM(FR3:FR24) | FS2: =SUM(FS3:FS24) | FT2: =SUM(FT3:FT24) | FU2: =SUM(FU3:FU24) | FV2: =SUM(FV3:FV24) | FW2: =SUM(FW3:FW24) | FX2: =SUM(FX3:FX24) | ... GB2: =SUM(GB3:GB24) | GC2: 湖南 | GD2: =SUM(GD3:GD24) | GE2: =SUM(GE3:GE24) | GF2: =SUM(GF3:GF24) | GG2: =SUM(GG3:GG24) | GH2: =SUM(GH3:GH24) | GI2: =SUM(GI3:GI24) | GJ2: =SUM(GJ3:GJ24) | GK2: =SUM(GK3:GK24) | ... GO2: =SUM(GO3:GO24) | GP2: 江西 | GQ2: =SUM(GQ3:GQ24) | GR2: =SUM(GR3:GR24) | GS2: =SUM(GS3:GS24) | GT2: =SUM(GT3:GT24) | GU2: =SUM(GU3:GU24) | GV2: =SUM(GV3:GV24) | GW2: =SUM(GW3:GW24) | GX2: =SUM(GX3:GX24) | ... HB2: =SUM(HB3:HB24) | HC2: 辽宁 | HD2: =SUM(HD3:HD24) | HE2: =SUM(HE3:HE24) | HF2: =SUM(HF3:HF24) | HG2: =SUM(HG3:HG24) | HH2: =SUM(HH3:HH24) | HI2: =SUM(HI3:HI24) | HJ2: =SUM(HJ3:HJ24) | HK2: =SUM(HK3:HK24) | ... HO2: =SUM(HO3:HO24) | HP2: 吉林 | HQ2: =SUM(HQ3:HQ24) | HR2: =SUM(HR3:HR24) | HS2: =SUM(HS3:HS24) | HT2: =SUM(HT3:HT24) | HU2: =SUM(HU3:HU24) | HV2: =SUM(HV3:HV24) | HW2: =SUM(HW3:HW24) | HX2: =SUM(HX3:HX24) | ... IB2: =SUM(IB3:IB24) | IC2: 黑龙江 | ID2: =SUM(ID3:ID24) | IE2: =SUM(IE3:IE24) | IF2: =SUM(IF3:IF24) | IG2: =SUM(IG3:IG24) | IH2: =SUM(IH3:IH24) | II2: =SUM(II3:II24) | IJ2: =SUM(IJ3:IJ24) | IK2: =SUM(IK3:IK24) | ... IO2: =SUM(IO3:IO24) | IP2: 蒙东 | IQ2: =SUM(IQ3:IQ24) | IR2: =SUM(IR3:IR24) | IS2: =SUM(IS3:IS24) | IT2: =SUM(IT3:IT24) | IU2: =SUM(IU3:IU24) | IV2: =SUM(IV3:IV24) | IW2: =SUM(IW3:IW24) | IX2: =SUM(IX3:IX24) | ... JB2: =SUM(JB3:JB24) | JC2: 陕西 | JD2: =SUM(JD3:JD24) | JE2: =SUM(JE3:JE24) | JF2: =SUM(JF3:JF24) | JG2: =SUM(JG3:JG24) | JH2: =SUM(JH3:JH24) | JI2: =SUM(JI3:JI24) | JJ2: =SUM(JJ3:JJ24) | JK2: =SUM(JK3:JK24) | ... JO2: =SUM(JO3:JO24) | JP2: 甘肃 | JQ2: =SUM(JQ3:JQ24) | JR2: =SUM(JR3:JR24) | JS2: =SUM(JS3:JS24) | JT2: =SUM(JT3:JT24) | JU2: =SUM(JU3:JU24) | JV2: =SUM(JV3:JV24) | JW2: =SUM(JW3:JW24) | JX2: =SUM(JX3:JX24) | ... KB2: =SUM(KB3:KB24) | KC2: 青海 | KD2: =SUM(KD3:KD24) | KE2: =SUM(KE3:KE24) | KF2: =SUM(KF3:KF24) | KG2: =SUM(KG3:KG24) | KH2: =SUM(KH3:KH24) | KI2: =SUM(KI3:KI24) | KJ2: =SUM(KJ3:KJ24) | KK2: =SUM(KK3:KK24) | ... KO2: =SUM(KO3:KO24) | KP2: 宁夏 | KQ2: =SUM(KQ3:KQ24) | KR2: =SUM(KR3:KR24) | KS2: =SUM(KS3:KS24) | KT2: =SUM(KT3:KT24) | KU2: =SUM(KU3:KU24) | KV2: =SUM(KV3:KV24) | KW2: =SUM(KW3:KW24) | KX2: =SUM(KX3:KX24) | ... LB2: =SUM(LB3:LB24) | LC2: 新疆 | LD2: =SUM(LD3:LD24) | LE2: =SUM(LE3:LE24) | LF2: =SUM(LF3:LF24) | LG2: =SUM(LG3:LG24) | LH2: =SUM(LH3:LH24) | LI2: =SUM(LI3:LI24) | LJ2: =SUM(LJ3:LJ24) | LK2: =SUM(LK3:LK24) | ... LO2: =SUM(LO3:LO24) | LP2: 重庆 | LQ2: =SUM(LQ3:LQ24) | LR2: =SUM(LR3:LR24) | LS2: =SUM(LS3:LS24) | LT2: =SUM(LT3:LT24) | LU2: =SUM(LU3:LU24) | LV2: =SUM(LV3:LV24) | LW2: =SUM(LW3:LW24) | LX2: =SUM(LX3:LX24) | ... MB2: =SUM(MB3:MB24) | MC2: 四川 | MD2: =SUM(MD3:MD24) | ME2: =SUM(ME3:ME24) | MF2: =SUM(MF3:MF24) | MG2: =SUM(MG3:MG24) | MH2: =SUM(MH3:MH24) | MI2: =SUM(MI3:MI24) | MJ2: =SUM(MJ3:MJ24) | MK2: =SUM(MK3:MK24) | ... MO2: =SUM(MO3:MO24) | MP2: 广东 | MQ2: =SUM(MQ3:MQ24) | MR2: =SUM(MR3:MR24) | MS2: =SUM(MS3:MS24) | MT2: =SUM(MT3:MT24) | MU2: =SUM(MU3:MU24) | MV2: =SUM(MV3:MV24) | MW2: =SUM(MW3:MW24) | MX2: =SUM(MX3:MX24) | ... NB2: =SUM(NB3:NB24) | NC2: 广西 | ND2: =SUM(ND3:ND24) | NE2: =SUM(NE3:NE24) | NF2: =SUM(NF3:NF24) | NG2: =SUM(NG3:NG24) | NH2: =SUM(NH3:NH24) | NI2: =SUM(NI3:NI24) | NJ2: =SUM(NJ3:NJ24) | NK2: =SUM(NK3:NK24) | ... NO2: =SUM(NO3:NO24) | NP2: 云南 | NQ2: =SUM(NQ3:NQ24) | NR2: =SUM(NR3:NR24) | NS2: =SUM(NS3:NS24) | NT2: =SUM(NT3:NT24) | NU2: =SUM(NU3:NU24) | NV2: =SUM(NV3:NV24) | NW2: =SUM(NW3:NW24) | NX2: =SUM(NX3:NX24) | ... OB2: =SUM(OB3:OB24) | OC2: 贵州 | OD2: =SUM(OD3:OD24) | OE2: =SUM(OE3:OE24) | OF2: =SUM(OF3:OF24) | OG2: =SUM(OG3:OG24) | OH2: =SUM(OH3:OH24) | OI2: =SUM(OI3:OI24) | OJ2: =SUM(OJ3:OJ24) | OK2: =SUM(OK3:OK24) | ... OO2: =SUM(OO3:OO24) | OP2: 海南 | OQ2: -0.004545 | OR2: 0.137592 | OS2: 0.158319 | OT2: =SUM(OT3:OT24) | OU2: =SUM(OU3:OU24) | OV2: =SUM(OV3:OV24) | OW2: =SUM(OW3:OW24) | OX2: =SUM(OX3:OX24) | OY2: =SUM(OY3:OY24) | OZ2: =SUM(OZ3:OZ24) | PA2: =SUM(PA3:PA24) | PB2: =SUM(PB3:PB24)
A3: 2 | B3: （1）辅助服务费用折合度电水平 | C3: 北京 | D3: 0 | E3: 0 | F3: 0 | G3: 0 | H3: 0 | P3: 天津 | Q3: 0 | R3: 0 | S3: 0 | T3: 0 | U3: 0 | AC3: 河北南网 | AD3: 0 | AE3: 0 | AF3: 0.000268 | AG3: 0.000234 | AH3: 0.000129 | AP3: 冀北 | AQ3: 0 | AR3: 0 | AS3: 0 | AT3: 0 | AU3: 0 | BC3: 山东 | BD3: 0 | BE3: 0 | BF3: 0 | BG3: 0 | BH3: 0 | BP3: 山西 | BQ3: 0.003301 | BR3: 0.003978 | BS3: 0.003473 | BT3: 0.003409 | BU3: 0.003521 | CC3: 蒙西 | CD3: 0.0008 | CE3: 0.0008 | CF3: 0.0004 | CG3: 0.0002 | CH3: 0.0017 | CP3: 上海 | CQ3: 0 | CR3: 0 | CS3: 0 | CT3: 0 | CU3: 0 | DC3: 江苏 | DD3: 0 | DE3: 0 | DF3: 0 | DG3: 0 | DH3: 0 | DP3: 浙江 | DQ3: 0 | DR3: 0 | DS3: 0 | DT3: 0 | DU3: 0 | EC3: 安徽 | ED3: 0 | EE3: 0 | EF3: 0 | EG3: 0 | EH3: 0 | EP3: 福建 | EQ3: 0 | ER3: 0 | ES3: 0 | ET3: 0 | EU3: 0 | FC3: 湖北 | FD3: 0 | FE3: 0 | FF3: 0 | FG3: 0.001138 | FH3: 0.00216 | FP3: 河南 | FQ3: 0 | FR3: 0 | FS3: 0 | FT3: 0 | FU3: 0 | GC3: 湖南 | GD3: 0 | GE3: 0 | GF3: 0 | GG3: 0 | GH3: 0 | GP3: 江西 | GQ3: 0 | GR3: 0 | GS3: 0 | GT3: 0 | GU3: 0 | HC3: 辽宁 | HD3: 0 | HE3: 0 | HF3: 0.000837 | HG3: 0.000687 | HH3: 0.00085 | HP3: 吉林 | HQ3: 0.003522 | HR3: 0.002456 | HS3: 0.005913 | HT3: -0.001415 | HU3: -0.000551 | IC3: 黑龙江 | ID3: 0 | IE3: 0 | IF3: 0 | IG3: 0 | IH3: 0 | IP3: 蒙东 | IQ3: 0 | IR3: 0 | IS3: 0 | IT3: 0 | IU3: 0 | JC3: 陕西 | JD3: 0.0025 | JE3: 0.0039 | JF3: 0.004 | JG3: 0.0031 | JH3: 0.0036 | JP3: 甘肃 | JQ3: 0.014437 | JR3: 0.017761 | JS3: 0.005119 | JT3: 0.004951 | JU3: 0.007169 | KC3: 青海 | KP3: 宁夏 | KQ3: 0 | KR3: 0 | KS3: 0 | KT3: 0 | KU3: 0 | LC3: 新疆 | LD3: 0.005025 | LE3: 0.006606 | LF3: 0.005018 | LG3: 0.00554 | LH3: 0.005135 | LP3: 重庆 | LQ3: 0 | LR3: 0 | LS3: 0 | LT3: 0 | LU3: 0 | MC3: 四川 | MD3: 0.003082 | ME3: 0.003312 | MF3: 0.002128 | MG3: 0.001182 | MH3: 0.000698 | MP3: 广东 | MQ3: 0.0042 | MR3: 0.0034 | MS3: 0.0017 | MT3: 0.0033 | MU3: 0.0022 | NC3: 广西 | ND3: 0.003968 | NE3: 0.003964 | NF3: 0.003611 | NG3: 0.002955 | NH3: 0.003716 | NP3: 云南 | OC3: 贵州 | OD3: 0 | OE3: 0 | OF3: 0 | OG3: 0 | OH3: 0 | OP3: 海南 | OT3: 0.00216 | OU3: 0.001664
A4: 3 | B4: （2）抽水蓄能容量电费折合度电水平 | C4: 北京 | D4: 0.007258 | E4: 0.009188 | F4: 0.008309 | G4: 0.009903 | H4: 0.008907 | P4: 天津 | Q4: 0.005129 | R4: 0.006585 | S4: 0.005202 | T4: 0.006771 | U4: 0.006079 | AC4: 河北南网 | AD4: 0.007452 | AE4: 0.011058 | AF4: 0.007869 | AG4: 0.008945 | AH4: 0.008182 | AP4: 冀北 | AQ4: 0.002952 | AR4: 0.003696 | AS4: 0.003003 | AT4: 0.003772 | AU4: 0.003412 | BC4: 山东 | BD4: 0.0046 | BE4: 0.0064 | BF4: 0.0052 | BG4: 0.0059 | BH4: 0.0052 | BP4: 山西 | BQ4: 0.00232 | BR4: 0.002824 | BS4: -0.00558 | BT4: -0.000525 | BU4: -0.00137 | CC4: 蒙西 | CD4: 0.0026 | CE4: 0.0042 | CF4: 0.0023 | CG4: 0.0024 | CH4: 0.0022 | CP4: 上海 | CQ4: 0.00987 | CR4: 0.00987 | CS4: 0.00987 | CT4: 0.00987 | CU4: 0.00987 | DC4: 江苏 | DD4: 0.0056 | DE4: 0.0089 | DF4: 0.0052 | DG4: 0.0055 | DH4: 0.0058 | DP4: 浙江 | DQ4: 0.018888 | DR4: 0.020755 | DS4: 0.008395 | DT4: 0.009798 | DU4: 0.009102 | EC4: 安徽 | ED4: 0.0094 | EE4: 0.0137 | EF4: 0.0101 | EG4: 0.0112 | EH4: 0.0101 | EP4: 福建 | EQ4: 0.013846 | ER4: 0.022276 | ES4: 0.013126 | ET4: 0.012811 | EU4: 0.012391 | FC4: 湖北 | FD4: 0.002316 | FE4: 0.003151 | FF4: 0.002248 | FG4: 0.002444 | FH4: 0.002369 | FP4: 河南 | FQ4: 0.004994 | FR4: 0.004994 | FS4: 0.004994 | FT4: 0.004994 | FU4: 0.004994 | GC4: 湖南 | GD4: 0.003475 | GE4: 0.004653 | GF4: 0.003342 | GG4: 0.004069 | GH4: 0.003622 | GP4: 江西 | GQ4: 0.003569 | GR4: 0.00619 | GS4: 0.003865 | GT4: 0.003726 | GU4: 0.003767 | HC4: 辽宁 | HD4: 0.009937 | HE4: 0.011568 | HF4: 0.009702 | HG4: 0.012784 | HH4: 0.012481 | HP4: 吉林 | HQ4: 0.010352 | HR4: 0.011051 | HS4: 0.009682 | HT4: 0.013653 | HU4: 0.013368 | IC4: 黑龙江 | ID4: 0.009281 | IE4: 0.012656 | IF4: 0.010562 | IG4: 0.012071 | IH4: 0.012165 | IP4: 蒙东 | IQ4: 0.007252 | IR4: 0.010647 | IS4: 0.007886 | IT4: 0.008586 | IU4: 0.007873 | JC4: 陕西 | JD4: 0.0025 | JE4: 0.0026 | JF4: 0.0056 | JG4: 0.0067 | JH4: 0.0025 | JP4: 甘肃 | JQ4: 0.000765 | JR4: 0.000887 | JS4: 0.000773 | JT4: 0.00089 | JU4: 0.00082 | KC4: 青海 | KD4: 0.000971 | KE4: 0.001154 | KF4: 0.001025 | KG4: 0.001075 | KH4: 0.001029 | KP4: 宁夏 | KQ4: 0.000704 | KR4: 0.000788 | KS4: 0.000687 | KT4: 0.000725 | KU4: 0.000673 | LC4: 新疆 | LD4: 0.004405 | LE4: 0.005708 | LF4: 0.00456 | LG4: 0.006045 | LH4: 0.005598 | LP4: 重庆 | LQ4: 0.00842 | LR4: 0.011558 | LS4: 0.008662 | LT4: 0.009132 | LU4: 0.008445 | MC4: 四川 | MP4: 广东 | MQ4: 0.0076 | MR4: 0.0134 | MS4: 0.0069 | MT4: 0.0068 | MU4: 0.0058 | NC4: 广西 | NP4: 云南 | OC4: 贵州 | OD4: 0 | OE4: 0 | OF4: 0 | OG4: 0 | OH4: 0 | OP4: 海南 | OT4: 0.038424 | OU4: 0.022927
A5: 4 | B5: （3）上网环节线损代理采购损益折合度电水平 | C5: 北京 | D5: 0.002937 | E5: 0.004371 | F5: 0.006783 | G5: 0.008456 | H5: 0.004059 | P5: 天津 | Q5: -0.002736 | R5: -0.006764 | S5: -0.000102 | T5: -0.008798 | U5: -0.006507 | AC5: 河北南网 | AD5: -0.007036 | AE5: -0.01229 | AF5: -0.009175 | AG5: -0.006058 | AH5: -0.005532 | AP5: 冀北 | AQ5: -0.005854 | AR5: -0.00603 | AS5: -0.005735 | AT5: -0.004254 | AU5: -0.004709 | BC5: 山东 | BD5: -0.0016 | BE5: -0.0007 | BF5: -0.0007 | BG5: 0.002 | BH5: -0.0003 | BP5: 山西 | BQ5: -0.000627 | BR5: -0.00335 | BS5: -0.000627 | BT5: 0.0004 | BU5: -0.001568 | CC5: 蒙西 | CD5: 0.0016 | CE5: 0.002 | CF5: 0.0014 | CG5: 0.0011 | CH5: -0.0009 | CP5: 上海 | CQ5: 0.003 | CR5: -0.001166 | CS5: -0.002345 | CT5: -0.003324 | CU5: -0.000817 | DC5: 江苏 | DD5: -0.0008 | DE5: -0.0044 | DF5: -0.0021 | DG5: -0.0004 | DH5: -0.002 | DP5: 浙江 | DQ5: 0 | DR5: 0 | DS5: 0 | DT5: 0 | DU5: 0 | EC5: 安徽 | ED5: -0.0002 | EE5: -0.0005 | EF5: 0.0005 | EG5: -0.0003 | EH5: 0 | EP5: 福建 | EQ5: -0.00281 | ER5: -0.003928 | ES5: -0.002455 | ET5: -0.001219 | EU5: -0.002243 | FC5: 湖北 | FD5: 0 | FE5: 0 | FF5: 0 | FG5: 0 | FH5: 0 | FP5: 河南 | FQ5: 0 | FR5: 0 | FS5: 0 | FT5: 0 | FU5: 0 | GC5: 湖南 | GD5: -0.013693 | GE5: -0.008985 | GF5: -0.021702 | GG5: 0.002105 | GH5: 0.009853 | GP5: 江西 | GQ5: 0.000774 | GR5: -0.002098 | GS5: -0.003915 | GT5: -0.001589 | GU5: -0.00279 | HC5: 辽宁 | HD5: 0.000995 | HE5: 0.001841 | HF5: 0.000497 | HG5: -0.002413 | HH5: 8e-06 | HP5: 吉林 | HQ5: -0.001944 | HR5: -0.002264 | HS5: -0.004851 | HT5: -0.011823 | HU5: 0.001682 | IC5: 黑龙江 | ID5: 0.006274 | IE5: 0.002778 | IF5: -0.000494 | IG5: -0.005983 | IH5: -0.006866 | IP5: 蒙东 | IQ5: -0.004101 | IR5: -0.006839 | IS5: -0.002463 | IT5: -0.002216 | IU5: -0.003802 | JC5: 陕西 | JD5: 0.0003 | JE5: -0.0008 | JF5: -0.0002 | JG5: -0.0001 | JH5: -0.0007 | JP5: 甘肃 | JQ5: -0.000657 | JR5: -0.000332 | JS5: 0.000755 | JT5: -0.002168 | JU5: -0.000411 | KC5: 青海 | KD5: -0.003711 | KE5: -0.004754 | KF5: -0.004917 | KG5: -0.007435 | KH5: -0.004082 | KP5: 宁夏 | KQ5: 0.0015 | KR5: -0.0005 | KS5: 0.0012 | KT5: -0.0001 | KU5: 0.0011 | LC5: 新疆 | LP5: 重庆 | LQ5: -0.000614 | LR5: -0.000572 | LS5: -0.001206 | LT5: 0.001483 | LU5: 5.4e-05 | MC5: 四川 | MP5: 广东 | NC5: 广西 | NP5: 云南 | OC5: 贵州 | OP5: 海南
A6: 5 | B6: （4）电价交叉补贴新增损益折合度电水平 | C6: 北京 | D6: -0.02 | E6: -0.02 | F6: -0.02 | G6: -0.02 | H6: -0.02 | P6: 天津 | Q6: 0.101753 | R6: 0.07277 | S6: 0.033072 | T6: 0.007389 | U6: 0.001197 | AC6: 河北南网 | AD6: 0.017188 | AE6: 0.019393 | AF6: -0.010192 | AG6: -0.051134 | AH6: -0.0258 | AP6: 冀北 | AQ6: 0.016109 | AR6: 0.016534 | AS6: 0.013603 | AT6: 0.005914 | AU6: 0.002418 | BC6: 山东 | BD6: -0.026 | BE6: -0.0095 | BF6: -0.0145 | BG6: -0.0217 | BH6: -0.0188 | BP6: 山西 | BQ6: 0.030867 | BR6: 0.025794 | BS6: 0.010438 | BT6: -0.003819 | BU6: -0.005836 | CC6: 蒙西 | CD6: -0.0013 | CE6: -0.0013 | CF6: -0.0026 | CG6: 0.007 | CH6: -0.0009 | CP6: 上海 | CQ6: -0.0182 | CR6: -0.026879 | CS6: -0.025757 | CT6: -0.011433 | CU6: -0.015644 | DC6: 江苏 | DD6: 0.0151 | DE6: 0.0349 | DF6: 0.0074 | DG6: -0.0194 | DH6: -0.0093 | DP6: 浙江 | DQ6: -0.015787 | DR6: -0.127455 | DS6: 0.009039 | DT6: 0.024189 | DU6: -0.003022 | EC6: 安徽 | ED6: -0.0132 | EE6: -0.0419 | EF6: 0.0046 | EG6: 0.0085 | EH6: -0.014 | EP6: 福建 | EQ6: 0.001979 | ER6: 0.02192 | ES6: -0.007435 | ET6: 0.005084 | EU6: 0.005205 | FC6: 湖北 | FD6: 0.017294 | FE6: 0.018906 | FF6: 0.00652 | FG6: -0.010275 | FH6: 0.001226 | FP6: 河南 | FQ6: -0.009535 | FR6: 0.016158 | FS6: 0.006228 | FT6: -0.043244 | FU6: -0.03674 | GC6: 湖南 | GD6: -0.013301 | GE6: 0.013344 | GF6: 0.00397 | GG6: -0.005667 | GH6: -0.081683 | GP6: 江西 | GQ6: 0.005922 | GR6: 0.009098 | GS6: -0.006052 | GT6: -0.015341 | GU6: -0.018751 | HC6: 辽宁 | HD6: 0.00226 | HE6: 0.007001 | HF6: 0.017285 | HG6: 0.011657 | HH6: 0.005449 | HP6: 吉林 | HQ6: -0.030037 | HR6: -0.032684 | HS6: -0.016926 | HT6: -0.044093 | HU6: -0.028266 | IC6: 黑龙江 | ID6: 0.01462 | IE6: 0.008691 | IF6: 0.00744 | IG6: -0.030406 | IH6: -0.03985 | IP6: 蒙东 | IQ6: -0.020048 | IR6: -0.021611 | IS6: -0.055316 | IT6: -0.038556 | IU6: 0.013359 | JC6: 陕西 | JD6: 0.0047 | JE6: 0.0018 | JF6: 0.0182 | JG6: -0.0105 | JH6: -0.0147 | JP6: 甘肃 | JQ6: 0.002364 | JR6: -0.006502 | JS6: -0.011909 | JT6: -0.009828 | JU6: -0.014908 | KC6: 青海 | KD6: 0.018925 | KE6: 0.016216 | KF6: 0.013277 | KG6: -0.004637 | KH6: -0.006313 | KP6: 宁夏 | KQ6: -0.0009 | KR6: 0.0034 | KS6: 0.0079 | KT6: -0.0067 | KU6: 0.0103 | LC6: 新疆 | LD6: 0.00327 | LE6: 0 | LF6: 0.001188 | LG6: -0.012294 | LH6: -0.023195 | LP6: 重庆 | LQ6: 0.006584 | LR6: 0.018179 | LS6: -0.026926 | LT6: -0.031526 | LU6: -0.030336 | MC6: 四川 | MD6: 0.036034 | ME6: 0.020977 | MF6: 0.011761 | MG6: 0.032673 | MH6: 0.014138 | MP6: 广东 | NC6: 广西 | NP6: 云南 | OC6: 贵州 | OD6: 0.065515 | OE6: 0.041932 | OF6: 0.002896 | OG6: -0.020795 | OH6: -0.019846 | OP6: 海南
A7: 6 | B7: （5）煤电容量电费折合度电水平 | C7: 北京 | D7: 0.019455 | E7: 0.024164 | F7: 0.014037 | G7: 0.023531 | H7: 0.016548 | P7: 天津 | Q7: 0.032915 | R7: 0.036182 | S7: 0.034397 | T7: 0.041502 | U7: 0.051853 | AC7: 河北南网 | AD7: 0.032369 | AE7: 0.047489 | AF7: 0.034704 | AG7: 0.041469 | AH7: 0.037512 | AP7: 冀北 | AQ7: 0.02612 | AR7: 0.032169 | AS7: 0.029361 | AT7: 0.03644 | AU7: 0.031846 | BC7: 山东 | BD7: 0.0172 | BE7: 0.0261 | BF7: 0.0189 | BG7: 0.0209 | BH7: 0.0176 | BP7: 山西 | BQ7: 0.023661 | BR7: 0.030768 | BS7: 0.032734 | BT7: 0.037411 | BU7: 0.03073 | CC7: 蒙西 | CD7: 0.0179 | CE7: 0.0203 | CF7: 0.0225 | CG7: 0.0231 | CH7: 0.0199 | CP7: 上海 | CQ7: 0.0219 | CR7: 0.027398 | CS7: 0.014705 | CT7: 0.026536 | CU7: 0.022786 | DC7: 江苏 | DD7: 0.0268 | DE7: 0.043 | DF7: 0.035 | DG7: 0.0342 | DH7: 0.034 | DP7: 浙江 | DQ7: 0.022566 | DR7: 0.045314 | DS7: 0.022437 | DT7: 0.024991 | DU7: 0.024256 | EC7: 安徽 | ED7: 0.034 | EE7: 0.0497 | EF7: 0.0379 | EG7: 0.0425 | EH7: 0.0386 | EP7: 福建 | EQ7: 0.024636 | ER7: 0.042078 | ES7: 0.024613 | ET7: 0.025997 | EU7: 0.027137 | FC7: 湖北 | FD7: 0.036657 | FE7: 0.051409 | FF7: 0.036851 | FG7: 0.040094 | FH7: 0.038793 | FP7: 河南 | FQ7: 0.038401 | FR7: 0.052143 | FS7: 0.041559 | FT7: 0.042552 | FU7: 0.040252 | GC7: 湖南 | GD7: 0.048457 | GE7: 0.06667 | GF7: 0.029762 | GG7: 0.048917 | GH7: 0.057163 | GP7: 江西 | GQ7: 0.033547 | GR7: 0.05915 | GS7: 0.038366 | GT7: 0.03597 | GU7: 0.036037 | HC7: 辽宁 | HD7: 0.023981 | HE7: 0.025696 | HF7: 0.021504 | HG7: 0.027077 | HH7: 0.029677 | HP7: 吉林 | HQ7: 0.080683 | HR7: 0.089897 | HS7: 0.066341 | HT7: 0.10351 | HU7: 0.115802 | IC7: 黑龙江 | ID7: 0.078206 | IE7: 0.092747 | IF7: 0.088419 | IG7: 0.100213 | IH7: 0.113296 | IP7: 蒙东 | IQ7: 0.028325 | IR7: 0.039816 | IS7: 0.028878 | IT7: 0.02766 | IU7: 0.021105 | JC7: 陕西 | JD7: 0.0173 | JE7: 0.0226 | JF7: 0.0286 | JG7: 0.0333 | JH7: 0.0175 | JP7: 甘肃 | JQ7: 0.01103 | JR7: 0.030476 | JS7: 0.039871 | JT7: 0.09178 | JU7: 0.045256 | KC7: 青海 | KD7: 0.004757 | KE7: 0.008912 | KF7: 0.007392 | KG7: 0.007434 | KH7: 0.007514 | KP7: 宁夏 | KQ7: 0.013 | KR7: 0.0146 | KS7: 0.0138 | KT7: 0.0152 | KU7: 0.0134 | LC7: 新疆 | LD7: 0.024175 | LE7: 0.027753 | LF7: 0.023533 | LG7: 0.033739 | LH7: 0.028216 | LP7: 重庆 | LQ7: 0.026618 | LR7: 0.036812 | LS7: 0.027721 | LT7: 0.029228 | LU7: 0.027027 | MC7: 四川 | MD7: 0.007687 | ME7: 0.014157 | MF7: 0.010491 | MG7: 0.013274 | MH7: 0.009639 | MP7: 广东 | MQ7: 0.0424 | MR7: 0.068 | MS7: 0.0449 | MT7: 0.0404 | MU7: 0.0351 | NC7: 广西 | ND7: 0.024752 | NE7: 0.034366 | NF7: 0.024304 | NG7: 0.023169 | NH7: 0.022689 | NP7: 云南 | OC7: 贵州 | OE7: 0.025105 | OF7: 0.002093 | OG7: 0.01974 | OH7: 0.01485 | OP7: 海南 | OT7: 0.012875 | OU7: 0.007639
A8: 7 | B8: （6）天然气发电容量电费折合度电水平 | C8: 北京 | P8: 天津 | Q8: 0.021376 | R8: 0.030427 | S8: 0.021619 | T8: 0.028341 | U8: 0.025143 | AC8: 河北南网 | AD8: 0.001412 | AE8: 0.002046 | AF8: 0.001532 | AG8: 0.001785 | AH8: 0.001573 | AP8: 冀北 | AQ8: 0 | AR8: 0 | AS8: 0 | AT8: 0 | AU8: 0 | BC8: 山东 | BP8: 山西 | CC8: 蒙西 | CD8: 0.0002 | CE8: 0.0019 | CF8: 0.0002 | CG8: 0.0003 | CH8: 0.0002 | CP8: 上海 | CQ8: 0.0289 | CR8: 0.0289 | CS8: 0.0289 | CT8: 0.0289 | CU8: 0.0289 | DC8: 江苏 | DD8: 0.023 | DE8: 0.023 | DF8: 0.023 | DG8: 0.023 | DH8: 0.023 | DP8: 浙江 | DQ8: 0.00926 | DR8: 0.019595 | DS8: 0.009302 | DT8: 0.010371 | DU8: 0.009385 | EC8: 安徽 | ED8: 0.0027 | EE8: 0.0039 | EF8: 0.0029 | EG8: 0.0032 | EH8: 0.0029 | EP8: 福建 | FC8: 湖北 | FP8: 河南 | FQ8: 0.005675 | FR8: 0.007703 | FS8: 0.006172 | FT8: 0.006287 | FU8: 0.005909 | GC8: 湖南 | GP8: 江西 | HC8: 辽宁 | HP8: 吉林 | IC8: 黑龙江 | IP8: 蒙东 | JC8: 陕西 | JP8: 甘肃 | KC8: 青海 | KD8: 0.000475 | KE8: 0.000493 | KF8: 0.000493 | KG8: 0.000508 | KH8: 0.000494 | KP8: 宁夏 | LC8: 新疆 | LP8: 重庆 | LQ8: 0.012495 | LR8: 0.02024 | LS8: 0.020023 | LT8: 0.016309 | LU8: 0.016945 | MC8: 四川 | MD8: 0.009838 | ME8: 0.018334 | MF8: 0.012783 | MG8: 0.009295 | MH8: 0.00731 | MP8: 广东 | NC8: 广西 | NP8: 云南 | OC8: 贵州 | OP8: 海南
A9: 8 | B9: （7）水电合约价差损益折合度电水平 | C9: 北京 | P9: 天津 | AC9: 河北南网 | AP9: 冀北 | BC9: 山东 | BP9: 山西 | CC9: 蒙西 | CP9: 上海 | DC9: 江苏 | DP9: 浙江 | EC9: 安徽 | EP9: 福建 | FC9: 湖北 | FP9: 河南 | GC9: 湖南 | GP9: 江西 | HC9: 辽宁 | HP9: 吉林 | IC9: 黑龙江 | IP9: 蒙东 | JC9: 陕西 | JP9: 甘肃 | JQ9: 0.000646 | JR9: 0.000997 | JS9: -0.005008 | JT9: 0.003989 | JU9: 0.00021 | KC9: 青海 | KP9: 宁夏 | LC9: 新疆 | LP9: 重庆 | MC9: 四川 | MP9: 广东 | NC9: 广西 | NP9: 云南 | OC9: 贵州 | OP9: 海南
A10: 9 | B10: （8）独立储能容量电费折合度电水平 | C10: 北京 | P10: 天津 | AC10: 河北南网 | AD10: 0.000352 | AE10: 0.000591 | AF10: 0.001106 | AG10: 0.001085 | AH10: 0.001191 | AP10: 冀北 | AQ10: 0 | AR10: 0 | AS10: 0 | AT10: 0 | AU10: 0 | BC10: 山东 | BP10: 山西 | CC10: 蒙西 | CP10: 上海 | DC10: 江苏 | DP10: 浙江 | EC10: 安徽 | EP10: 福建 | FC10: 湖北 | FP10: 河南 | GC10: 湖南 | GP10: 江西 | HC10: 辽宁 | HP10: 吉林 | IC10: 黑龙江 | IP10: 蒙东 | JC10: 陕西 | JP10: 甘肃 | KC10: 青海 | KP10: 宁夏 | LC10: 新疆 | LD10: 0.002985 | LE10: 0.003531 | LF10: 0 | LG10: 0.000551 | LH10: 3e-06 | LP10: 重庆 | MC10: 四川 | MP10: 广东 | NC10: 广西 | NP10: 云南 | OC10: 贵州 | OP10: 海南
A11: 10 | B11: （9）容量补偿电价峰谷损益折合度电水平 | C11: 北京 | P11: 天津 | AC11: 河北南网 | AP11: 冀北 | BC11: 山东 | BD11: 0.0028 | BE11: 0.0067 | BF11: 0.0057 | BG11: 0.0049 | BH11: 0.0047 | BP11: 山西 | CC11: 蒙西 | CP11: 上海 | DC11: 江苏 | DP11: 浙江 | EC11: 安徽 | EP11: 福建 | FC11: 湖北 | FP11: 河南 | GC11: 湖南 | GP11: 江西 | HC11: 辽宁 | HP11: 吉林 | IC11: 黑龙江 | IP11: 蒙东 | JC11: 陕西 | JP11: 甘肃 | KC11: 青海 | KP11: 宁夏 | LC11: 新疆 | LP11: 重庆 | MC11: 四川 | MP11: 广东 | NC11: 广西 | NP11: 云南 | OC11: 贵州 | OP11: 海南
A12: 11 | B12: （10）工商业峰谷分时损益折合度电水平 | C12: 北京 | P12: 天津 | Q12: -0.013407 | R12: -0.025522 | S12: -0.008463 | T12: -0.001186 | U12: -0.00866 | AC12: 河北南网 | AP12: 冀北 | BC12: 山东 | BP12: 山西 | CC12: 蒙西 | CP12: 上海 | DC12: 江苏 | DD12: -0.0038 | DE12: -0.0036 | DF12: -0.0028 | DG12: 0.0005 | DH12: 0.0021 | DP12: 浙江 | DQ12: 0 | DR12: 0.08896 | DS12: 0 | DT12: 0 | DU12: 0 | EC12: 安徽 | ED12: 0.015 | EE12: 0.004 | EF12: -0.0063 | EG12: -0.0011 | EH12: 0.025 | EP12: 福建 | FC12: 湖北 | FP12: 河南 | GC12: 湖南 | GD12: -0.006572 | GE12: 0.001622 | GF12: 0.020775 | GG12: 0.019403 | GH12: -0.002431 | GP12: 江西 | GQ12: -0.015777 | GR12: -0.052576 | GS12: -0.020777 | GT12: -0.007881 | GU12: -0.01505 | HC12: 辽宁 | HD12: 0.001325 | HE12: 0.001847 | HF12: 0.002013 | HG12: 0.001588 | HH12: 0.001163 | HP12: 吉林 | HQ12: 0.001591 | HR12: 0.002885 | HS12: 0.002398 | HT12: 0.002368 | HU12: 0.001475 | IC12: 黑龙江 | IP12: 蒙东 | JC12: 陕西 | JP12: 甘肃 | KC12: 青海 | KD12: 0.001453 | KE12: 0.012893 | KF12: 0.010392 | KG12: 0.024726 | KH12: 0.008186 | KP12: 宁夏 | LC12: 新疆 | LP12: 重庆 | MC12: 四川 | MP12: 广东 | NC12: 广西 | NP12: 云南 | OC12: 贵州 | OE12: 0.026611 | OF12: 0.015694 | OG12: 0.018086 | OH12: 0.004145 | OP12: 海南
A13: 12 | B13: （11）功率因数调整电费损益折合度电水平 | C13: 北京 | D13: 0.006437 | E13: 0.006901 | F13: 0.006796 | G13: 0.006411 | H13: 0.006326 | P13: 天津 | Q13: 0.00407 | R13: 0.004699 | S13: 0.004338 | T13: 0.001654 | U13: 0.002356 | AC13: 河北南网 | AD13: 0.001521 | AE13: 0.002591 | AF13: 0.002686 | AG13: -0.000266 | AH13: 0.000696 | AP13: 冀北 | AQ13: 0.002856 | AR13: 0.002757 | AS13: 0.00272 | AT13: 0.001846 | AU13: 0.001865 | BC13: 山东 | BP13: 山西 | CC13: 蒙西 | CP13: 上海 | DC13: 江苏 | DD13: 0.0037 | DE13: 0.0035 | DF13: 0.0032 | DG13: 0.0024 | DH13: 0.0026 | DP13: 浙江 | EC13: 安徽 | ED13: 0.0013 | EE13: 0.0033 | EF13: 0.0026 | EG13: 0.0007 | EH13: 0.0022 | EP13: 福建 | FC13: 湖北 | FP13: 河南 | GC13: 湖南 | GD13: 0.002915 | GE13: 0.003501 | GF13: 0.001911 | GG13: 0.001243 | GH13: 0.002842 | GP13: 江西 | HC13: 辽宁 | HP13: 吉林 | IC13: 黑龙江 | IG13: 0 | IH13: 0 | IP13: 蒙东 | JC13: 陕西 | JP13: 甘肃 | KC13: 青海 | KD13: 0.002318 | KE13: 0.002654 | KF13: 0.002139 | KG13: 0.002189 | KH13: 0.002012 | KP13: 宁夏 | LC13: 新疆 | LP13: 重庆 | MC13: 四川 | MP13: 广东 | NC13: 广西 | NP13: 云南 | OC13: 贵州 | OP13: 海南
A14: 13 | B14: （12）新能源可持续发展价格结算机制差价结算费用折合度电水平 | C14: 北京 | D14: 0 | E14: 0 | F14: -0.000181 | G14: -0.000274 | H14: -0.000193 | P14: 天津 | Q14: -0.001684 | R14: -0.002255 | S14: -0.002541 | T14: -0.002936 | U14: -0.002527 | AC14: 河北南网 | AD14: 0.010742 | AE14: 0.014774 | AF14: 0.017237 | AG14: 0.058523 | AH14: 0.032584 | AP14: 冀北 | AQ14: -0.005183 | AR14: -0.004163 | AS14: -0.004757 | AT14: -0.005363 | AU14: -0.003425 | BC14: 山东 | BD14: 0.0576 | BE14: 0.0573 | BF14: 0.0741 | BG14: 0.0998 | BH14: 0.0621 | BP14: 山西 | BQ14: 0.034314 | BR14: 0.042364 | BS14: 0.052479 | BT14: 0.051744 | BU14: 0.051123 | CC14: 蒙西 | CD14: 0.0182 | CE14: 0.0138 | CF14: 0.0045 | CG14: 0.0186 | CH14: 0.0135 | CP14: 上海 | CQ14: -0.0039 | CR14: -0.001105 | CS14: 0.000525 | CT14: 0.003399 | CU14: -0.000777 | DC14: 江苏 | DD14: 0.0118 | DE14: 0.0194 | DF14: 0.0186 | DG14: 0.023 | DH14: 0.0188 | DP14: 浙江 | DQ14: 0.00608 | DR14: 0.010397 | DS14: 0.00548 | DT14: 0.021616 | DU14: 0.025542 | EC14: 安徽 | ED14: 0.0386 | EE14: 0.0412 | EF14: 0.0166 | EG14: 0.0351 | EH14: 0.0456 | EP14: 福建 | EQ14: 0.018401 | ER14: 0.01002 | ES14: -0.008233 | ET14: 0.007169 | EU14: 0.009416 | FC14: 湖北 | FD14: 0.019244 | FE14: 0.027002 | FF14: 0.012959 | FG14: 0.016481 | FH14: 0.019776 | FP14: 河南 | FQ14: 0.061704 | FR14: 0.046172 | FS14: 0.049873 | FT14: 0.110619 | FU14: 0.128481 | GC14: 湖南 | GD14: 0.008546 | GE14: 0.001597 | GF14: -0.004827 | GG14: 0.01114 | GH14: 0.058751 | GP14: 江西 | GQ14: 0.044702 | GR14: 0.066054 | GS14: 0.006637 | GT14: 0.022508 | GU14: 0.031012 | HC14: 辽宁 | HE14: 0.051352 | HF14: 0.105189 | HG14: 0.051298 | HH14: 0.020532 | HP14: 吉林 | HQ14: 0.017404 | HR14: 0.024872 | HS14: 0.031945 | HT14: 0.046945 | HU14: 0.031608 | IC14: 黑龙江 | ID14: 0.008477 | IE14: 0.020078 | IF14: 0.028064 | IG14: 0.055244 | IH14: 0.057071 | IP14: 蒙东 | IQ14: 0.043278 | IR14: 0.070214 | IS14: 0.077746 | IT14: 0.077961 | IU14: 0.034284 | JC14: 陕西 | JD14: 0.0484 | JE14: 0.0576 | JF14: 0.0507 | JG14: 0.0759 | JH14: 0.0887 | JP14: 甘肃 | JS14: 2e-06 | JT14: 6e-06 | JU14: 2.5e-05 | KC14: 青海 | KF14: 0.009855 | KG14: 0.02331 | KH14: 0.027025 | KP14: 宁夏 | KQ14: 0.0158 | KR14: 0.0254 | KS14: 0.0279 | KT14: 0.0311 | KU14: 0.014 | LC14: 新疆 | LD14: 0.028122 | LE14: 0.017461 | LF14: 0.022544 | LG14: 0.040359 | LH14: 0.053398 | LP14: 重庆 | LQ14: -0.003797 | LR14: -0.003424 | LS14: 0.003453 | LT14: 0.005705 | LU14: 0.005782 | MC14: 四川 | MD14: 0.008957 | ME14: 0.029609 | MF14: 0.011367 | MG14: 0.008079 | MH14: 0.012254 | MP14: 广东 | MQ14: 0.0148 | MR14: 0.044 | MS14: 0.0515 | MT14: 0.0354 | MU14: 0.015 | NC14: 广西 | ND14: 0.040482 | NE14: 0.064476 | NF14: 0.051476 | NG14: 0.042569 | NH14: 0.034909 | NP14: 云南 | OC14: 贵州 | OE14: 0 | OF14: 0.003882 | OG14: 0.003063 | OH14: -0.006437 | OP14: 海南 | OT14: 0.102083 | OU14: 0.101683
A15: 14 | B15: （13）绿电发展价格机制损益折合度电水平 | C15: 北京 | P15: 天津 | AC15: 河北南网 | AP15: 冀北 | BC15: 山东 | BP15: 山西 | CC15: 蒙西 | CP15: 上海 | DC15: 江苏 | DP15: 浙江 | EC15: 安徽 | EP15: 福建 | FC15: 湖北 | FP15: 河南 | GC15: 湖南 | GP15: 江西 | HC15: 辽宁 | HP15: 吉林 | IC15: 黑龙江 | IP15: 蒙东 | JC15: 陕西 | JP15: 甘肃 | KC15: 青海 | KD15: 0.002712 | KE15: 0.003705 | KF15: 0.002669 | KG15: 0.002478 | KH15: 0.002649 | KP15: 宁夏 | LC15: 新疆 | LD15: 0 | LE15: 0 | LF15: -0.000356 | LG15: 0 | LH15: 0 | LP15: 重庆 | MC15: 四川 | MP15: 广东 | NC15: 广西 | NP15: 云南 | OC15: 贵州 | OP15: 海南
A16: 15 | B16: （14）核电机制电价差价结算电费折合度电水平 | C16: 北京 | P16: 天津 | AC16: 河北南网 | AP16: 冀北 | BC16: 山东 | BP16: 山西 | CC16: 蒙西 | CP16: 上海 | DC16: 江苏 | DP16: 浙江 | EC16: 安徽 | EP16: 福建 | FC16: 湖北 | FP16: 河南 | GC16: 湖南 | GP16: 江西 | HC16: 辽宁 | HG16: 0.040801 | HH16: 0.069389 | HP16: 吉林 | IC16: 黑龙江 | IP16: 蒙东 | JC16: 陕西 | JP16: 甘肃 | KC16: 青海 | KP16: 宁夏 | LC16: 新疆 | LP16: 重庆 | MC16: 四川 | MP16: 广东 | NC16: 广西 | NE16: 0.032608 | NF16: 0.063234 | NG16: 0.026294 | NH16: 0.023974 | NP16: 云南 | OC16: 贵州 | OP16: 海南
A17: 16 | B17: （15）趸售电价损益折合度电水平 | C17: 北京 | P17: 天津 | AC17: 河北南网 | AP17: 冀北 | BC17: 山东 | BP17: 山西 | BQ17: 0.003629 | BR17: 0.004136 | BS17: 0.003257 | BT17: 0.002679 | BU17: 0.002026 | CC17: 蒙西 | CP17: 上海 | DC17: 江苏 | DP17: 浙江 | EC17: 安徽 | EP17: 福建 | FC17: 湖北 | FP17: 河南 | GC17: 湖南 | GP17: 江西 | HC17: 辽宁 | HP17: 吉林 | HQ17: 0.001344 | HR17: 0.001659 | HS17: 0.000943 | HT17: 0.000622 | HU17: 0.00038 | IC17: 黑龙江 | IP17: 蒙东 | JC17: 陕西 | JP17: 甘肃 | KC17: 青海 | KP17: 宁夏 | LC17: 新疆 | LP17: 重庆 | MC17: 四川 | MP17: 广东 | NC17: 广西 | NP17: 云南 | OC17: 贵州 | OP17: 海南
A18: 17 | B18: （16）代理购电价格新增损益折合度电水平 | C18: 北京 | P18: 天津 | AC18: 河北南网 | AP18: 冀北 | BC18: 山东 | BP18: 山西 | CC18: 蒙西 | CP18: 上海 | DC18: 江苏 | DP18: 浙江 | EC18: 安徽 | EP18: 福建 | FC18: 湖北 | FP18: 河南 | GC18: 湖南 | GP18: 江西 | HC18: 辽宁 | HP18: 吉林 | HQ18: 0.009948 | HR18: 0.018936 | HS18: 0.00455 | HT18: -0.005253 | HU18: 0.014541 | IC18: 黑龙江 | IP18: 蒙东 | JC18: 陕西 | JP18: 甘肃 | KC18: 青海 | KP18: 宁夏 | LC18: 新疆 | LP18: 重庆 | MC18: 四川 | MP18: 广东 | NC18: 广西 | NP18: 云南 | OC18: 贵州 | OP18: 海南
A19: 18 | B19: （17）成本补偿费用（现货）分摊折合度电水平 | C19: 北京 | P19: 天津 | AC19: 河北南网 | AP19: 冀北 | BC19: 山东 | BP19: 山西 | CC19: 蒙西 | CP19: 上海 | DC19: 江苏 | DP19: 浙江 | DQ19: 3e-06 | DR19: 4e-06 | DS19: 0 | DT19: 1.6e-05 | DU19: 0 | EC19: 安徽 | EP19: 福建 | FC19: 湖北 | FP19: 河南 | GC19: 湖南 | GP19: 江西 | HC19: 辽宁 | HP19: 吉林 | IC19: 黑龙江 | IP19: 蒙东 | JC19: 陕西 | JP19: 甘肃 | JS19: 0.002058 | JT19: 0.004733 | JU19: 0.004355 | KC19: 青海 | KP19: 宁夏 | LC19: 新疆 | LP19: 重庆 | MC19: 四川 | MP19: 广东 | NC19: 广西 | NP19: 云南 | OC19: 贵州 | OP19: 海南
A20: 19 | B20: （18）跨省跨区应急调度价差损益折合度电水平 | C20: 北京 | P20: 天津 | Q20: 0 | R20: 0 | S20: 0 | T20: 0 | U20: 0 | AC20: 河北南网 | AP20: 冀北 | BC20: 山东 | BP20: 山西 | CC20: 蒙西 | CP20: 上海 | DC20: 江苏 | DP20: 浙江 | EC20: 安徽 | EP20: 福建 | FC20: 湖北 | FP20: 河南 | GC20: 湖南 | GP20: 江西 | HC20: 辽宁 | HD20: 0 | HE20: 0 | HF20: 0 | HG20: 0 | HH20: 0 | HP20: 吉林 | IC20: 黑龙江 | IP20: 蒙东 | JC20: 陕西 | JP20: 甘肃 | JU20: 0 | KC20: 青海 | KP20: 宁夏 | LC20: 新疆 | LD20: 0 | LE20: 4.4e-05 | LF20: 6e-05 | LG20: -6.1e-05 | LH20: 0 | LP20: 重庆 | MC20: 四川 | MD20: 0 | ME20: -0.000166 | MF20: 0 | MG20: 0 | MH20: 0 | MP20: 广东 | NC20: 广西 | NP20: 云南 | OC20: 贵州 | OP20: 海南
A21: 20 | B21: （19）电力保障综合费用折合度电水平 | C21: 北京 | P21: 天津 | AC21: 河北南网 | AP21: 冀北 | BC21: 山东 | BP21: 山西 | CC21: 蒙西 | CP21: 上海 | CQ21: 0 | CR21: 0.002042 | CS21: 0 | CT21: 0 | CU21: 0 | DC21: 江苏 | DD21: 0 | DE21: 0.0001 | DF21: 0.0001 | DG21: 0 | DH21: 0 | DP21: 浙江 | EC21: 安徽 | EP21: 福建 | FC21: 湖北 | FP21: 河南 | GC21: 湖南 | GP21: 江西 | HC21: 辽宁 | HP21: 吉林 | IC21: 黑龙江 | IP21: 蒙东 | JC21: 陕西 | JP21: 甘肃 | KC21: 青海 | KP21: 宁夏 | LC21: 新疆 | LP21: 重庆 | MC21: 四川 | MP21: 广东 | NC21: 广西 | NP21: 云南 | OC21: 贵州 | OP21: 海南
A22: 21 | B22: （20）地方电网减免电费损益折合度电水平 | C22: 北京 | P22: 天津 | AC22: 河北南网 | AP22: 冀北 | BC22: 山东 | BP22: 山西 | CC22: 蒙西 | CP22: 上海 | DC22: 江苏 | DP22: 浙江 | EC22: 安徽 | EP22: 福建 | FC22: 湖北 | FP22: 河南 | GC22: 湖南 | GD22: 0.004933 | GE22: 0.007461 | GF22: 0.001629 | GG22: 0.006607 | GH22: 0.002629 | GP22: 江西 | HC22: 辽宁 | HP22: 吉林 | IC22: 黑龙江 | IP22: 蒙东 | JC22: 陕西 | JP22: 甘肃 | KC22: 青海 | KP22: 宁夏 | LC22: 新疆 | LP22: 重庆 | MC22: 四川 | MP22: 广东 | NC22: 广西 | NP22: 云南 | OC22: 贵州 | OP22: 海南
A23: 22 | B23: （21）剩余优先发电价差损益度电水平 | C23: 北京 | P23: 天津 | AC23: 河北南网 | AP23: 冀北 | BC23: 山东 | BP23: 山西 | CC23: 蒙西 | CP23: 上海 | DC23: 江苏 | DP23: 浙江 | EC23: 安徽 | EP23: 福建 | FC23: 湖北 | FD23: 0.006762 | FE23: 0.00485 | FF23: 0.004538 | FG23: 0.002046 | FH23: -0.003934 | FP23: 河南 | GC23: 湖南 | GP23: 江西 | HC23: 辽宁 | HP23: 吉林 | IC23: 黑龙江 | IP23: 蒙东 | JC23: 陕西 | JP23: 甘肃 | KC23: 青海 | KP23: 宁夏 | LC23: 新疆 | LP23: 重庆 | MC23: 四川 | MP23: 广东 | NC23: 广西 | NP23: 云南 | OC23: 贵州 | OE23: 0.018164 | OF23: 0.001106 | OG23: -0.000626 | OH23: -0.018048 | OP23: 海南
A24: 23 | B24: （22）其他费用折合度电水平 | C24: 北京 | D24: -0.0089 | E24: -0.0089 | F24: -0.0089 | G24: -0.0089 | H24: -0.0089 | P24: 天津 | AC24: 河北南网 | AD24: 0 | AE24: 0 | AF24: 0 | AG24: 0 | AH24: 0 | AP24: 冀北 | AQ24: 0 | AR24: 0 | AS24: 0 | AT24: 0 | AU24: 0 | BC24: 山东 | BP24: 山西 | CC24: 蒙西 | CP24: 上海 | DC24: 江苏 | DP24: 浙江 | EC24: 安徽 | EP24: 福建 | EQ24: 0.005891 | ER24: 0.007833 | ES24: 0.008334 | ET24: 0.009375 | EU24: 0.002561 | FC24: 湖北 | FP24: 河南 | FQ24: 0 | FR24: 0 | FS24: 0 | FT24: 0 | FU24: 0 | GC24: 湖南 | GD24: 0 | GE24: 0 | GF24: 0 | GG24: 0 | GH24: 0 | GP24: 江西 | GQ24: -0.03442 | GR24: -0.057529 | GS24: 0.023293 | GT24: -0.006832 | GU24: 0.001174 | HC24: 辽宁 | HP24: 吉林 | IC24: 黑龙江 | ID24: 0 | IE24: 0 | IF24: 0 | IG24: 0 | IH24: 0 | IP24: 蒙东 | JC24: 陕西 | JD24: 0 | JE24: 0 | JF24: 0 | JG24: 0 | JH24: 0 | JP24: 甘肃 | KC24: 青海 | KP24: 宁夏 | KQ24: 0 | KR24: 0 | KS24: 0 | KT24: 0 | KU24: 0 | LC24: 新疆 | LP24: 重庆 | LQ24: 0.008585 | LR24: 0.012105 | LS24: 0.015681 | LT24: 0.010857 | LU24: 0.009472 | MC24: 四川 | MP24: 广东 | NC24: 广西 | ND24: -9.2e-05 | NE24: 0.001501 | NF24: -0.000376 | NG24: -0.000172 | NH24: -0.000226 | NP24: 云南 | OC24: 贵州 | OE24: -0.068142 | OF24: 0.008885 | OG24: 0.023617 | OH24: 0.060434 | OP24: 海南 | OT24: -0.03935 | OU24: -0.043

Sheet 分表4-电度输配电价
A1: 序号 | B1: 省份 | C1: 单一/两部制 | D1: 电压等级 | E1: 输配电价
A2: 1 | B2: 北京 | C2: 单一制 | D2: 10kV | E2: 0.39
A3: 2 | B3: 北京 | C3: 单一制 | D3: 35kV | E3: 0.32
A4: 3 | B4: 北京 | C4: 单一制 | D4: 110kV | E4: 0.32
A5: 4 | B5: 北京 | C5: 单一制 | D5: 220kV | E5: 0.275
A6: 5 | B6: 北京 | C6: 两部制 | D6: 10kV | E6: 0.2065
A7: 6 | B7: 北京 | C7: 两部制 | D7: 35kV | E7: 0.166
A8: 7 | B8: 北京 | C8: 两部制 | D8: 110kV | E8: 0.166
A9: 8 | B9: 北京 | C9: 两部制 | D9: 220kV | E9: 0.151
A10: 9 | B10: 天津 | C10: 单一制 | D10: 10kV | E10: 0.251
A11: 10 | B11: 天津 | C11: 单一制 | D11: 35kV | E11: 0.1866
A12: 11 | B12: 天津 | C12: 单一制 | D12: 110kV | E12: 0.1536
A13: 12 | B13: 天津 | C13: 单一制 | D13: 220kV | E13: 0.1316
... A27: 26 | B27: 冀北 | C27: 单一制 | D27: 35kV | E27: 0.1282
A28: 27 | B28: 冀北 | C28: 单一制 | D28: 110kV | E28: /
A29: 28 | B29: 冀北 | C29: 单一制 | D29: 220kV | E29: /
A30: 29 | B30: 冀北 | C30: 两部制 | D30: 10kV | E30: 0.1292
A31: 30 | B31: 冀北 | C31: 两部制 | D31: 35kV | E31: 0.1132
A32: 31 | B32: 冀北 | C32: 两部制 | D32: 110kV | E32: 0.0972
A33: 32 | B33: 冀北 | C33: 两部制 | D33: 220kV | E33: 0.0912
A34: 33 | B34: 山东 | C34: 单一制 | D34: 10kV | E34: 0.2069
A35: 34 | B35: 山东 | C35: 单一制 | D35: 35kV | E35: 0.1919
A36: 35 | B36: 山东 | C36: 单一制 | D36: 110kV | E36: 0.1919
A37: 36 | B37: 山东 | C37: 单一制 | D37: 220kV | E37: 0.1919
A38: 37 | B38: 山东 | C38: 两部制 | D38: 10kV | E38: 0.1491
A39: 38 | B39: 山东 | C39: 两部制 | D39: 35kV | E39: 0.1341
A40: 39 | B40: 山东 | C40: 两部制 | D40: 110kV | E40: 0.1191
A41: 40 | B41: 山东 | C41: 两部制 | D41: 220kV | E41: 0.1041
... A43: 42 | B43: 山西 | C43: 单一制 | D43: 35kV | E43: 0.1106
A44: 43 | B44: 山西 | C44: 单一制 | D44: 110kV | E44: /
A45: 44 | B45: 山西 | C45: 单一制 | D45: 220kV | E45: /
A46: 45 | B46: 山西 | C46: 两部制 | D46: 10kV | E46: 0.104
A47: 46 | B47: 山西 | C47: 两部制 | D47: 35kV | E47: 0.074
A48: 47 | B48: 山西 | C48: 两部制 | D48: 110kV | E48: 0.049
A49: 48 | B49: 山西 | C49: 两部制 | D49: 220kV | E49: 0.029
A50: 49 | B50: 蒙西 | C50: 单一制 | D50: 10kV | E50: 0.1289
A51: 50 | B51: 蒙西 | C51: 单一制 | D51: 35kV | E51: 0.1139
A52: 51 | B52: 蒙西 | C52: 单一制 | D52: 110kV | E52: /
A53: 52 | B53: 蒙西 | C53: 单一制 | D53: 220kV | E53: /
A54: 53 | B54: 蒙西 | C54: 两部制 | D54: 10kV | E54: 0.0795
A55: 54 | B55: 蒙西 | C55: 两部制 | D55: 35kV | E55: 0.0645
A56: 55 | B56: 蒙西 | C56: 两部制 | D56: 110kV | E56: 0.0525
A57: 56 | B57: 蒙西 | C57: 两部制 | D57: 220kV | E57: 0.0455
A58: 57 | B58: 上海 | C58: 单一制 | D58: 10kV | E58: 0.2305
A59: 58 | B59: 上海 | C59: 单一制 | D59: 35kV | E59: 0.1859
A60: 59 | B60: 上海 | C60: 单一制 | D60: 110kV | E60: /
A61: 60 | B61: 上海 | C61: 单一制 | D61: 220kV | E61: /
A62: 61 | B62: 上海 | C62: 两部制 | D62: 10kV | E62: 0.2039
A63: 62 | B63: 上海 | C63: 两部制 | D63: 35kV | E63: 0.1547
A64: 63 | B64: 上海 | C64: 两部制 | D64: 110kV | E64: 0.1251
A65: 64 | B65: 上海 | C65: 两部制 | D65: 220kV | E65: 0.1127
A66: 65 | B66: 江苏 | C66: 单一制 | D66: 10kV | E66: 0.2134
A67: 66 | B67: 江苏 | C67: 单一制 | D67: 35kV | E67: 0.1884
A68: 67 | B68: 江苏 | C68: 单一制 | D68: 110kV | E68: /
A69: 68 | B69: 江苏 | C69: 单一制 | D69: 220kV | E69: /
A70: 69 | B70: 江苏 | C70: 两部制 | D70: 10kV | E70: 0.1357
A71: 70 | B71: 江苏 | C71: 两部制 | D71: 35kV | E71: 0.1107
A72: 71 | B72: 江苏 | C72: 两部制 | D72: 110kV | E72: 0.0857
A73: 72 | B73: 江苏 | C73: 两部制 | D73: 220kV | E73: 0.0597
A74: 73 | B74: 浙江 | C74: 单一制 | D74: 10kV | E74: 0.2144
A75: 74 | B75: 浙江 | C75: 单一制 | D75: 35kV | E75: 0.177
A76: 75 | B76: 浙江 | C76: 单一制 | D76: 110kV | E76: /
A77: 76 | B77: 浙江 | C77: 单一制 | D77: 220kV | E77: /
A78: 77 | B78: 浙江 | C78: 两部制 | D78: 10kV | E78: 0.126
A79: 78 | B79: 浙江 | C79: 两部制 | D79: 35kV | E79: 0.0955
A80: 79 | B80: 浙江 | C80: 两部制 | D80: 110kV | E80: 0.0791
A81: 80 | B81: 浙江 | C81: 两部制 | D81: 220kV | E81: 0.0688
A82: 81 | B82: 安徽 | C82: 单一制 | D82: 10kV | E82: 0.1614
A83: 82 | B83: 安徽 | C83: 单一制 | D83: 35kV | E83: 0.1414
A84: 83 | B84: 安徽 | C84: 单一制 | D84: 110kV | E84: /
A85: 84 | B85: 安徽 | C85: 单一制 | D85: 220kV | E85: /
A86: 85 | B86: 安徽 | C86: 两部制 | D86: 10kV | E86: 0.1428
A87: 86 | B87: 安徽 | C87: 两部制 | D87: 35kV | E87: 0.1175
A88: 87 | B88: 安徽 | C88: 两部制 | D88: 110kV | E88: 0.0924
A89: 88 | B89: 安徽 | C89: 两部制 | D89: 220kV | E89: 0.0673
A90: 89 | B90: 福建 | C90: 单一制 | D90: 10kV | E90: 0.1633
A91: 90 | B91: 福建 | C91: 单一制 | D91: 35kV | E91: 0.1433
A92: 91 | B92: 福建 | C92: 单一制 | D92: 110kV | E92: 0.1233
A93: 92 | B93: 福建 | C93: 单一制 | D93: 220kV | E93: 0.1033
A94: 93 | B94: 福建 | C94: 两部制 | D94: 10kV | E94: 0.1292
A95: 94 | B95: 福建 | C95: 两部制 | D95: 35kV | E95: 0.1092
A96: 95 | B96: 福建 | C96: 两部制 | D96: 110kV | E96: 0.0842
A97: 96 | B97: 福建 | C97: 两部制 | D97: 220kV | E97: 0.0592
... A99: 98 | B99: 湖北 | C99: 单一制 | D99: 35kV | E99: 0.1703
A100: 99 | B100: 湖北 | C100: 单一制 | D100: 110kV | E100: /
A101: 100 | B101: 湖北 | C101: 单一制 | D101: 220kV | E101: /
A102: 101 | B102: 湖北 | C102: 两部制 | D102: 10kV | E102: 0.1263
A103: 102 | B103: 湖北 | C103: 两部制 | D103: 35kV | E103: 0.1065
A104: 103 | B104: 湖北 | C104: 两部制 | D104: 110kV | E104: 0.0884
A105: 104 | B105: 湖北 | C105: 两部制 | D105: 220kV | E105: 0.0694
A106: 105 | B106: 河南 | C106: 单一制 | D106: 10kV | E106: 0.168
A107: 106 | B107: 河南 | C107: 单一制 | D107: 35kV | E107: 0.1412
A108: 107 | B108: 河南 | C108: 单一制 | D108: 110kV | E108: 0.1145
A109: 108 | B109: 河南 | C109: 单一制 | D109: 220kV | E109: 0.1145
A110: 109 | B110: 河南 | C110: 两部制 | D110: 10kV | E110: 0.168
A111: 110 | B111: 河南 | C111: 两部制 | D111: 35kV | E111: 0.1456
A112: 111 | B112: 河南 | C112: 两部制 | D112: 110kV | E112: 0.121
A113: 112 | B113: 河南 | C113: 两部制 | D113: 220kV | E113: 0.103
... A123: 122 | B123: 江西 | C123: 单一制 | D123: 35kV | E123: 0.1466
A124: 123 | B124: 江西 | C124: 单一制 | D124: 110kV | E124: /
...

Sheet 分表5-政府性基金及附加
A1: 序号 | B1: 省份 | C1: 区域电网 | D1: 政府性基金及附加
A2: 1 | B2: 北京 | C2: 华北电网 | D2: 0.02716875
A3: 2 | B3: 天津 | C3: 华北电网 | D3: 0.02716875
A4: 3 | B4: 河北南网 | C4: 华北电网 | D4: 0.02406875
A5: 4 | B5: 冀北 | C5: 华北电网 | D5: 0.02406875
A6: 5 | B6: 山东 | C6: 华北电网 | D6: 0.02716875
A7: 6 | B7: 山西 | C7: 华北电网 | D7: 0.04336875
A8: 7 | B8: 蒙西 | C8: 蒙西电网 | D8: 0.022425
A9: 8 | B9: 上海 | C9: 华中电网 | D9: 0.029115
A10: 9 | B10: 江苏 | C10: 华中电网 | D10: 0.0294
A11: 10 | B11: 浙江 | C11: 华中电网 | D11: 0.02923875
A12: 11 | B12: 安徽 | C12: 华中电网 | D12: 0.02887
A13: 12 | B13: 福建 | C13: 华中电网 | D13: 0.02766875
... A33: 32 | B33: 海南 | C33: 南方电网 | D33: 0.026825

Sheet 分表6-容(需)量电价
A1: 序号 | B1: 省份 | C1: 电压等级 | D1: 最大需量电价（元/千瓦·月） | E1: 变压器容量电价（元/千伏安·月）
A2: 1 | B2: 北京 | C2: 10kV | D2: 51 | E2: 32
A3: 2 | B3: 北京 | C3: 35kV | D3: 48 | E3: 30
A4: 3 | B4: 北京 | C4: 110kV | D4: 48 | E4: 30
A5: 4 | B5: 北京 | C5: 220kV | D5: 45 | E5: 28
A6: 5 | B6: 天津 | C6: 10kV | D6: 41.6 | E6: 26
A7: 6 | B7: 天津 | C7: 35kV | D7: 38.4 | E7: 24
A8: 7 | B8: 天津 | C8: 110kV | D8: 38.4 | E8: 24
A9: 8 | B9: 天津 | C9: 220kV | D9: 35.2 | E9: 22
A10: 9 | B10: 河北南网 | C10: 10kV | D10: 35 | E10: 21.9
A11: 10 | B11: 河北南网 | C11: 35kV | D11: 35 | E11: 21.9
A12: 11 | B12: 河北南网 | C12: 110kV | D12: 32 | E12: 20
A13: 12 | B13: 河北南网 | C13: 220kV | D13: 32 | E13: 20
... A66: 65 | B66: 辽宁 | C66: 10kV | D66: 36.8 | E66: 23
A67: 66 | B67: 辽宁 | C67: 35kV | D67: / | E67: /
A68: 67 | B68: 辽宁 | C68: 110kV | D68: 35.2 | E68: 22
A69: 68 | B69: 辽宁 | C69: 220kV | D69: 33.6 | E69: 21
A70: 69 | B70: 吉林 | C70: 10kV | D70: 36.8 | E70: 23
A71: 70 | B71: 吉林 | C71: 35kV
A72: 71 | B72: 吉林 | C72: 110kV | D72: 35.2 | E72: 22
A73: 72 | B73: 吉林 | C73: 220kV | D73: 35.2 | E73: 22
A74: 73 | B74: 黑龙江 | C74: 10kV | D74: 36.8 | E74: 23
A75: 74 | B75: 黑龙江 | C75: 35kV | D75: 36.8 | E75: 23
A76: 75 | B76: 黑龙江 | C76: 110kV | D76: 35.2 | E76: 22
A77: 76 | B77: 黑龙江 | C77: 220kV | D77: 35.2 | E77: 22
A78: 77 | B78: 蒙东 | C78: 10kV | D78: 32.8 | E78: 20.5
A79: 78 | B79: 蒙东 | C79: 35kV | D79: 32.8 | E79: 20.5
A80: 79 | B80: 蒙东 | C80: 110kV | D80: 31.2 | E80: 19.5
A81: 80 | B81: 蒙东 | C81: 220kV | D81: 31.2 | E81: 19.5
A82: 81 | B82: 陕西 | C82: 10kV | D82: 35.2 | E82: 22
A83: 82 | B83: 陕西 | C83: 35kV | D83: 35.2 | E83: 22
... A129: 96 | B129: 海南 | C129: 220kV | D129: 35.2 | E129: 22

Sheet 分表7-2026交易价格
A1: 序号 | B1: 省份 | C1: 2026年入市购电电价表 | D1: 1月 | E1: 2月 | F1: 3月 | G1: 4月 | H1: 5月 | I1: 6月 | J1: 7月 | K1: 8月 | L1: 9月 | M1: 10月 | N1: 11月 | O1: 12月 | P1: 年均 | Q1: 趋势图
A2: 1 | B2: 北京 | C2: 入市购电价格 | D2: 0.39 | E2: =D2 | F2: =E2 | G2: =F2 | H2: =G2 | I2: =H2 | J2: =I2 | K2: =J2 | L2: =K2 | ... O2: =N2 | P2: =IF(SUM(D2:O2)=0,"0",AVERAGEIF(D2:O2,"<>0",D2:O2))
A3: 2 | B3: 天津 | C3: 入市购电价格 | P3: =IF(SUM(D3:O3)=0,"0",AVERAGEIF(D3:O3,"<>0",D3:O3))
A4: 3 | B4: 河北南网 | C4: 入市购电价格 | P4: =IF(SUM(D4:O4)=0,"0",AVERAGEIF(D4:O4,"<>0",D4:O4))
A5: 4 | B5: 冀北 | C5: 入市购电价格 | D5: 0.385 | E5: =D5 | F5: =E5 | G5: =F5 | H5: =G5 | I5: =H5 | J5: =I5 | K5: =J5 | L5: =K5 | ... O5: =N5 | P5: =IF(SUM(D5:O5)=0,"0",AVERAGEIF(D5:O5,"<>0",D5:O5))
A6: 5 | B6: 山东 | C6: 入市购电价格 | P6: =IF(SUM(D6:O6)=0,"0",AVERAGEIF(D6:O6,"<>0",D6:O6))
A7: 6 | B7: 山西 | C7: 入市购电价格 | P7: =IF(SUM(D7:O7)=0,"0",AVERAGEIF(D7:O7,"<>0",D7:O7))
A8: 7 | B8: 蒙西 | C8: 入市购电价格 | D8: 0.281 | E8: 0.281 | F8: 0.281 | G8: 0.281 | H8: 0.281 | I8: 0.281 | J8: 0.281 | K8: 0.281 | L8: 0.281 | M8: 0.281 | N8: 0.281 | O8: 0.281 | P8: =IF(SUM(D8:O8)=0,"0",AVERAGEIF(D8:O8,"<>0",D8:O8))
A9: 8 | B9: 上海 | C9: 入市购电价格 | D9: 0.3937 | E9: =D9 | F9: =E9 | G9: =F9 | H9: =G9 | I9: =H9 | J9: =I9 | K9: =J9 | L9: =K9 | ... O9: =N9 | P9: =IF(SUM(D9:O9)=0,"0",AVERAGEIF(D9:O9,"<>0",D9:O9))
A10: 9 | B10: 江苏 | C10: 入市购电价格 | D10: 0.3349 | E10: =D10 | F10: =E10 | G10: =F10 | H10: =G10 | I10: =H10 | J10: =I10 | K10: =J10 | L10: =K10 | ... O10: =N10 | P10: =IF(SUM(D10:O10)=0,"0",AVERAGEIF(D10:O10,"<>0",D10:O10))
A11: 10 | B11: 浙江 | C11: 入市购电价格 | P11: =IF(SUM(D11:O11)=0,"0",AVERAGEIF(D11:O11,"<>0",D11:O11))
A12: 11 | B12: 安徽 | C12: 入市购电价格 | D12: 0.3858 | E12: =D12 | F12: =E12 | G12: =F12 | H12: =G12 | I12: =H12 | J12: =I12 | K12: =J12 | L12: =K12 | ... O12: =N12 | P12: =IF(SUM(D12:O12)=0,"0",AVERAGEIF(D12:O12,"<>0",D12:O12))
A13: 12 | B13: 福建 | C13: 入市购电价格 | P13: =IF(SUM(D13:O13)=0,"0",AVERAGEIF(D13:O13,"<>0",D13:O13))
A14: 13 | B14: 湖北 | C14: 入市购电价格 | P14: =IF(SUM(D14:O14)=0,"0",AVERAGEIF(D14:O14,"<>0",D14:O14))
A15: 14 | B15: 河南 | C15: 入市购电价格 | P15: =IF(SUM(D15:O15)=0,"0",AVERAGEIF(D15:O15,"<>0",D15:O15))
A16: 15 | B16: 湖南 | C16: 入市购电价格 | P16: =IF(SUM(D16:O16)=0,"0",AVERAGEIF(D16:O16,"<>0",D16:O16))
A17: 16 | B17: 江西 | C17: 入市购电价格 | P17: =IF(SUM(D17:O17)=0,"0",AVERAGEIF(D17:O17,"<>0",D17:O17))
A18: 17 | B18: 辽宁 | C18: 入市购电价格 | P18: =IF(SUM(D18:O18)=0,"0",AVERAGEIF(D18:O18,"<>0",D18:O18))
A19: 18 | B19: 吉林 | C19: 入市购电价格 | P19: =IF(SUM(D19:O19)=0,"0",AVERAGEIF(D19:O19,"<>0",D19:O19))
A20: 19 | B20: 黑龙江 | C20: 入市购电价格 | P20: =IF(SUM(D20:O20)=0,"0",AVERAGEIF(D20:O20,"<>0",D20:O20))
A21: 20 | B21: 蒙东 | C21: 入市购电价格 | P21: =IF(SUM(D21:O21)=0,"0",AVERAGEIF(D21:O21,"<>0",D21:O21))
A22: 21 | B22: 陕西 | C22: 入市购电价格 | D22: 0.37 | E22: 0.37 | F22: 0.37 | G22: 0.37 | H22: 0.37 | I22: 0.37 | J22: 0.37 | K22: 0.37 | L22: 0.37 | M22: 0.37 | N22: 0.37 | O22: 0.37 | P22: =IF(SUM(D22:O22)=0,"0",AVERAGEIF(D22:O22,"<>0",D22:O22))
A23: 22 | B23: 甘肃 | C23: 入市购电价格 | P23: =IF(SUM(D23:O23)=0,"0",AVERAGEIF(D23:O23,"<>0",D23:O23))
A24: 23 | B24: 青海 | C24: 入市购电价格 | P24: =IF(SUM(D24:O24)=0,"0",AVERAGEIF(D24:O24,"<>0",D24:O24))
A25: 24 | B25: 宁夏 | C25: 入市购电价格 | P25: =IF(SUM(D25:O25)=0,"0",AVERAGEIF(D25:O25,"<>0",D25:O25))
A26: 25 | B26: 新疆 | C26: 入市购电价格 | P26: =IF(SUM(D26:O26)=0,"0",AVERAGEIF(D26:O26,"<>0",D26:O26))
A27: 26 | B27: 重庆 | C27: 入市购电价格 | P27: =IF(SUM(D27:O27)=0,"0",AVERAGEIF(D27:O27,"<>0",D27:O27))
A28: 27 | B28: 四川 | C28: 入市购电价格 | P28: =IF(SUM(D28:O28)=0,"0",AVERAGEIF(D28:O28,"<>0",D28:O28))
A29: 28 | B29: 广东 | C29: 入市购电价格 | D29: 0.372 | E29: 0.372 | F29: 0.372 | G29: 0.372 | H29: 0.372 | I29: 0.372 | J29: 0.372 | K29: 0.372 | L29: 0.372 | M29: 0.372 | N29: 0.372 | O29: 0.372 | P29: =IF(SUM(D29:O29)=0,"0",AVERAGEIF(D29:O29,"<>0",D29:O29))
A30: 29 | B30: 广西 | C30: 入市购电价格 | P30: =IF(SUM(D30:O30)=0,"0",AVERAGEIF(D30:O30,"<>0",D30:O30))
A31: 30 | B31: 云南 | C31: 入市购电价格 | P31: =IF(SUM(D31:O31)=0,"0",AVERAGEIF(D31:O31,"<>0",D31:O31))
A32: 31 | B32: 贵州 | C32: 入市购电价格 | P32: =IF(SUM(D32:O32)=0,"0",AVERAGEIF(D32:O32,"<>0",D32:O32))
A33: 32 | B33: 海南 | C33: 入市购电价格 | P33: =IF(SUM(D33:O33)=0,"0",AVERAGEIF(D33:O33,"<>0",D33:O33))

Sheet 总表-2025
B1: 电压等级 | C1: ='首页+选择功能'!B4 | Q1: 单一制10kV
A2: 序号 | B2: 省份 | C2: 2025年电价表 | D2: 1月 | E2: 2月 | F2: 3月 | G2: 4月 | H2: 5月 | I2: 6月 | J2: 7月 | K2: 8月 | L2: 9月 | M2: 10月 | N2: 11月 | O2: 12月 | P2: 年均 | Q2: 趋势图
A3: 1 | B3: 北京 | C3: 代理购电价格 | D3: ='分表8-2025三类细分价'!D2 | E3: ='分表8-2025三类细分价'!E2 | F3: ='分表8-2025三类细分价'!F2 | G3: ='分表8-2025三类细分价'!G2 | H3: ='分表8-2025三类细分价'!H2 | I3: ='分表8-2025三类细分价'!I2 | J3: ='分表8-2025三类细分价'!J2 | K3: ='分表8-2025三类细分价'!K2 | ... O3: ='分表8-2025三类细分价'!O2 | P3: =IF(SUM(D3:O3)=0,"0",AVERAGEIF(D3:O3,"<>0",D3:O3))
A4: 2 | B4: 北京 | C4: 上网环节线损电价 | D4: ='分表8-2025三类细分价'!D5 | E4: ='分表8-2025三类细分价'!E5 | F4: ='分表8-2025三类细分价'!F5 | G4: ='分表8-2025三类细分价'!G5 | H4: ='分表8-2025三类细分价'!H5 | I4: ='分表8-2025三类细分价'!I5 | J4: ='分表8-2025三类细分价'!J5 | K4: ='分表8-2025三类细分价'!K5 | ... O4: ='分表8-2025三类细分价'!O5 | P4: =IF(SUM(D4:O4)=0,"0",AVERAGEIF(D4:O4,"<>0",D4:O4))
A5: 3 | B5: 北京 | C5: 电度输配电价 | D5: {=_xlfn.XLOOKUP($C$1,'分表4-电度输配电价'!$C2：'分表4-电度输配电价'!$C9&'分表4-电度输配电价'!$D2：'分表4-电度输配电价'!$D9,'分表4-电度输配电价'!$E2：'分表4-电度输配电价'!$E9)} | E5: {=_xlfn.XLOOKUP($C$1,'分表4-电度输配电价'!$C2：'分表4-电度输配电价'!$C9&'分表4-电度输配电价'!$D2：'分表4-电度输配电价'!$D9,'分表4-电度输配电价'!$E2：'分表4-电度输配电价'!$E9)} | F5: {=_xlfn.XLOOKUP($C$1,'分表4-电度输配电价'!$C2：'分表4-电度输配电价'!$C9&'分表4-电度输配电价'!$D2：'分表4-电度输配电价'!$D9,'分表4-电度输配电价'!$E2：'分表4-电度输配电价'!$E9)} | G5: {=_xlfn.XLOOKUP($C$1,'分表4-电度输配电价'!$C2：'分表4-电度输配电价'!$C9&'分表4-电度输配电价'!$D2：'分表4-电度输配电价'!$D9,'分表4-电度输配电价'!$E2：'分表4-电度输配电价'!$E9)} | H5: {=_xlfn.XLOOKUP($C$1,'分表4-电度输配电价'!$C2：'分表4-电度输配电价'!$C9&'分表4-电度输配电价'!$D2：'分表4-电度输配电价'!$D9,'分表4-电度输配电价'!$E2：'分表4-电度输配电价'!$E9)} | I5: {=_xlfn.XLOOKUP($C$1,'分表4-电度输配电价'!$C2：'分表4-电度输配电价'!$C9&'分表4-电度输配电价'!$D2：'分表4-电度输配电价'!$D9,'分表4-电度输配电价'!$E2：'分表4-电度输配电价'!$E9)} | J5: {=_xlfn.XLOOKUP($C$1,'分表4-电度输配电价'!$C2：'分表4-电度输配电价'!$C9&'分表4-电度输配电价'!$D2：'分表4-电度输配电价'!$D9,'分表4-电度输配电价'!$E2：'分表4-电度输配电价'!$E9)} | K5: {=_xlfn.XLOOKUP($C$1,'分表4-电度输配电价'!$C2：'分表4-电度输配电价'!$C9&'分表4-电度输配电价'!$D2：'分表4-电度输配电价'!$D9,'分表4-电度输配电价'!$E2：'分表4-电度输配电价'!$E9)} | ... O5: {=_xlfn.XLOOKUP($C$1,'分表4-电度输配电价'!$C2：'分表4-电度输配电价'!$C9&'分表4-电度输配电价'!$D2：'分表4-电度输配电价'!$D9,'分表4-电度输配电价'!$E2：'分表4-电度输配电价'!$E9)} | P5: =IF(SUM(D5:O5)=0,"0",AVERAGEIF(D5:O5,"<>0",D5:O5))
A6: 4 | B6: 北京 | C6: 政府性基金及附加 | D6: {=_xlfn.XLOOKUP($B$6,'分表5-政府性基金及附加'!$B$2：'分表5-政府性基金及附加'!$B$199,'分表5-政府性基金及附加'!$D$2：'分表5-政府性基金及附加'!$D$199)} | E6: {=_xlfn.XLOOKUP($B$6,'分表5-政府性基金及附加'!$B$2：'分表5-政府性基金及附加'!$B$199,'分表5-政府性基金及附加'!$D$2：'分表5-政府性基金及附加'!$D$199)} | F6: {=_xlfn.XLOOKUP($B$6,'分表5-政府性基金及附加'!$B$2：'分表5-政府性基金及附加'!$B$199,'分表5-政府性基金及附加'!$D$2：'分表5-政府性基金及附加'!$D$199)} | G6: {=_xlfn.XLOOKUP($B$6,'分表5-政府性基金及附加'!$B$2：'分表5-政府性基金及附加'!$B$199,'分表5-政府性基金及附加'!$D$2：'分表5-政府性基金及附加'!$D$199)} | H6: {=_xlfn.XLOOKUP($B$6,'分表5-政府性基金及附加'!$B$2：'分表5-政府性基金及附加'!$B$199,'分表5-政府性基金及附加'!$D$2：'分表5-政府性基金及附加'!$D$199)} | I6: {=_xlfn.XLOOKUP($B$6,'分表5-政府性基金及附加'!$B$2：'分表5-政府性基金及附加'!$B$199,'分表5-政府性基金及附加'!$D$2：'分表5-政府性基金及附加'!$D$199)} | J6: {=_xlfn.XLOOKUP($B$6,'分表5-政府性基金及附加'!$B$2：'分表5-政府性基金及附加'!$B$199,'分表5-政府性基金及附加'!$D$2：'分表5-政府性基金及附加'!$D$199)} | K6: {=_xlfn.XLOOKUP($B$6,'分表5-政府性基金及附加'!$B$2：'分表5-政府性基金及附加'!$B$199,'分表5-政府性基金及附加'!$D$2：'分表5-政府性基金及附加'!$D$199)} | ... O6: {=_xlfn.XLOOKUP($B$6,'分表5-政府性基金及附加'!$B$2：'分表5-政府性基金及附加'!$B$199,'分表5-政府性基金及附加'!$D$2：'分表5-政府性基金及附加'!$D$199)} | P6: =IF(SUM(D6:O6)=0,"0",AVERAGEIF(D6:O6,"<>0",D6:O6))
A7: 5 | B7: 北京 | C7: 系统运行费折价 | D7: ='分表8-2025三类细分价'!D6 | E7: ='分表8-2025三类细分价'!E6 | F7: ='分表8-2025三类细分价'!F6 | G7: ='分表8-2025三类细分价'!G6 | H7: ='分表8-2025三类细分价'!H6 | I7: ='分表8-2025三类细分价'!I6 | J7: ='分表8-2025三类细分价'!J6 | K7: ='分表8-2025三类细分价'!K6 | ... O7: ='分表8-2025三类细分价'!O6 | P7: =IF(SUM(D7:O7)=0,"0",AVERAGEIF(D7:O7,"<>0",D7:O7))
A8: 6 | B8: 北京 | C8: 综合平段电价--电网代购 | D8: =IF(D5="/","/",SUM(D3:D7)) | E8: =IF(E5="/","/",SUM(E3:E7)) | F8: =IF(F5="/","/",SUM(F3:F7)) | G8: =IF(G5="/","/",SUM(G3:G7)) | H8: =IF(H5="/","/",SUM(H3:H7)) | I8: =IF(I5="/","/",SUM(I3:I7)) | J8: =IF(J5="/","/",SUM(J3:J7)) | K8: =IF(K5="/","/",SUM(K3:K7)) | ... O8: =IF(O5="/","/",SUM(O3:O7)) | P8: =IF(SUM(D8:O8)=0,"0",AVERAGEIF(D8:O8,"<>0",D8:O8))
A9: 7 | B9: 北京 | C9: 入市交易购电价格 | D9: ='分表9-2025交易价格'!D2 | E9: ='分表9-2025交易价格'!E2 | F9: ='分表9-2025交易价格'!F2 | G9: ='分表9-2025交易价格'!G2 | H9: ='分表9-2025交易价格'!H2 | I9: ='分表9-2025交易价格'!I2 | J9: ='分表9-2025交易价格'!J2 | K9: ='分表9-2025交易价格'!K2 | ... O9: ='分表9-2025交易价格'!O2 | P9: =IF(SUM(D9:O9)=0,"0",AVERAGEIF(D9:O9,"<>0",D9:O9))
A10: 8 | B10: 北京 | C10: 综合平段电价--入市交易 | D10: =IF(D5="/","/",IF(D9>0,D9+SUM(D4:D7),"/")) | E10: =IF(E5="/","/",IF(E9>0,E9+SUM(E4:E7),"/")) | F10: =IF(F5="/","/",IF(F9>0,F9+SUM(F4:F7),"/")) | G10: =IF(G5="/","/",IF(G9>0,G9+SUM(G4:G7),"/")) | H10: =IF(H5="/","/",IF(H9>0,H9+SUM(H4:H7),"/")) | I10: =IF(I5="/","/",IF(I9>0,I9+SUM(I4:I7),"/")) | J10: =IF(J5="/","/",IF(J9>0,J9+SUM(J4:J7),"/")) | K10: =IF(K5="/","/",IF(K9>0,K9+SUM(K4:K7),"/")) | ... O10: =IF(O5="/","/",IF(O9>0,O9+SUM(O4:O7),"/")) | P10: =IF(SUM(D10:O10)=0,"0",AVERAGEIF(D10:O10,"<>0",D10:O10))
A11: 9 | B11: 天津 | C11: 代理购电价格 | D11: ='分表8-2025三类细分价'!D23 | E11: ='分表8-2025三类细分价'!E23 | F11: ='分表8-2025三类细分价'!F23 | G11: ='分表8-2025三类细分价'!G23 | H11: ='分表8-2025三类细分价'!H23 | I11: ='分表8-2025三类细分价'!I23 | J11: ='分表8-2025三类细分价'!J23 | K11: ='分表8-2025三类细分价'!K23 | ... O11: ='分表8-2025三类细分价'!O23 | P11: =IF(SUM(D11:O11)=0,"0",AVERAGEIF(D11:O11,"<>0",D11:O11))
A12: 10 | B12: 天津 | C12: 上网环节线损电价 | D12: ='分表8-2025三类细分价'!D26 | E12: ='分表8-2025三类细分价'!E26 | F12: ='分表8-2025三类细分价'!F26 | G12: ='分表8-2025三类细分价'!G26 | H12: ='分表8-2025三类细分价'!H26 | I12: ='分表8-2025三类细分价'!I26 | J12: ='分表8-2025三类细分价'!J26 | K12: ='分表8-2025三类细分价'!K26 | ... O12: ='分表8-2025三类细分价'!O26 | P12: =IF(SUM(D12:O12)=0,"0",AVERAGEIF(D12:O12,"<>0",D12:O12))
A13: 11 | B13: 天津 | C13: 电度输配电价 | D13: {=_xlfn.XLOOKUP($C$1,'分表4-电度输配电价'!$C10：'分表4-电度输配电价'!$C17&'分表4-电度输配电价'!$D10：'分表4-电度输配电价'!$D17,'分表4-电度输配电价'!$E10：'分表4-电度输配电价'!$E17)} | E13: {=_xlfn.XLOOKUP($C$1,'分表4-电度输配电价'!$C10：'分表4-电度输配电价'!$C17&'分表4-电度输配电价'!$D10：'分表4-电度输配电价'!$D17,'分表4-电度输配电价'!$E10：'分表4-电度输配电价'!$E17)} | F13: {=_xlfn.XLOOKUP($C$1,'分表4-电度输配电价'!$C10：'分表4-电度输配电价'!$C17&'分表4-电度输配电价'!$D10：'分表4-电度输配电价'!$D17,'分表4-电度输配电价'!$E10：'分表4-电度输配电价'!$E17)} | G13: {=_xlfn.XLOOKUP($C$1,'分表4-电度输配电价'!$C10：'分表4-电度输配电价'!$C17&'分表4-电度输配电价'!$D10：'分表4-电度输配电价'!$D17,'分表4-电度输配电价'!$E10：'分表4-电度输配电价'!$E17)} | H13: {=_xlfn.XLOOKUP($C$1,'分表4-电度输配电价'!$C10：'分表4-电度输配电价'!$C17&'分表4-电度输配电价'!$D10：'分表4-电度输配电价'!$D17,'分表4-电度输配电价'!$E10：'分表4-电度输配电价'!$E17)} | I13: {=_xlfn.XLOOKUP($C$1,'分表4-电度输配电价'!$C10：'分表4-电度输配电价'!$C17&'分表4-电度输配电价'!$D10：'分表4-电度输配电价'!$D17,'分表4-电度输配电价'!$E10：'分表4-电度输配电价'!$E17)} | J13: {=_xlfn.XLOOKUP($C$1,'分表4-电度输配电价'!$C10：'分表4-电度输配电价'!$C17&'分表4-电度输配电价'!$D10：'分表4-电度输配电价'!$D17,'分表4-电度输配电价'!$E10：'分表4-电度输配电价'!$E17)} | K13: {=_xlfn.XLOOKUP($C$1,'分表4-电度输配电价'!$C10：'分表4-电度输配电价'!$C17&'分表4-电度输配电价'!$D10：'分表4-电度输配电价'!$D17,'分表4-电度输配电价'!$E10：'分表4-电度输配电价'!$E17)} | ... O13: {=_xlfn.XLOOKUP($C$1,'分表4-电度输配电价'!$C10：'分表4-电度输配电价'!$C17&'分表4-电度输配电价'!$D10：'分表4-电度输配电价'!$D17,'分表4-电度输配电价'!$E10：'分表4-电度输配电价'!$E17)} | P13: =IF(SUM(D13:O13)=0,"0",AVERAGEIF(D13:O13,"<>0",D13:O13))
A14: 12 | B14: 天津 | C14: 政府性基金及附加 | D14: {=_xlfn.XLOOKUP($B$14,'分表5-政府性基金及附加'!$B$2：'分表5-政府性基金及附加'!$B$199,'分表5-政府性基金及附加'!$D$2：'分表5-政府性基金及附加'!$D$199)} | E14: {=_xlfn.XLOOKUP($B$14,'分表5-政府性基金及附加'!$B$2：'分表5-政府性基金及附加'!$B$199,'分表5-政府性基金及附加'!$D$2：'分表5-政府性基金及附加'!$D$199)} | F14: {=_xlfn.XLOOKUP($B$14,'分表5-政府性基金及附加'!$B$2：'分表5-政府性基金及附加'!$B$199,'分表5-政府性基金及附加'!$D$2：'分表5-政府性基金及附加'!$D$199)} | G14: {=_xlfn.XLOOKUP($B$14,'分表5-政府性基金及附加'!$B$2：'分表5-政府性基金及附加'!$B$199,'分表5-政府性基金及附加'!$D$2：'分表5-政府性基金及附加'!$D$199)} | H14: {=_xlfn.XLOOKUP($B$14,'分表5-政府性基金及附加'!$B$2：'分表5-政府性基金及附加'!$B$199,'分表5-政府性基金及附加'!$D$2：'分表5-政府性基金及附加'!$D$199)} | I14: {=_xlfn.XLOOKUP($B$14,'分表5-政府性基金及附加'!$B$2：'分表5-政府性基金及附加'!$B$199,'分表5-政府性基金及附加'!$D$2：'分表5-政府性基金及附加'!$D$199)} | J14: {=_xlfn.XLOOKUP($B$14,'分表5-政府性基金及附加'!$B$2：'分表5-政府性基金及附加'!$B$199,'分表5-政府性基金及附加'!$D$2：'分表5-政府性基金及附加'!$D$199)} | K14: {=_xlfn.XLOOKUP($B$14,'分表5-政府性基金及附加'!$B$2：'分表5-政府性基金及附加'!$B$199,'分表5-政府性基金及附加'!$D$2：'分表5-政府性基金及附加'!$D$199)} | ... O14: {=_xlfn.XLOOKUP($B$14,'分表5-政府性基金及附加'!$B$2：'分表5-政府性基金及附加'!$B$199,'分表5-政府性基金及附加'!$D$2：'分表5-政府性基金及附加'!$D$199)} | P14: =IF(SUM(D14:O14)=0,"0",AVERAGEIF(D14:O14,"<>0",D14:O14))
A15: 13 | B15: 天津 | C15: 系统运行费折价 | D15: ='分表8-2025三类细分价'!D27 | E15: ='分表8-2025三类细分价'!E27 | F15: ='分表8-2025三类细分价'!F27 | G15: ='分表8-2025三类细分价'!G27 | H15: ='分表8-2025三类细分价'!H27 | I15: ='分表8-2025三类细分价'!I27 | J15: ='分表8-2025三类细分价'!J27 | K15: ='分表8-2025三类细分价'!K27 | ... O15: ='分表8-2025三类细分价'!O27 | P15: =IF(SUM(D15:O15)=0,"0",AVERAGEIF(D15:O15,"<>0",D15:O15))
A16: 14 | B16: 天津 | C16: 综合平段电价--电网代购 | D16: =IF(D13="/","/",SUM(D11:D15)) | E16: =IF(E13="/","/",SUM(E11:E15)) | F16: =IF(F13="/","/",SUM(F11:F15)) | G16: =IF(G13="/","/",SUM(G11:G15)) | H16: =IF(H13="/","/",SUM(H11:H15)) | I16: =IF(I13="/","/",SUM(I11:I15)) | J16: =IF(J13="/","/",SUM(J11:J15)) | K16: =IF(K13="/","/",SUM(K11:K15)) | ... O16: =IF(O13="/","/",SUM(O11:O15)) | P16: =IF(SUM(D16:O16)=0,"0",AVERAGEIF(D16:O16,"<>0",D16:O16))
A17: 15 | B17: 天津 | C17: 入市交易购电价格 | D17: ='分表9-2025交易价格'!D3 | E17: ='分表9-2025交易价格'!E3 | F17: ='分表9-2025交易价格'!F3 | G17: ='分表9-2025交易价格'!G3 | H17: ='分表9-2025交易价格'!H3 | I17: ='分表9-2025交易价格'!I3 | J17: ='分表9-2025交易价格'!J3 | K17: ='分表9-2025交易价格'!K3 | ... O17: ='分表9-2025交易价格'!O3 | P17: =IF(SUM(D17:O17)=0,"0",AVERAGEIF(D17:O17,"<>0",D17:O17))
A18: 16 | B18: 天津 | C18: 综合平段电价--入市交易 | D18: =IF(D13="/","/",IF(D17>0,D17+SUM(D12:D15),"/")) | E18: =IF(E13="/","/",IF(E17>0,E17+SUM(E12:E15),"/")) | F18: =IF(F13="/","/",IF(F17>0,F17+SUM(F12:F15),"/")) | G18: =IF(G13="/","/",IF(G17>0,G17+SUM(G12:G15),"/")) | H18: =IF(H13="/","/",IF(H17>0,H17+SUM(H12:H15),"/")) | I18: =IF(I13="/","/",IF(I17>0,I17+SUM(I12:I15),"/")) | J18: =IF(J13="/","/",IF(J17>0,J17+SUM(J12:J15),"/")) | K18: =IF(K13="/","/",IF(K17>0,K17+SUM(K12:K15),"/")) | ... O18: =IF(O13="/","/",IF(O17>0,O17+SUM(O12:O15),"/")) | P18: =IF(SUM(D18:O18)=0,"0",AVERAGEIF(D18:O18,"<>0",D18:O18))
A19: 17 | B19: 河北南网 | C19: 代理购电价格 | D19: ='分表8-2025三类细分价'!D44 | E19: ='分表8-2025三类细分价'!E44 | F19: ='分表8-2025三类细分价'!F44 | G19: ='分表8-2025三类细分价'!G44 | H19: ='分表8-2025三类细分价'!H44 | I19: ='分表8-2025三类细分价'!I44 | J19: ='分表8-2025三类细分价'!J44 | K19: ='分表8-2025三类细分价'!K44 | ... O19: ='分表8-2025三类细分价'!O44 | P19: =IF(SUM(D19:O19)=0,"0",AVERAGEIF(D19:O19,"<>0",D19:O19))
A20: 18 | B20: 河北南网 | C20: 上网环节线损电价 | D20: ='分表8-2025三类细分价'!D47 | E20: ='分表8-2025三类细分价'!E47 | F20: ='分表8-2025三类细分价'!F47 | G20: ='分表8-2025三类细分价'!G47 | H20: ='分表8-2025三类细分价'!H47 | I20: ='分表8-2025三类细分价'!I47 | J20: ='分表8-2025三类细分价'!J47 | K20: ='分表8-2025三类细分价'!K47 | ... O20: ='分表8-2025三类细分价'!O47 | P20: =IF(SUM(D20:O20)=0,"0",AVERAGEIF(D20:O20,"<>0",D20:O20))
A21: 19 | B21: 河北南网 | C21: 电度输配电价 | D21: {=_xlfn.XLOOKUP($C$1,'分表4-电度输配电价'!$C18：'分表4-电度输配电价'!$C25&'分表4-电度输配电价'!$D18：'分表4-电度输配电价'!$D25,'分表4-电度输配电价'!$E18：'分表4-电度输配电价'!$E25)} | E21: {=_xlfn.XLOOKUP($C$1,'分表4-电度输配电价'!$C18：'分表4-电度输配电价'!$C25&'分表4-电度输配电价'!$D18：'分表4-电度输配电价'!$D25,'分表4-电度输配电价'!$E18：'分表4-电度输配电价'!$E25)} | F21: {=_xlfn.XLOOKUP($C$1,'分表4-电度输配电价'!$C18：'分表4-电度输配电价'!$C25&'分表4-电度输配电价'!$D18：'分表4-电度输配电价'!$D25,'分表4-电度输配电价'!$E18：'分表4-电度输配电价'!$E25)} | G21: {=_xlfn.XLOOKUP($C$1,'分表4-电度输配电价'!$C18：'分表4-电度输配电价'!$C25&'分表4-电度输配电价'!$D18：'分表4-电度输配电价'!$D25,'分表4-电度输配电价'!$E18：'分表4-电度输配电价'!$E25)} | H21: {=_xlfn.XLOOKUP($C$1,'分表4-电度输配电价'!$C18：'分表4-电度输配电价'!$C25&'分表4-电度输配电价'!$D18：'分表4-电度输配电价'!$D25,'分表4-电度输配电价'!$E18：'分表4-电度输配电价'!$E25)} | I21: {=_xlfn.XLOOKUP($C$1,'分表4-电度输配电价'!$C18：'分表4-电度输配电价'!$C25&'分表4-电度输配电价'!$D18：'分表4-电度输配电价'!$D25,'分表4-电度输配电价'!$E18：'分表4-电度输配电价'!$E25)} | J21: {=_xlfn.XLOOKUP($C$1,'分表4-电度输配电价'!$C18：'分表4-电度输配电价'!$C25&'分表4-电度输配电价'!$D18：'分表4-电度输配电价'!$D25,'分表4-电度输配电价'!$E18：'分表4-电度输配电价'!$E25)} | K21: {=_xlfn.XLOOKUP($C$1,'分表4-电度输配电价'!$C18：'分表4-电度输配电价'!$C25&'分表4-电度输配电价'!$D18：'分表4-电度输配电价'!$D25,'分表4-电度输配电价'!$E18：'分表4-电度输配电价'!$E25)} | ... O21: {=_xlfn.XLOOKUP($C$1,'分表4-电度输配电价'!$C18：'分表4-电度输配电价'!$C25&'分表4-电度输配电价'!$D18：'分表4-电度输配电价'!$D25,'分表4-电度输配电价'!$E18：'分表4-电度输配电价'!$E25)} | P21: =IF(SUM(D21:O21)=0,"0",AVERAGEIF(D21:O21,"<>0",D21:O21))
A22: 20 | B22: 河北南网 | C22: 政府性基金及附加 | D22: {=_xlfn.XLOOKUP($B$22,'分表5-政府性基金及附加'!$B$2：'分表5-政府性基金及附加'!$B$199,'分表5-政府性基金及附加'!$D$2：'分表5-政府性基金及附加'!$D$199)} | E22: {=_xlfn.XLOOKUP($B$22,'分表5-政府性基金及附加'!$B$2：'分表5-政府性基金及附加'!$B$199,'分表5-政府性基金及附加'!$D$2：'分表5-政府性基金及附加'!$D$199)} | F22: {=_xlfn.XLOOKUP($B$22,'分表5-政府性基金及附加'!$B$2：'分表5-政府性基金及附加'!$B$199,'分表5-政府性基金及附加'!$D$2：'分表5-政府性基金及附加'!$D$199)} | G22: {=_xlfn.XLOOKUP($B$22,'分表5-政府性基金及附加'!$B$2：'分表5-政府性基金及附加'!$B$199,'分表5-政府性基金及附加'!$D$2：'分表5-政府性基金及附加'!$D$199)} | H22: {=_xlfn.XLOOKUP($B$22,'分表5-政府性基金及附加'!$B$2：'分表5-政府性基金及附加'!$B$199,'分表5-政府性基金及附加'!$D$2：'分表5-政府性基金及附加'!$D$199)} | I22: {=_xlfn.XLOOKUP($B$22,'分表5-政府性基金及附加'!$B$2：'分表5-政府性基金及附加'!$B$199,'分表5-政府性基金及附加'!$D$2：'分表5-政府性基金及附加'!$D$199)} | J22: {=_xlfn.XLOOKUP($B$22,'分表5-政府性基金及附加'!$B$2：'分表5-政府性基金及附加'!$B$199,'分表5-政府性基金及附加'!$D$2：'分表5-政府性基金及附加'!$D$199)} | K22: {=_xlfn.XLOOKUP($B$22,'分表5-政府性基金及附加'!$B$2：'分表5-政府性基金及附加'!$B$199,'分表5-政府性基金及附加'!$D$2：'分表5-政府性基金及附加'!$D$199)} | ... O22: {=_xlfn.XLOOKUP($B$22,'分表5-政府性基金及附加'!$B$2：'分表5-政府性基金及附加'!$B$199,'分表5-政府性基金及附加'!$D$2：'分表5-政府性基金及附加'!$D$199)} | P22: =IF(SUM(D22:O22)=0,"0",AVERAGEIF(D22:O22,"<>0",D22:O22))
A23: 21 | B23: 河北南网 | C23: 系统运行费折价 | D23: ='分表8-2025三类细分价'!D48 | E23: ='分表8-2025三类细分价'!E48 | F23: ='分表8-2025三类细分价'!F48 | G23: ='分表8-2025三类细分价'!G48 | H23: ='分表8-2025三类细分价'!H48 | I23: ='分表8-2025三类细分价'!I48 | J23: ='分表8-2025三类细分价'!J48 | K23: ='分表8-2025三类细分价'!K48 | ... O23: ='分表8-2025三类细分价'!O48 | P23: =IF(SUM(D23:O23)=0,"0",AVERAGEIF(D23:O23,"<>0",D23:O23))
A24: 22 | B24: 河北南网 | C24: 综合平段电价--电网代购 | D24: =IF(D21="/","/",SUM(D19:D23)) | E24: =IF(E21="/","/",SUM(E19:E23)) | F24: =IF(F21="/","/",SUM(F19:F23)) | G24: =IF(G21="/","/",SUM(G19:G23)) | H24: =IF(H21="/","/",SUM(H19:H23)) | I24: =IF(I21="/","/",SUM(I19:I23)) | J24: =IF(J21="/","/",SUM(J19:J23)) | K24: =IF(K21="/","/",SUM(K19:K23)) | ... O24: =IF(O21="/","/",SUM(O19:O23)) | P24: =IF(SUM(D24:O24)=0,"0",AVERAGEIF(D24:O24,"<>0",D24:O24))
A25: 23 | B25: 河北南网 | C25: 入市交易购电价格 | D25: ='分表9-2025交易价格'!D4 | E25: ='分表9-2025交易价格'!E4 | F25: ='分表9-2025交易价格'!F4 | G25: ='分表9-2025交易价格'!G4 | H25: ='分表9-2025交易价格'!H4 | I25: ='分表9-2025交易价格'!I4 | J25: ='分表9-2025交易价格'!J4 | K25: ='分表9-2025交易价格'!K4 | ... O25: ='分表9-2025交易价格'!O4 | P25: =IF(SUM(D25:O25)=0,"0",AVERAGEIF(D25:O25,"<>0",D25:O25))
A26: 24 | B26: 河北南网 | C26: 综合平段电价--入市交易 | D26: =IF(D21="/","/",IF(D25>0,D25+SUM(D20:D23),"/")) | E26: =IF(E21="/","/",IF(E25>0,E25+SUM(E20:E23),"/")) | F26: =IF(F21="/","/",IF(F25>0,F25+SUM(F20:F23),"/")) | G26: =IF(G21="/","/",IF(G25>0,G25+SUM(G20:G23),"/")) | H26: =IF(H21="/","/",IF(H25>0,H25+SUM(H20:H23),"/")) | I26: =IF(I21="/","/",IF(I25>0,I25+SUM(I20:I23),"/")) | J26: =IF(J21="/","/",IF(J25>0,J25+SUM(J20:J23),"/")) | K26: =IF(K21="/","/",IF(K25>0,K25+SUM(K20:K23),"/")) | ... O26: =IF(O21="/","/",IF(O25>0,O25+SUM(O20:O23),"/")) | P26: =IF(SUM(D26:O26)=0,"0",AVERAGEIF(D26:O26,"<>0",D26:O26))
A27: 25 | B27: 冀北 | C27: 代理购电价格 | D27: ='分表8-2025三类细分价'!D65 | E27: ='分表8-2025三类细分价'!E65 | F27: ='分表8-2025三类细分价'!F65 | G27: ='分表8-2025三类细分价'!G65 | H27: ='分表8-2025三类细分价'!H65 | I27: ='分表8-2025三类细分价'!I65 | J27: ='分表8-2025三类细分价'!J65 | K27: ='分表8-2025三类细分价'!K65 | ... O27: ='分表8-2025三类细分价'!O65 | P27: =IF(SUM(D27:O27)=0,"0",AVERAGEIF(D27:O27,"<>0",D27:O27))
A28: 26 | B28: 冀北 | C28: 上网环节线损电价 | D28: ='分表8-2025三类细分价'!D68 | E28: ='分表8-2025三类细分价'!E68 | F28: ='分表8-2025三类细分价'!F68 | G28: ='分表8-2025三类细分价'!G68 | H28: ='分表8-2025三类细分价'!H68 | I28: ='分表8-2025三类细分价'!I68 | J28: ='分表8-2025三类细分价'!J68 | K28: ='分表8-2025三类细分价'!K68 | ... O28: ='分表8-2025三类细分价'!O68 | P28: =IF(SUM(D28:O28)=0,"0",AVERAGEIF(D28:O28,"<>0",D28:O28))
A29: 27 | B29: 冀北 | C29: 电度输配电价 | D29: {=_xlfn.XLOOKUP($C$1,'分表4-电度输配电价'!$C26：'分表4-电度输配电价'!$C33&'分表4-电度输配电价'!$D26：'分表4-电度输配电价'!$D33,'分表4-电度输配电价'!$E26：'分表4-电度输配电价'!$E33)} | E29: {=_xlfn.XLOOKUP($C$1,'分表4-电度输配电价'!$C26：'分表4-电度输配电价'!$C33&'分表4-电度输配电价'!$D26：'分表4-电度输配电价'!$D33,'分表4-电度输配电价'!$E26：'分表4-电度输配电价'!$E33)} | F29: {=_xlfn.XLOOKUP($C$1,'分表4-电度输配电价'!$C26：'分表4-电度输配电价'!$C33&'分表4-电度输配电价'!$D26：'分表4-电度输配电价'!$D33,'分表4-电度输配电价'!$E26：'分表4-电度输配电价'!$E33)} | G29: {=_xlfn.XLOOKUP($C$1,'分表4-电度输配电价'!$C26：'分表4-电度输配电价'!$C33&'分表4-电度输配电价'!$D26：'分表4-电度输配电价'!$D33,'分表4-电度输配电价'!$E26：'分表4-电度输配电价'!$E33)} | H29: {=_xlfn.XLOOKUP($C$1,'分表4-电度输配电价'!$C26：'分表4-电度输配电价'!$C33&'分表4-电度输配电价'!$D26：'分表4-电度输配电价'!$D33,'分表4-电度输配电价'!$E26：'分表4-电度输配电价'!$E33)} | I29: {=_xlfn.XLOOKUP($C$1,'分表4-电度输配电价'!$C26：'分表4-电度输配电价'!$C33&'分表4-电度输配电价'!$D26：'分表4-电度输配电价'!$D33,'分表4-电度输配电价'!$E26：'分表4-电度输配电价'!$E33)} | J29: {=_xlfn.XLOOKUP($C$1,'分表4-电度输配电价'!$C26：'分表4-电度输配电价'!$C33&'分表4-电度输配电价'!$D26：'分表4-电度输配电价'!$D33,'分表4-电度输配电价'!$E26：'分表4-电度输配电价'!$E33)} | K29: {=_xlfn.XLOOKUP($C$1,'分表4-电度输配电价'!$C26：'分表4-电度输配电价'!$C33&'分表4-电度输配电价'!$D26：'分表4-电度输配电价'!$D33,'分表4-电度输配电价'!$E26：'分表4-电度输配电价'!$E33)} | ... O29: {=_xlfn.XLOOKUP($C$1,'分表4-电度输配电价'!$C26：'分表4-电度输配电价'!$C33&'分表4-电度输配电价'!$D26：'分表4-电度输配电价'!$D33,'分表4-电度输配电价'!$E26：'分表4-电度输配电价'!$E33)} | P29: =IF(SUM(D29:O29)=0,"0",AVERAGEIF(D29:O29,"<>0",D29:O29))
A30: 28 | B30: 冀北 | C30: 政府性基金及附加 | D30: {=_xlfn.XLOOKUP($B$30,'分表5-政府性基金及附加'!$B$2：'分表5-政府性基金及附加'!$B$199,'分表5-政府性基金及附加'!$D$2：'分表5-政府性基金及附加'!$D$199)} | E30: {=_xlfn.XLOOKUP($B$30,'分表5-政府性基金及附加'!$B$2：'分表5-政府性基金及附加'!$B$199,'分表5-政府性基金及附加'!$D$2：'分表5-政府性基金及附加'!$D$199)} | F30: {=_xlfn.XLOOKUP($B$30,'分表5-政府性基金及附加'!$B$2：'分表5-政府性基金及附加'!$B$199,'分表5-政府性基金及附加'!$D$2：'分表5-政府性基金及附加'!$D$199)} | G30: {=_xlfn.XLOOKUP($B$30,'分表5-政府性基金及附加'!$B$2：'分表5-政府性基金及附加'!$B$199,'分表5-政府性基金及附加'!$D$2：'分表5-政府性基金及附加'!$D$199)} | H30: {=_xlfn.XLOOKUP($B$30,'分表5-政府性基金及附加'!$B$2：'分表5-政府性基金及附加'!$B$199,'分表5-政府性基金及附加'!$D$2：'分表5-政府性基金及附加'!$D$199)} | I30: {=_xlfn.XLOOKUP($B$30,'分表5-政府性基金及附加'!$B$2：'分表5-政府性基金及附加'!$B$199,'分表5-政府性基金及附加'!$D$2：'分表5-政府性基金及附加'!$D$199)} | J30: {=_xlfn.XLOOKUP($B$30,'分表5-政府性基金及附加'!$B$2：'分表5-政府性基金及附加'!$B$199,'分表5-政府性基金及附加'!$D$2：'分表5-政府性基金及附加'!$D$199)} | K30: {=_xlfn.XLOOKUP($B$30,'分表5-政府性基金及附加'!$B$2：'分表5-政府性基金及附加'!$B$199,'分表5-政府性基金及附加'!$D$2：'分表5-政府性基金及附加'!$D$199)} | ... O30: {=_xlfn.XLOOKUP($B$30,'分表5-政府性基金及附加'!$B$2：'分表5-政府性基金及附加'!$B$199,'分表5-政府性基金及附加'!$D$2：'分表5-政府性基金及附加'!$D$199)} | P30: =IF(SUM(D30:O30)=0,"0",AVERAGEIF(D30:O30,"<>0",D30:O30))
A31: 29 | B31: 冀北 | C31: 系统运行费折价 | D31: ='分表8-2025三类细分价'!D69 | E31: ='分表8-2025三类细分价'!E69 | F31: ='分表8-2025三类细分价'!F69 | G31: ='分表8-2025三类细分价'!G69 | H31: ='分表8-2025三类细分价'!H69 | I31: ='分表8-2025三类细分价'!I69 | J31: ='分表8-2025三类细分价'!J69 | K31: ='分表8-2025三类细分价'!K69 | ... O31: ='分表8-2025三类细分价'!O69 | P31: =IF(SUM(D31:O31)=0,"0",AVERAGEIF(D31:O31,"<>0",D31:O31))
A32: 30 | B32: 冀北 | C32: 综合平段电价--电网代购 | D32: =IF(D29="/","/",SUM(D27:D31)) | E32: =IF(E29="/","/",SUM(E27:E31)) | F32: =IF(F29="/","/",SUM(F27:F31)) | G32: =IF(G29="/","/",SUM(G27:G31)) | H32: =IF(H29="/","/",SUM(H27:H31)) | I32: =IF(I29="/","/",SUM(I27:I31)) | J32: =IF(J29="/","/",SUM(J27:J31)) | K32: =IF(K29="/","/",SUM(K27:K31)) | ... O32: =IF(O29="/","/",SUM(O27:O31)) | P32: =IF(SUM(D32:O32)=0,"0",AVERAGEIF(D32:O32,"<>0",D32:O32))
A33: 31 | B33: 冀北 | C33: 入市交易购电价格 | D33: ='分表9-2025交易价格'!D5 | E33: ='分表9-2025交易价格'!E5 | F33: ='分表9-2025交易价格'!F5 | G33: ='分表9-2025交易价格'!G5 | H33: ='分表9-2025交易价格'!H5 | I33: ='分表9-2025交易价格'!I5 | J33: ='分表9-2025交易价格'!J5 | K33: ='分表9-2025交易价格'!K5 | ... O33: ='分表9-2025交易价格'!O5 | P33: =IF(SUM(D33:O33)=0,"0",AVERAGEIF(D33:O33,"<>0",D33:O33))
A34: 32 | B34: 冀北 | C34: 综合平段电价--入市交易 | D34: =IF(D29="/","/",IF(D33>0,D33+SUM(D28:D31),"/")) | E34: =IF(E29="/","/",IF(E33>0,E33+SUM(E28:E31),"/")) | F34: =IF(F29="/","/",IF(F33>0,F33+SUM(F28:F31),"/")) | G34: =IF(G29="/","/",IF(G33>0,G33+SUM(G28:G31),"/")) | H34: =IF(H29="/","/",IF(H33>0,H33+SUM(H28:H31),"/")) | I34: =IF(I29="/","/",IF(I33>0,I33+SUM(I28:I31),"/")) | J34: =IF(J29="/","/",IF(J33>0,J33+SUM(J28:J31),"/")) | K34: =IF(K29="/","/",IF(K33>0,K33+SUM(K28:K31),"/")) | ... O34: =IF(O29="/","/",IF(O33>0,O33+SUM(O28:O31),"/")) | P34: =IF(SUM(D34:O34)=0,"0",AVERAGEIF(D34:O34,"<>0",D34:O34))
A35: 33 | B35: 山东 | C35: 代理购电价格 | D35: ='分表8-2025三类细分价'!D86 | E35: ='分表8-2025三类细分价'!E86 | F35: ='分表8-2025三类细分价'!F86 | G35: ='分表8-2025三类细分价'!G86 | H35: ='分表8-2025三类细分价'!H86 | I35: ='分表8-2025三类细分价'!I86 | J35: ='分表8-2025三类细分价'!J86 | K35: ='分表8-2025三类细分价'!K86 | ... O35: ='分表8-2025三类细分价'!O86 | P35: =IF(SUM(D35:O35)=0,"0",AVERAGEIF(D35:O35,"<>0",D35:O35))
A36: 34 | B36: 山东 | C36: 上网环节线损电价 | D36: ='分表8-2025三类细分价'!D90 | E36: ='分表8-2025三类细分价'!E90 | F36: ='分表8-2025三类细分价'!F90 | G36: ='分表8-2025三类细分价'!G90 | H36: ='分表8-2025三类细分价'!H90 | I36: ='分表8-2025三类细分价'!I90 | J36: ='分表8-2025三类细分价'!J90 | K36: ='分表8-2025三类细分价'!K90 | ... O36: ='分表8-2025三类细分价'!O90 | P36: =IF(SUM(D36:O36)=0,"0",AVERAGEIF(D36:O36,"<>0",D36:O36))
A37: 35 | B37: 山东 | C37: 电度输配电价 | D37: {=_xlfn.XLOOKUP($C$1,'分表4-电度输配电价'!$C34：'分表4-电度输配电价'!$C41&'分表4-电度输配电价'!$D34：'分表4-电度输配电价'!$D41,'分表4-电度输配电价'!$E34：'分表4-电度输配电价'!$E41)} | E37: {=_xlfn.XLOOKUP($C$1,'分表4-电度输配电价'!$C34：'分表4-电度输配电价'!$C41&'分表4-电度输配电价'!$D34：'分表4-电度输配电价'!$D41,'分表4-电度输配电价'!$E34：'分表4-电度输配电价'!$E41)} | F37: {=_xlfn.XLOOKUP($C$1,'分表4-电度输配电价'!$C34：'分表4-电度输配电价'!$C41&'分表4-电度输配电价'!$D34：'分表4-电度输配电价'!$D41,'分表4-电度输配电价'!$E34：'分表4-电度输配电价'!$E41)} | G37: {=_xlfn.XLOOKUP($C$1,'分表4-电度输配电价'!$C34：'分表4-电度输配电价'!$C41&'分表4-电度输配电价'!$D34：'分表4-电度输配电价'!$D41,'分表4-电度输配电价'!$E34：'分表4-电度输配电价'!$E41)} | H37: {=_xlfn.XLOOKUP($C$1,'分表4-电度输配电价'!$C34：'分表4-电度输配电价'!$C41&'分表4-电度输配电价'!$D34：'分表4-电度输配电价'!$D41,'分表4-电度输配电价'!$E34：'分表4-电度输配电价'!$E41)} | I37: {=_xlfn.XLOOKUP($C$1,'分表4-电度输配电价'!$C34：'分表4-电度输配电价'!$C41&'分表4-电度输配电价'!$D34：'分表4-电度输配电价'!$D41,'分表4-电度输配电价'!$E34：'分表4-电度输配电价'!$E41)} | J37: {=_xlfn.XLOOKUP($C$1,'分表4-电度输配电价'!$C34：'分表4-电度输配电价'!$C41&'分表4-电度输配电价'!$D34：'分表4-电度输配电价'!$D41,'分表4-电度输配电价'!$E34：'分表4-电度输配电价'!$E41)} | K37: {=_xlfn.XLOOKUP($C$1,'分表4-电度输配电价'!$C34：'分表4-电度输配电价'!$C41&'分表4-电度输配电价'!$D34：'分表4-电度输配电价'!$D41,'分表4-电度输配电价'!$E34：'分表4-电度输配电价'!$E41)} | ... O37: {=_xlfn.XLOOKUP($C$1,'分表4-电度输配电价'!$C34：'分表4-电度输配电价'!$C41&'分表4-电度输配电价'!$D34：'分表4-电度输配电价'!$D41,'分表4-电度输配电价'!$E34：'分表4-电度输配电价'!$E41)} | P37: =IF(SUM(D37:O37)=0,"0",AVERAGEIF(D37:O37,"<>0",D37:O37))
A38: 36 | B38: 山东 | C38: 政府性基金及附加 | D38: {=_xlfn.XLOOKUP($B$38,'分表5-政府性基金及附加'!$B$2：'分表5-政府性基金及附加'!$B$199,'分表5-政府性基金及附加'!$D$2：'分表5-政府性基金及附加'!$D$199)} | E38: {=_xlfn.XLOOKUP($B$38,'分表5-政府性基金及附加'!$B$2：'分表5-政府性基金及附加'!$B$199,'分表5-政府性基金及附加'!$D$2：'分表5-政府性基金及附加'!$D$199)} | F38: {=_xlfn.XLOOKUP($B$38,'分表5-政府性基金及附加'!$B$2：'分表5-政府性基金及附加'!$B$199,'分表5-政府性基金及附加'!$D$2：'分表5-政府性基金及附加'!$D$199)} | G38: {=_xlfn.XLOOKUP($B$38,'分表5-政府性基金及附加'!$B$2：'分表5-政府性基金及附加'!$B$199,'分表5-政府性基金及附加'!$D$2：'分表5-政府性基金及附加'!$D$199)} | H38: {=_xlfn.XLOOKUP($B$38,'分表5-政府性基金及附加'!$B$2：'分表5-政府性基金及附加'!$B$199,'分表5-政府性基金及附加'!$D$2：'分表5-政府性基金及附加'!$D$199)} | I38: {=_xlfn.XLOOKUP($B$38,'分表5-政府性基金及附加'!$B$2：'分表5-政府性基金及附加'!$B$199,'分表5-政府性基金及附加'!$D$2：'分表5-政府性基金及附加'!$D$199)} | J38: {=_xlfn.XLOOKUP($B$38,'分表5-政府性基金及附加'!$B$2：'分表5-政府性基金及附加'!$B$199,'分表5-政府性基金及附加'!$D$2：'分表5-政府性基金及附加'!$D$199)} | K38: {=_xlfn.XLOOKUP($B$38,'分表5-政府性基金及附加'!$B$2：'分表5-政府性基金及附加'!$B$199,'分表5-政府性基金及附加'!$D$2：'分表5-政府性基金及附加'!$D$199)} | ... O38: {=_xlfn.XLOOKUP($B$38,'分表5-政府性基金及附加'!$B$2：'分表5-政府性基金及附加'!$B$199,'分表5-政府性基金及附加'!$D$2：'分表5-政府性基金及附加'!$D$199)} | P38: =IF(SUM(D38:O38)=0,"0",AVERAGEIF(D38:O38,"<>0",D38:O38))
A39: 37 | B39: 山东 | C39: 系统运行费折价 | D39: ='分表8-2025三类细分价'!D91 | E39: ='分表8-2025三类细分价'!E91 | F39: ='分表8-2025三类细分价'!F91 | G39: ='分表8-2025三类细分价'!G91 | H39: ='分表8-2025三类细分价'!H91 | I39: ='分表8-2025三类细分价'!I91 | J39: ='分表8-2025三类细分价'!J91 | K39: ='分表8-2025三类细分价'!K91 | ... O39: ='分表8-2025三类细分价'!O91 | P39: =IF(SUM(D39:O39)=0,"0",AVERAGEIF(D39:O39,"<>0",D39:O39))
A40: 38 | B40: 山东 | C40: 综合平段电价--电网代购 | D40: =IF(D37="/","/",SUM(D35:D39)) | E40: =IF(E37="/","/",SUM(E35:E39)) | F40: =IF(F37="/","/",SUM(F35:F39)) | G40: =IF(G37="/","/",SUM(G35:G39)) | H40: =IF(H37="/","/",SUM(H35:H39)) | I40: =IF(I37="/","/",SUM(I35:I39)) | J40: =IF(J37="/","/",SUM(J35:J39)) | K40: =IF(K37="/","/",SUM(K35:K39)) | ... O40: =IF(O37="/","/",SUM(O35:O39)) | P40: =IF(SUM(D40:O40)=0,"0",AVERAGEIF(D40:O40,"<>0",D40:O40))
A41: 39 | B41: 山东 | C41: 入市交易购电价格 | D41: ='分表9-2025交易价格'!D6 | E41: ='分表9-2025交易价格'!E6 | F41: ='分表9-2025交易价格'!F6 | G41: ='分表9-2025交易价格'!G6 | H41: ='分表9-2025交易价格'!H6 | I41: ='分表9-2025交易价格'!I6 | J41: ='分表9-2025交易价格'!J6 | K41: ='分表9-2025交易价格'!K6 | ... O41: ='分表9-2025交易价格'!O6 | P41: =IF(SUM(D41:O41)=0,"0",AVERAGEIF(D41:O41,"<>0",D41:O41))
A42: 40 | B42: 山东 | C42: 综合平段电价--入市交易 | D42: =IF(D37="/","/",IF(D41>0,D41+SUM(D36:D39),"/")) | E42: =IF(E37="/","/",IF(E41>0,E41+SUM(E36:E39),"/")) | F42: =IF(F37="/","/",IF(F41>0,F41+SUM(F36:F39),"/")) | G42: =IF(G37="/","/",IF(G41>0,G41+SUM(G36:G39),"/")) | H42: =IF(H37="/","/",IF(H41>0,H41+SUM(H36:H39),"/")) | I42: =IF(I37="/","/",IF(I41>0,I41+SUM(I36:I39),"/")) | J42: =IF(J37="/","/",IF(J41>0,J41+SUM(J36:J39),"/")) | K42: =IF(K37="/","/",IF(K41>0,K41+SUM(K36:K39),"/")) | ... O42: =IF(O37="/","/",IF(O41>0,O41+SUM(O36:O39),"/")) | P42: =IF(SUM(D42:O42)=0,"0",AVERAGEIF(D42:O42,"<>0",D42:O42))
A43: 41 | B43: 山西 | C43: 代理购电价格 | D43: ='分表8-2025三类细分价'!D108 | E43: ='分表8-2025三类细分价'!E108 | F43: ='分表8-2025三类细分价'!F108 | G43: ='分表8-2025三类细分价'!G108 | H43: ='分表8-2025三类细分价'!H108 | I43: ='分表8-2025三类细分价'!I108 | J43: ='分表8-2025三类细分价'!J108 | K43: ='分表8-2025三类细分价'!K108 | ... O43: ='分表8-2025三类细分价'!O108 | P43: =IF(SUM(D43:O43)=0,"0",AVERAGEIF(D43:O43,"<>0",D43:O43))
A44: 42 | B44: 山西 | C44: 上网环节线损电价 | D44: ='分表8-2025三类细分价'!D111 | E44: ='分表8-2025三类细分价'!E111 | F44: ='分表8-2025三类细分价'!F111 | G44: ='分表8-2025三类细分价'!G111 | H44: ='分表8-2025三类细分价'!H111 | I44: ='分表8-2025三类细分价'!I111 | J44: ='分表8-2025三类细分价'!J111 | K44: ='分表8-2025三类细分价'!K111 | ... O44: ='分表8-2025三类细分价'!O111 | P44: =IF(SUM(D44:O44)=0,"0",AVERAGEIF(D44:O44,"<>0",D44:O44))
A45: 43 | B45: 山西 | C45: 电度输配电价 | D45: {=_xlfn.XLOOKUP($C$1,'分表4-电度输配电价'!$C42：'分表4-电度输配电价'!$C49&'分表4-电度输配电价'!$D42：'分表4-电度输配电价'!$D49,'分表4-电度输配电价'!$E42：'分表4-电度输配电价'!$E49)} | E45: {=_xlfn.XLOOKUP($C$1,'分表4-电度输配电价'!$C42：'分表4-电度输配电价'!$C49&'分表4-电度输配电价'!$D42：'分表4-电度输配电价'!$D49,'分表4-电度输配电价'!$E42：'分表4-电度输配电价'!$E49)} | F45: {=_xlfn.XLOOKUP($C$1,'分表4-电度输配电价'!$C42：'分表4-电度输配电价'!$C49&'分表4-电度输配电价'!$D42：'分表4-电度输配电价'!$D49,'分表4-电度输配电价'!$E42：'分表4-电度输配电价'!$E49)} | G45: {=_xlfn.XLOOKUP($C$1,'分表4-电度输配电价'!$C42：'分表4-电度输配电价'!$C49&'分表4-电度输配电价'!$D42：'分表4-电度输配电价'!$D49,'分表4-电度输配电价'!$E42：'分表4-电度输配电价'!$E49)} | H45: {=_xlfn.XLOOKUP($C$1,'分表4-电度输配电价'!$C42：'分表4-电度输配电价'!$C49&'分表4-电度输配电价'!$D42：'分表4-电度输配电价'!$D49,'分表4-电度输配电价'!$E42：'分表4-电度输配电价'!$E49)} | I45: {=_xlfn.XLOOKUP($C$1,'分表4-电度输配电价'!$C42：'分表4-电度输配电价'!$C49&'分表4-电度输配电价'!$D42：'分表4-电度输配电价'!$D49,'分表4-电度输配电价'!$E42：'分表4-电度输配电价'!$E49)} | J45: {=_xlfn.XLOOKUP($C$1,'分表4-电度输配电价'!$C42：'分表4-电度输配电价'!$C49&'分表4-电度输配电价'!$D42：'分表4-电度输配电价'!$D49,'分表4-电度输配电价'!$E42：'分表4-电度输配电价'!$E49)} | K45: {=_xlfn.XLOOKUP($C$1,'分表4-电度输配电价'!$C42：'分表4-电度输配电价'!$C49&'分表4-电度输配电价'!$D42：'分表4-电度输配电价'!$D49,'分表4-电度输配电价'!$E42：'分表4-电度输配电价'!$E49)} | ... O45: {=_xlfn.XLOOKUP($C$1,'分表4-电度输配电价'!$C42：'分表4-电度输配电价'!$C49&'分表4-电度输配电价'!$D42：'分表4-电度输配电价'!$D49,'分表4-电度输配电价'!$E42：'分表4-电度输配电价'!$E49)} | P45: =IF(SUM(D45:O45)=0,"0",AVERAGEIF(D45:O45,"<>0",D45:O45))
A46: 44 | B46: 山西 | C46: 政府性基金及附加 | D46: {=_xlfn.XLOOKUP($B$46,'分表5-政府性基金及附加'!$B$2：'分表5-政府性基金及附加'!$B$199,'分表5-政府性基金及附加'!$D$2：'分表5-政府性基金及附加'!$D$199)} | E46: {=_xlfn.XLOOKUP($B$46,'分表5-政府性基金及附加'!$B$2：'分表5-政府性基金及附加'!$B$199,'分表5-政府性基金及附加'!$D$2：'分表5-政府性基金及附加'!$D$199)} | F46: {=_xlfn.XLOOKUP($B$46,'分表5-政府性基金及附加'!$B$2：'分表5-政府性基金及附加'!$B$199,'分表5-政府性基金及附加'!$D$2：'分表5-政府性基金及附加'!$D$199)} | G46: {=_xlfn.XLOOKUP($B$46,'分表5-政府性基金及附加'!$B$2：'分表5-政府性基金及附加'!$B$199,'分表5-政府性基金及附加'!$D$2：'分表5-政府性基金及附加'!$D$199)} | H46: {=_xlfn.XLOOKUP($B$46,'分表5-政府性基金及附加'!$B$2：'分表5-政府性基金及附加'!$B$199,'分表5-政府性基金及附加'!$D$2：'分表5-政府性基金及附加'!$D$199)} | I46: {=_xlfn.XLOOKUP($B$46,'分表5-政府性基金及附加'!$B$2：'分表5-政府性基金及附加'!$B$199,'分表5-政府性基金及附加'!$D$2：'分表5-政府性基金及附加'!$D$199)} | J46: {=_xlfn.XLOOKUP($B$46,'分表5-政府性基金及附加'!$B$2：'分表5-政府性基金及附加'!$B$199,'分表5-政府性基金及附加'!$D$2：'分表5-政府性基金及附加'!$D$199)} | K46: {=_xlfn.XLOOKUP($B$46,'分表5-政府性基金及附加'!$B$2：'分表5-政府性基金及附加'!$B$199,'分表5-政府性基金及附加'!$D$2：'分表5-政府性基金及附加'!$D$199)} | ... O46: {=_xlfn.XLOOKUP($B$46,'分表5-政府性基金及附加'!$B$2：'分表5-政府性基金及附加'!$B$199,'分表5-政府性基金及附加'!$D$2：'分表5-政府性基金及附加'!$D$199)} | P46: =IF(SUM(D46:O46)=0,"0",AVERAGEIF(D46:O46,"<>0",D46:O46))
A47: 45 | B47: 山西 | C47: 系统运行费折价 | D47: ='分表8-2025三类细分价'!D112 | E47: ='分表8-2025三类细分价'!E112 | F47: ='分表8-2025三类细分价'!F112 | G47: ='分表8-2025三类细分价'!G112 | H47: ='分表8-2025三类细分价'!H112 | I47: ='分表8-2025三类细分价'!I112 | J47: ='分表8-2025三类细分价'!J112 | K47: ='分表8-2025三类细分价'!K112 | ... O47: ='分表8-2025三类细分价'!O112 | P47: =IF(SUM(D47:O47)=0,"0",AVERAGEIF(D47:O47,"<>0",D47:O47))
A48: 46 | B48: 山西 | C48: 综合平段电价--电网代购 | D48: =IF(D45="/","/",SUM(D43:D47)) | E48: =IF(E45="/","/",SUM(E43:E47)) | F48: =IF(F45="/","/",SUM(F43:F47)) | G48: =IF(G45="/","/",SUM(G43:G47)) | H48: =IF(H45="/","/",SUM(H43:H47)) | I48: =IF(I45="/","/",SUM(I43:I47)) | J48: =IF(J45="/","/",SUM(J43:J47)) | K48: =IF(K45="/","/",SUM(K43:K47)) | ... O48: =IF(O45="/","/",SUM(O43:O47)) | P48: =IF(SUM(D48:O48)=0,"0",AVERAGEIF(D48:O48,"<>0",D48:O48))
A49: 47 | B49: 山西 | C49: 入市交易购电价格 | D49: ='分表9-2025交易价格'!D7 | E49: ='分表9-2025交易价格'!E7 | F49: ='分表9-2025交易价格'!F7 | G49: ='分表9-2025交易价格'!G7 | H49: ='分表9-2025交易价格'!H7 | I49: ='分表9-2025交易价格'!I7 | J49: ='分表9-2025交易价格'!J7 | K49: ='分表9-2025交易价格'!K7 | ... O49: ='分表9-2025交易价格'!O7 | P49: =IF(SUM(D49:O49)=0,"0",AVERAGEIF(D49:O49,"<>0",D49:O49))
A50: 48 | B50: 山西 | C50: 综合平段电价--入市交易 | D50: =IF(D45="/","/",IF(D49>0,D49+SUM(D44:D47),"/")) | E50: =IF(E45="/","/",IF(E49>0,E49+SUM(E44:E47),"/")) | F50: =IF(F45="/","/",IF(F49>0,F49+SUM(F44:F47),"/")) | G50: =IF(G45="/","/",IF(G49>0,G49+SUM(G44:G47),"/")) | H50: =IF(H45="/","/",IF(H49>0,H49+SUM(H44:H47),"/")) | I50: =IF(I45="/","/",IF(I49>0,I49+SUM(I44:I47),"/")) | J50: =IF(J45="/","/",IF(J49>0,J49+SUM(J44:J47),"/")) | K50: =IF(K45="/","/",IF(K49>0,K49+SUM(K44:K47),"/")) | ... O50: =IF(O45="/","/",IF(O49>0,O49+SUM(O44:O47),"/")) | P50: =IF(SUM(D50:O50)=0,"0",AVERAGEIF(D50:O50,"<>0",D50:O50))
A51: 49 | B51: 蒙西 | C51: 代理购电价格 | D51: ='分表8-2025三类细分价'!D129 | E51: ='分表8-2025三类细分价'!E129 | F51: ='分表8-2025三类细分价'!F129 | G51: ='分表8-2025三类细分价'!G129 | H51: ='分表8-2025三类细分价'!H129 | I51: ='分表8-2025三类细分价'!I129 | J51: ='分表8-2025三类细分价'!J129 | K51: ='分表8-2025三类细分价'!K129 | ... O51: ='分表8-2025三类细分价'!O129 | P51: =IF(SUM(D51:O51)=0,"0",AVERAGEIF(D51:O51,"<>0",D51:O51))
A52: 50 | B52: 蒙西 | C52: 上网环节线损电价 | D52: ='分表8-2025三类细分价'!D132 | E52: ='分表8-2025三类细分价'!E132 | F52: ='分表8-2025三类细分价'!F132 | G52: ='分表8-2025三类细分价'!G132 | H52: ='分表8-2025三类细分价'!H132 | I52: ='分表8-2025三类细分价'!I132 | J52: ='分表8-2025三类细分价'!J132 | K52: ='分表8-2025三类细分价'!K132 | ... O52: ='分表8-2025三类细分价'!O132 | P52: =IF(SUM(D52:O52)=0,"0",AVERAGEIF(D52:O52,"<>0",D52:O52))
A53: 51 | B53: 蒙西 | C53: 电度输配电价 | D53: {=_xlfn.XLOOKUP($C$1,'分表4-电度输配电价'!$C50：'分表4-电度输配电价'!$C57&'分表4-电度输配电价'!$D50：'分表4-电度输配电价'!$D57,'分表4-电度输配电价'!$E50：'分表4-电度输配电价'!$E57)} | E53: {=_xlfn.XLOOKUP($C$1,'分表4-电度输配电价'!$C50：'分表4-电度输配电价'!$C57&'分表4-电度输配电价'!$D50：'分表4-电度输配电价'!$D57,'分表4-电度输配电价'!$E50：'分表4-电度输配电价'!$E57)} | F53: {=_xlfn.XLOOKUP($C$1,'分表4-电度输配电价'!$C50：'分表4-电度输配电价'!$C57&'分表4-电度输配电价'!$D50：'分表4-电度输配电价'!$D57,'分表4-电度输配电价'!$E50：'分表4-电度输配电价'!$E57)} | G53: {=_xlfn.XLOOKUP($C$1,'分表4-电度输配电价'!$C50：'分表4-电度输配电价'!$C57&'分表4-电度输配电价'!$D50：'分表4-电度输配电价'!$D57,'分表4-电度输配电价'!$E50：'分表4-电度输配电价'!$E57)} | H53: {=_xlfn.XLOOKUP($C$1,'分表4-电度输配电价'!$C50：'分表4-电度输配电价'!$C57&'分表4-电度输配电价'!$D50：'分表4-电度输配电价'!$D57,'分表4-电度输配电价'!$E50：'分表4-电度输配电价'!$E57)} | I53: {=_xlfn.XLOOKUP($C$1,'分表4-电度输配电价'!$C50：'分表4-电度输配电价'!$C57&'分表4-电度输配电价'!$D50：'分表4-电度输配电价'!$D57,'分表4-电度输配电价'!$E50：'分表4-电度输配电价'!$E57)} | J53: {=_xlfn.XLOOKUP($C$1,'分表4-电度输配电价'!$C50：'分表4-电度输配电价'!$C57&'分表4-电度输配电价'!$D50：'分表4-电度输配电价'!$D57,'分表4-电度输配电价'!$E50：'分表4-电度输配电价'!$E57)} | K53: {=_xlfn.XLOOKUP($C$1,'分表4-电度输配电价'!$C50：'分表4-电度输配电价'!$C57&'分表4-电度输配电价'!$D50：'分表4-电度输配电价'!$D57,'分表4-电度输配电价'!$E50：'分表4-电度输配电价'!$E57)} | ... O53: {=_xlfn.XLOOKUP($C$1,'分表4-电度输配电价'!$C50：'分表4-电度输配电价'!$C57&'分表4-电度输配电价'!$D50：'分表4-电度输配电价'!$D57,'分表4-电度输配电价'!$E50：'分表4-电度输配电价'!$E57)} | P53: =IF(SUM(D53:O53)=0,"0",AVERAGEIF(D53:O53,"<>0",D53:O53))
A54: 52 | B54: 蒙西 | C54: 政府性基金及附加 | D54: {=_xlfn.XLOOKUP($B$54,'分表5-政府性基金及附加'!$B$2：'分表5-政府性基金及附加'!$B$199,'分表5-政府性基金及附加'!$D$2：'分表5-政府性基金及附加'!$D$199)} | E54: {=_xlfn.XLOOKUP($B$54,'分表5-政府性基金及附加'!$B$2：'分表5-政府性基金及附加'!$B$199,'分表5-政府性基金及附加'!$D$2：'分表5-政府性基金及附加'!$D$199)} | F54: {=_xlfn.XLOOKUP($B$54,'分表5-政府性基金及附加'!$B$2：'分表5-政府性基金及附加'!$B$199,'分表5-政府性基金及附加'!$D$2：'分表5-政府性基金及附加'!$D$199)} | G54: {=_xlfn.XLOOKUP($B$54,'分表5-政府性基金及附加'!$B$2：'分表5-政府性基金及附加'!$B$199,'分表5-政府性基金及附加'!$D$2：'分表5-政府性基金及附加'!$D$199)} | H54: {=_xlfn.XLOOKUP($B$54,'分表5-政府性基金及附加'!$B$2：'分表5-政府性基金及附加'!$B$199,'分表5-政府性基金及附加'!$D$2：'分表5-政府性基金及附加'!$D$199)} | I54: {=_xlfn.XLOOKUP($B$54,'分表5-政府性基金及附加'!$B$2：'分表5-政府性基金及附加'!$B$199,'分表5-政府性基金及附加'!$D$2：'分表5-政府性基金及附加'!$D$199)} | J54: {=_xlfn.XLOOKUP($B$54,'分表5-政府性基金及附加'!$B$2：'分表5-政府性基金及附加'!$B$199,'分表5-政府性基金及附加'!$D$2：'分表5-政府性基金及附加'!$D$199)} | K54: {=_xlfn.XLOOKUP($B$54,'分表5-政府性基金及附加'!$B$2：'分表5-政府性基金及附加'!$B$199,'分表5-政府性基金及附加'!$D$2：'分表5-政府性基金及附加'!$D$199)} | ... O54: {=_xlfn.XLOOKUP($B$54,'分表5-政府性基金及附加'!$B$2：'分表5-政府性基金及附加'!$B$199,'分表5-政府性基金及附加'!$D$2：'分表5-政府性基金及附加'!$D$199)} | P54: =IF(SUM(D54:O54)=0,"0",AVERAGEIF(D54:O54,"<>0",D54:O54))
A55: 53 | B55: 蒙西 | C55: 系统运行费折价 | D55: ='分表8-2025三类细分价'!D133 | E55: ='分表8-2025三类细分价'!E133 | F55: ='分表8-2025三类细分价'!F133 | G55: ='分表8-2025三类细分价'!G133 | H55: ='分表8-2025三类细分价'!H133 | I55: ='分表8-2025三类细分价'!I133 | J55: ='分表8-2025三类细分价'!J133 | K55: ='分表8-2025三类细分价'!K133 | ... O55: ='分表8-2025三类细分价'!O133 | P55: =IF(SUM(D55:O55)=0,"0",AVERAGEIF(D55:O55,"<>0",D55:O55))
A56: 54 | B56: 蒙西 | C56: 综合平段电价--电网代购 | D56: =IF(D53="/","/",SUM(D51:D55)) | E56: =IF(E53="/","/",SUM(E51:E55)) | F56: =IF(F53="/","/",SUM(F51:F55)) | G56: =IF(G53="/","/",SUM(G51:G55)) | H56: =IF(H53="/","/",SUM(H51:H55)) | I56: =IF(I53="/","/",SUM(I51:I55)) | J56: =IF(J53="/","/",SUM(J51:J55)) | K56: =IF(K53="/","/",SUM(K51:K55)) | ... O56: =IF(O53="/","/",SUM(O51:O55)) | P56: =IF(SUM(D56:O56)=0,"0",AVERAGEIF(D56:O56,"<>0",D56:O56))
A57: 55 | B57: 蒙西 | C57: 入市交易购电价格 | D57: ='分表9-2025交易价格'!D8 | E57: ='分表9-2025交易价格'!E8 | F57: ='分表9-2025交易价格'!F8 | G57: ='分表9-2025交易价格'!G8 | H57: ='分表9-2025交易价格'!H8 | I57: ='分表9-2025交易价格'!I8 | J57: ='分表9-2025交易价格'!J8 | K57: ='分表9-2025交易价格'!K8 | ... O57: ='分表9-2025交易价格'!O8 | P57: =IF(SUM(D57:O57)=0,"0",AVERAGEIF(D57:O57,"<>0",D57:O57))
A58: 56 | B58: 蒙西 | C58: 综合平段电价--入市交易 | D58: =IF(D53="/","/",IF(D57>0,D57+SUM(D52:D55),"/")) | E58: =IF(E53="/","/",IF(E57>0,E57+SUM(E52:E55),"/")) | F58: =IF(F53="/","/",IF(F57>0,F57+SUM(F52:F55),"/")) | G58: =IF(G53="/","/",IF(G57>0,G57+SUM(G52:G55),"/")) | H58: =IF(H53="/","/",IF(H57>0,H57+SUM(H52:H55),"/")) | I58: =IF(I53="/","/",IF(I57>0,I57+SUM(I52:I55),"/")) | J58: =IF(J53="/","/",IF(J57>0,J57+SUM(J52:J55),"/")) | K58: =IF(K53="/","/",IF(K57>0,K57+SUM(K52:K55),"/")) | ... O58: =IF(O53="/","/",IF(O57>0,O57+SUM(O52:O55),"/")) | P58: =IF(SUM(D58:O58)=0,"0",AVERAGEIF(D58:O58,"<>0",D58:O58))
A59: 57 | B59: 上海 | C59: 代理购电价格 | D59: ='分表8-2025三类细分价'!D150 | E59: ='分表8-2025三类细分价'!E150 | F59: ='分表8-2025三类细分价'!F150 | G59: ='分表8-2025三类细分价'!G150 | H59: ='分表8-2025三类细分价'!H150 | I59: ='分表8-2025三类细分价'!I150 | J59: ='分表8-2025三类细分价'!J150 | K59: ='分表8-2025三类细分价'!K150 | ... O59: ='分表8-2025三类细分价'!O150 | P59: =IF(SUM(D59:O59)=0,"0",AVERAGEIF(D59:O59,"<>0",D59:O59))
A60: 58 | B60: 上海 | C60: 上网环节线损电价 | D60: ='分表8-2025三类细分价'!D153 | E60: ='分表8-2025三类细分价'!E153 | F60: ='分表8-2025三类细分价'!F153 | G60: ='分表8-2025三类细分价'!G153 | H60: ='分表8-2025三类细分价'!H153 | I60: ='分表8-2025三类细分价'!I153 | J60: ='分表8-2025三类细分价'!J153 | K60: ='分表8-2025三类细分价'!K153 | ... O60: ='分表8-2025三类细分价'!O153 | P60: =IF(SUM(D60:O60)=0,"0",AVERAGEIF(D60:O60,"<>0",D60:O60))
A61: 59 | B61: 上海 | C61: 电度输配电价 | D61: {=_xlfn.XLOOKUP($C$1,'分表4-电度输配电价'!$C58：'分表4-电度输配电价'!$C65&'分表4-电度输配电价'!$D58：'分表4-电度输配电价'!$D65,'分表4-电度输配电价'!$E58：'分表4-电度输配电价'!$E65)} | E61: {=_xlfn.XLOOKUP($C$1,'分表4-电度输配电价'!$C58：'分表4-电度输配电价'!$C65&'分表4-电度输配电价'!$D58：'分表4-电度输配电价'!$D65,'分表4-电度输配电价'!$E58：'分表4-电度输配电价'!$E65)} | F61: {=_xlfn.XLOOKUP($C$1,'分表4-电度输配电价'!$C58：'分表4-电度输配电价'!$C65&'分表4-电度输配电价'!$D58：'分表4-电度输配电价'!$D65,'分表4-电度输配电价'!$E58：'分表4-电度输配电价'!$E65)} | G61: {=_xlfn.XLOOKUP($C$1,'分表4-电度输配电价'!$C58：'分表4-电度输配电价'!$C65&'分表4-电度输配电价'!$D58：'分表4-电度输配电价'!$D65,'分表4-电度输配电价'!$E58：'分表4-电度输配电价'!$E65)} | H61: {=_xlfn.XLOOKUP($C$1,'分表4-电度输配电价'!$C58：'分表4-电度输配电价'!$C65&'分表4-电度输配电价'!$D58：'分表4-电度输配电价'!$D65,'分表4-电度输配电价'!$E58：'分表4-电度输配电价'!$E65)} | I61: {=_xlfn.XLOOKUP($C$1,'分表4-电度输配电价'!$C58：'分表4-电度输配电价'!$C65&'分表4-电度输配电价'!$D58：'分表4-电度输配电价'!$D65,'分表4-电度输配电价'!$E58：'分表4-电度输配电价'!$E65)} | J61: {=_xlfn.XLOOKUP($C$1,'分表4-电度输配电价'!$C58：'分表4-电度输配电价'!$C65&'分表4-电度输配电价'!$D58：'分表4-电度输配电价'!$D65,'分表4-电度输配电价'!$E58：'分表4-电度输配电价'!$E65)} | K61: {=_xlfn.XLOOKUP($C$1,'分表4-电度输配电价'!$C58：'分表4-电度输配电价'!$C65&'分表4-电度输配电价'!$D58：'分表4-电度输配电价'!$D65,'分表4-电度输配电价'!$E58：'分表4-电度输配电价'!$E65)} | ... O61: {=_xlfn.XLOOKUP($C$1,'分表4-电度输配电价'!$C58：'分表4-电度输配电价'!$C65&'分表4-电度输配电价'!$D58：'分表4-电度输配电价'!$D65,'分表4-电度输配电价'!$E58：'分表4-电度输配电价'!$E65)} | P61: =IF(SUM(D61:O61)=0,"0",AVERAGEIF(D61:O61,"<>0",D61:O61))
A62: 60 | B62: 上海 | C62: 政府性基金及附加 | D62: {=_xlfn.XLOOKUP($B$62,'分表5-政府性基金及附加'!$B$2：'分表5-政府性基金及附加'!$B$199,'分表5-政府性基金及附加'!$D$2：'分表5-政府性基金及附加'!$D$199)} | E62: {=_xlfn.XLOOKUP($B$62,'分表5-政府性基金及附加'!$B$2：'分表5-政府性基金及附加'!$B$199,'分表5-政府性基金及附加'!$D$2：'分表5-政府性基金及附加'!$D$199)} | F62: {=_xlfn.XLOOKUP($B$62,'分表5-政府性基金及附加'!$B$2：'分表5-政府性基金及附加'!$B$199,'分表5-政府性基金及附加'!$D$2：'分表5-政府性基金及附加'!$D$199)} | G62: {=_xlfn.XLOOKUP($B$62,'分表5-政府性基金及附加'!$B$2：'分表5-政府性基金及附加'!$B$199,'分表5-政府性基金及附加'!$D$2：'分表5-政府性基金及附加'!$D$199)} | H62: {=_xlfn.XLOOKUP($B$62,'分表5-政府性基金及附加'!$B$2：'分表5-政府性基金及附加'!$B$199,'分表5-政府性基金及附加'!$D$2：'分表5-政府性基金及附加'!$D$199)} | I62: {=_xlfn.XLOOKUP($B$62,'分表5-政府性基金及附加'!$B$2：'分表5-政府性基金及附加'!$B$199,'分表5-政府性基金及附加'!$D$2：'分表5-政府性基金及附加'!$D$199)} | J62: {=_xlfn.XLOOKUP($B$62,'分表5-政府性基金及附加'!$B$2：'分表5-政府性基金及附加'!$B$199,'分表5-政府性基金及附加'!$D$2：'分表5-政府性基金及附加'!$D$199)} | K62: {=_xlfn.XLOOKUP($B$62,'分表5-政府性基金及附加'!$B$2：'分表5-政府性基金及附加'!$B$199,'分表5-政府性基金及附加'!$D$2：'分表5-政府性基金及附加'!$D$199)} | ... O62: {=_xlfn.XLOOKUP($B$62,'分表5-政府性基金及附加'!$B$2：'分表5-政府性基金及附加'!$B$199,'分表5-政府性基金及附加'!$D$2：'分表5-政府性基金及附加'!$D$199)} | P62: =IF(SUM(D62:O62)=0,"0",AVERAGEIF(D62:O62,"<>0",D62:O62))
A63: 61 | B63: 上海 | C63: 系统运行费折价 | D63: ='分表8-2025三类细分价'!D154 | E63: ='分表8-2025三类细分价'!E154 | F63: ='分表8-2025三类细分价'!F154 | G63: ='分表8-2025三类细分价'!G154 | H63: ='分表8-2025三类细分价'!H154 | I63: ='分表8-2025三类细分价'!I154 | J63: ='分表8-2025三类细分价'!J154 | K63: ='分表8-2025三类细分价'!K154 | ... O63: ='分表8-2025三类细分价'!O154 | P63: =IF(SUM(D63:O63)=0,"0",AVERAGEIF(D63:O63,"<>0",D63:O63))
A64: 62 | B64: 上海 | C64: 综合平段电价--电网代购 | D64: =IF(D61="/","/",SUM(D59:D63)) | E64: =IF(E61="/","/",SUM(E59:E63)) | F64: =IF(F61="/","/",SUM(F59:F63)) | G64: =IF(G61="/","/",SUM(G59:G63)) | H64: =IF(H61="/","/",SUM(H59:H63)) | I64: =IF(I61="/","/",SUM(I59:I63)) | J64: =IF(J61="/","/",SUM(J59:J63)) | K64: =IF(K61="/","/",SUM(K59:K63)) | ... O64: =IF(O61="/","/",SUM(O59:O63)) | P64: =IF(SUM(D64:O64)=0,"0",AVERAGEIF(D64:O64,"<>0",D64:O64))
A65: 63 | B65: 上海 | C65: 入市交易购电价格 | D65: ='分表9-2025交易价格'!D9 | E65: ='分表9-2025交易价格'!E9 | F65: ='分表9-2025交易价格'!F9 | G65: ='分表9-2025交易价格'!G9 | H65: ='分表9-2025交易价格'!H9 | I65: ='分表9-2025交易价格'!I9 | J65: ='分表9-2025交易价格'!J9 | K65: ='分表9-2025交易价格'!K9 | ... O65: ='分表9-2025交易价格'!O9 | P65: =IF(SUM(D65:O65)=0,"0",AVERAGEIF(D65:O65,"<>0",D65:O65))
A66: 64 | B66: 上海 | C66: 综合平段电价--入市交易 | D66: =IF(D61="/","/",IF(D65>0,D65+SUM(D60:D63),"/")) | E66: =IF(E61="/","/",IF(E65>0,E65+SUM(E60:E63),"/")) | F66: =IF(F61="/","/",IF(F65>0,F65+SUM(F60:F63),"/")) | G66: =IF(G61="/","/",IF(G65>0,G65+SUM(G60:G63),"/")) | H66: =IF(H61="/","/",IF(H65>0,H65+SUM(H60:H63),"/")) | I66: =IF(I61="/","/",IF(I65>0,I65+SUM(I60:I63),"/")) | J66: =IF(J61="/","/",IF(J65>0,J65+SUM(J60:J63),"/")) | K66: =IF(K61="/","/",IF(K65>0,K65+SUM(K60:K63),"/")) | ... O66: =IF(O61="/","/",IF(O65>0,O65+SUM(O60:O63),"/")) | P66: =IF(SUM(D66:O66)=0,"0",AVERAGEIF(D66:O66,"<>0",D66:O66))
A67: 65 | B67: 江苏 | C67: 代理购电价格 | D67: ='分表8-2025三类细分价'!D171 | E67: ='分表8-2025三类细分价'!E171 | F67: ='分表8-2025三类细分价'!F171 | G67: ='分表8-2025三类细分价'!G171 | H67: ='分表8-2025三类细分价'!H171 | I67: ='分表8-2025三类细分价'!I171 | J67: ='分表8-2025三类细分价'!J171 | K67: ='分表8-2025三类细分价'!K171 | ... O67: ='分表8-2025三类细分价'!O171 | P67: =IF(SUM(D67:O67)=0,"0",AVERAGEIF(D67:O67,"<>0",D67:O67))
A68: 66 | B68: 江苏 | C68: 上网环节线损电价 | D68: ='分表8-2025三类细分价'!D174 | E68: ='分表8-2025三类细分价'!E174 | F68: ='分表8-2025三类细分价'!F174 | G68: ='分表8-2025三类细分价'!G174 | H68: ='分表8-2025三类细分价'!H174 | I68: ='分表8-2025三类细分价'!I174 | J68: ='分表8-2025三类细分价'!J174 | K68: ='分表8-2025三类细分价'!K174 | ... O68: ='分表8-2025三类细分价'!O174 | P68: =IF(SUM(D68:O68)=0,"0",AVERAGEIF(D68:O68,"<>0",D68:O68))
A69: 67 | B69: 江苏 | C69: 电度输配电价 | D69: {=_xlfn.XLOOKUP($C$1,'分表4-电度输配电价'!$C66：'分表4-电度输配电价'!$C73&'分表4-电度输配电价'!$D66：'分表4-电度输配电价'!$D73,'分表4-电度输配电价'!$E66：'分表4-电度输配电价'!$E73)} | E69: {=_xlfn.XLOOKUP($C$1,'分表4-电度输配电价'!$C66：'分表4-电度输配电价'!$C73&'分表4-电度输配电价'!$D66：'分表4-电度输配电价'!$D73,'分表4-电度输配电价'!$E66：'分表4-电度输配电价'!$E73)} | F69: {=_xlfn.XLOOKUP($C$1,'分表4-电度输配电价'!$C66：'分表4-电度输配电价'!$C73&'分表4-电度输配电价'!$D66：'分表4-电度输配电价'!$D73,'分表4-电度输配电价'!$E66：'分表4-电度输配电价'!$E73)} | G69: {=_xlfn.XLOOKUP($C$1,'分表4-电度输配电价'!$C66：'分表4-电度输配电价'!$C73&'分表4-电度输配电价'!$D66：'分表4-电度输配电价'!$D73,'分表4-电度输配电价'!$E66：'分表4-电度输配电价'!$E73)} | H69: {=_xlfn.XLOOKUP($C$1,'分表4-电度输配电价'!$C66：'分表4-电度输配电价'!$C73&'分表4-电度输配电价'!$D66：'分表4-电度输配电价'!$D73,'分表4-电度输配电价'!$E66：'分表4-电度输配电价'!$E73)} | I69: {=_xlfn.XLOOKUP($C$1,'分表4-电度输配电价'!$C66：'分表4-电度输配电价'!$C73&'分表4-电度输配电价'!$D66：'分表4-电度输配电价'!$D73,'分表4-电度输配电价'!$E66：'分表4-电度输配电价'!$E73)} | J69: {=_xlfn.XLOOKUP($C$1,'分表4-电度输配电价'!$C66：'分表4-电度输配电价'!$C73&'分表4-电度输配电价'!$D66：'分表4-电度输配电价'!$D73,'分表4-电度输配电价'!$E66：'分表4-电度输配电价'!$E73)} | K69: {=_xlfn.XLOOKUP($C$1,'分表4-电度输配电价'!$C66：'分表4-电度输配电价'!$C73&'分表4-电度输配电价'!$D66：'分表4-电度输配电价'!$D73,'分表4-电度输配电价'!$E66：'分表4-电度输配电价'!$E73)} | ... O69: {=_xlfn.XLOOKUP($C$1,'分表4-电度输配电价'!$C66：'分表4-电度输配电价'!$C73&'分表4-电度输配电价'!$D66：'分表4-电度输配电价'!$D73,'分表4-电度输配电价'!$E66：'分表4-电度输配电价'!$E73)} | P69: =IF(SUM(D69:O69)=0,"0",AVERAGEIF(D69:O69,"<>0",D69:O69))
A70: 68 | B70: 江苏 | C70: 政府性基金及附加 | D70: {=_xlfn.XLOOKUP($B$70,'分表5-政府性基金及附加'!$B$2：'分表5-政府性基金及附加'!$B$199,'分表5-政府性基金及附加'!$D$2：'分表5-政府性基金及附加'!$D$199)} | E70: {=_xlfn.XLOOKUP($B$70,'分表5-政府性基金及附加'!$B$2：'分表5-政府性基金及附加'!$B$199,'分表5-政府性基金及附加'!$D$2：'分表5-政府性基金及附加'!$D$199)} | F70: {=_xlfn.XLOOKUP($B$70,'分表5-政府性基金及附加'!$B$2：'分表5-政府性基金及附加'!$B$199,'分表5-政府性基金及附加'!$D$2：'分表5-政府性基金及附加'!$D$199)} | G70: {=_xlfn.XLOOKUP($B$70,'分表5-政府性基金及附加'!$B$2：'分表5-政府性基金及附加'!$B$199,'分表5-政府性基金及附加'!$D$2：'分表5-政府性基金及附加'!$D$199)} | H70: {=_xlfn.XLOOKUP($B$70,'分表5-政府性基金及附加'!$B$2：'分表5-政府性基金及附加'!$B$199,'分表5-政府性基金及附加'!$D$2：'分表5-政府性基金及附加'!$D$199)} | I70: {=_xlfn.XLOOKUP($B$70,'分表5-政府性基金及附加'!$B$2：'分表5-政府性基金及附加'!$B$199,'分表5-政府性基金及附加'!$D$2：'分表5-政府性基金及附加'!$D$199)} | J70: {=_xlfn.XLOOKUP($B$70,'分表5-政府性基金及附加'!$B$2：'分表5-政府性基金及附加'!$B$199,'分表5-政府性基金及附加'!$D$2：'分表5-政府性基金及附加'!$D$199)} | K70: {=_xlfn.XLOOKUP($B$70,'分表5-政府性基金及附加'!$B$2：'分表5-政府性基金及附加'!$B$199,'分表5-政府性基金及附加'!$D$2：'分表5-政府性基金及附加'!$D$199)} | ... O70: {=_xlfn.XLOOKUP($B$70,'分表5-政府性基金及附加'!$B$2：'分表5-政府性基金及附加'!$B$199,'分表5-政府性基金及附加'!$D$2：'分表5-政府性基金及附加'!$D$199)} | P70: =IF(SUM(D70:O70)=0,"0",AVERAGEIF(D70:O70,"<>0",D70:O70))
A71: 69 | B71: 江苏 | C71: 系统运行费折价 | D71: ='分表8-2025三类细分价'!D175 | E71: ='分表8-2025三类细分价'!E175 | F71: ='分表8-2025三类细分价'!F175 | G71: ='分表8-2025三类细分价'!G175 | H71: ='分表8-2025三类细分价'!H175 | I71: ='分表8-2025三类细分价'!I175 | J71: ='分表8-2025三类细分价'!J175 | K71: ='分表8-2025三类细分价'!K175 | ... O71: ='分表8-2025三类细分价'!O175 | P71: =IF(SUM(D71:O71)=0,"0",AVERAGEIF(D71:O71,"<>0",D71:O71))
A72: 70 | B72: 江苏 | C72: 综合平段电价--电网代购 | D72: =IF(D69="/","/",SUM(D67:D71)) | E72: =IF(E69="/","/",SUM(E67:E71)) | F72: =IF(F69="/","/",SUM(F67:F71)) | G72: =IF(G69="/","/",SUM(G67:G71)) | H72: =IF(H69="/","/",SUM(H67:H71)) | I72: =IF(I69="/","/",SUM(I67:I71)) | J72: =IF(J69="/","/",SUM(J67:J71)) | K72: =IF(K69="/","/",SUM(K67:K71)) | ... O72: =IF(O69="/","/",SUM(O67:O71)) | P72: =IF(SUM(D72:O72)=0,"0",AVERAGEIF(D72:O72,"<>0",D72:O72))
A73: 71 | B73: 江苏 | C73: 入市交易购电价格 | D73: ='分表9-2025交易价格'!D10 | E73: ='分表9-2025交易价格'!E10 | F73: ='分表9-2025交易价格'!F10 | G73: ='分表9-2025交易价格'!G10 | H73: ='分表9-2025交易价格'!H10 | I73: ='分表9-2025交易价格'!I10 | J73: ='分表9-2025交易价格'!J10 | K73: ='分表9-2025交易价格'!K10 | ... O73: ='分表9-2025交易价格'!O10 | P73: =IF(SUM(D73:O73)=0,"0",AVERAGEIF(D73:O73,"<>0",D73:O73))
A74: 72 | B74: 江苏 | C74: 综合平段电价--入市交易 | D74: =IF(D69="/","/",IF(D73>0,D73+SUM(D68:D71),"/")) | E74: =IF(E69="/","/",IF(E73>0,E73+SUM(E68:E71),"/")) | F74: =IF(F69="/","/",IF(F73>0,F73+SUM(F68:F71),"/")) | G74: =IF(G69="/","/",IF(G73>0,G73+SUM(G68:G71),"/")) | H74: =IF(H69="/","/",IF(H73>0,H73+SUM(H68:H71),"/")) | I74: =IF(I69="/","/",IF(I73>0,I73+SUM(I68:I71),"/")) | J74: =IF(J69="/","/",IF(J73>0,J73+SUM(J68:J71),"/")) | K74: =IF(K69="/","/",IF(K73>0,K73+SUM(K68:K71),"/")) | ... O74: =IF(O69="/","/",IF(O73>0,O73+SUM(O68:O71),"/")) | P74: =IF(SUM(D74:O74)=0,"0",AVERAGEIF(D74:O74,"<>0",D74:O74))
A75: 73 | B75: 浙江 | C75: 代理购电价格 | D75: ='分表8-2025三类细分价'!D192 | E75: ='分表8-2025三类细分价'!E192 | F75: ='分表8-2025三类细分价'!F192 | G75: ='分表8-2025三类细分价'!G192 | H75: ='分表8-2025三类细分价'!H192 | I75: ='分表8-2025三类细分价'!I192 | J75: ='分表8-2025三类细分价'!J192 | K75: ='分表8-2025三类细分价'!K192 | ... O75: ='分表8-2025三类细分价'!O192 | P75: =IF(SUM(D75:O75)=0,"0",AVERAGEIF(D75:O75,"<>0",D75:O75))
A76: 74 | B76: 浙江 | C76: 上网环节线损电价 | D76: ='分表8-2025三类细分价'!D195 | E76: ='分表8-2025三类细分价'!E195 | F76: ='分表8-2025三类细分价'!F195 | G76: ='分表8-2025三类细分价'!G195 | H76: ='分表8-2025三类细分价'!H195 | I76: ='分表8-2025三类细分价'!I195 | J76: ='分表8-2025三类细分价'!J195 | K76: ='分表8-2025三类细分价'!K195 | ... O76: ='分表8-2025三类细分价'!O195 | P76: =IF(SUM(D76:O76)=0,"0",AVERAGEIF(D76:O76,"<>0",D76:O76))
A77: 75 | B77: 浙江 | C77: 电度输配电价 | D77: {=_xlfn.XLOOKUP($C$1,'分表4-电度输配电价'!$C74：'分表4-电度输配电价'!$C81&'分表4-电度输配电价'!$D74：'分表4-电度输配电价'!$D81,'分表4-电度输配电价'!$E74：'分表4-电度输配电价'!$E81)} | E77: {=_xlfn.XLOOKUP($C$1,'分表4-电度输配电价'!$C74：'分表4-电度输配电价'!$C81&'分表4-电度输配电价'!$D74：'分表4-电度输配电价'!$D81,'分表4-电度输配电价'!$E74：'分表4-电度输配电价'!$E81)} | F77: {=_xlfn.XLOOKUP($C$1,'分表4-电度输配电价'!$C74：'分表4-电度输配电价'!$C81&'分表4-电度输配电价'!$D74：'分表4-电度输配电价'!$D81,'分表4-电度输配电价'!$E74：'分表4-电度输配电价'!$E81)} | G77: {=_xlfn.XLOOKUP($C$1,'分表4-电度输配电价'!$C74：'分表4-电度输配电价'!$C81&'分表4-电度输配电价'!$D74：'分表4-电度输配电价'!$D81,'分表4-电度输配电价'!$E74：'分表4-电度输配电价'!$E81)} | H77: {=_xlfn.XLOOKUP($C$1,'分表4-电度输配电价'!$C74：'分表4-电度输配电价'!$C81&'分表4-电度输配电价'!$D74：'分表4-电度输配电价'!$D81,'分表4-电度输配电价'!$E74：'分表4-电度输配电价'!$E81)} | I77: {=_xlfn.XLOOKUP($C$1,'分表4-电度输配电价'!$C74：'分表4-电度输配电价'!$C81&'分表4-电度输配电价'!$D74：'分表4-电度输配电价'!$D81,'分表4-电度输配电价'!$E74：'分表4-电度输配电价'!$E81)} | J77: {=_xlfn.XLOOKUP($C$1,'分表4-电度输配电价'!$C74：'分表4-电度输配电价'!$C81&'分表4-电度输配电价'!$D74：'分表4-电度输配电价'!$D81,'分表4-电度输配电价'!$E74：'分表4-电度输配电价'!$E81)} | K77: {=_xlfn.XLOOKUP($C$1,'分表4-电度输配电价'!$C74：'分表4-电度输配电价'!$C81&'分表4-电度输配电价'!$D74：'分表4-电度输配电价'!$D81,'分表4-电度输配电价'!$E74：'分表4-电度输配电价'!$E81)} | ... O77: {=_xlfn.XLOOKUP($C$1,'分表4-电度输配电价'!$C74：'分表4-电度输配电价'!$C81&'分表4-电度输配电价'!$D74：'分表4-电度输配电价'!$D81,'分表4-电度输配电价'!$E74：'分表4-电度输配电价'!$E81)} | P77: =IF(SUM(D77:O77)=0,"0",AVERAGEIF(D77:O77,"<>0",D77:O77))
A78: 76 | B78: 浙江 | C78: 政府性基金及附加 | D78: {=_xlfn.XLOOKUP($B$78,'分表5-政府性基金及附加'!$B$2：'分表5-政府性基金及附加'!$B$199,'分表5-政府性基金及附加'!$D$2：'分表5-政府性基金及附加'!$D$199)} | E78: {=_xlfn.XLOOKUP($B$78,'分表5-政府性基金及附加'!$B$2：'分表5-政府性基金及附加'!$B$199,'分表5-政府性基金及附加'!$D$2：'分表5-政府性基金及附加'!$D$199)} | F78: {=_xlfn.XLOOKUP($B$78,'分表5-政府性基金及附加'!$B$2：'分表5-政府性基金及附加'!$B$199,'分表5-政府性基金及附加'!$D$2：'分表5-政府性基金及附加'!$D$199)} | G78: {=_xlfn.XLOOKUP($B$78,'分表5-政府性基金及附加'!$B$2：'分表5-政府性基金及附加'!$B$199,'分表5-政府性基金及附加'!$D$2：'分表5-政府性基金及附加'!$D$199)} | H78: {=_xlfn.XLOOKUP($B$78,'分表5-政府性基金及附加'!$B$2：'分表5-政府性基金及附加'!$B$199,'分表5-政府性基金及附加'!$D$2：'分表5-政府性基金及附加'!$D$199)} | I78: {=_xlfn.XLOOKUP($B$78,'分表5-政府性基金及附加'!$B$2：'分表5-政府性基金及附加'!$B$199,'分表5-政府性基金及附加'!$D$2：'分表5-政府性基金及附加'!$D$199)} | J78: {=_xlfn.XLOOKUP($B$78,'分表5-政府性基金及附加'!$B$2：'分表5-政府性基金及附加'!$B$199,'分表5-政府性基金及附加'!$D$2：'分表5-政府性基金及附加'!$D$199)} | K78: {=_xlfn.XLOOKUP($B$78,'分表5-政府性基金及附加'!$B$2：'分表5-政府性基金及附加'!$B$199,'分表5-政府性基金及附加'!$D$2：'分表5-政府性基金及附加'!$D$199)} | ... O78: {=_xlfn.XLOOKUP($B$78,'分表5-政府性基金及附加'!$B$2：'分表5-政府性基金及附加'!$B$199,'分表5-政府性基金及附加'!$D$2：'分表5-政府性基金及附加'!$D$199)} | P78: =IF(SUM(D78:O78)=0,"0",AVERAGEIF(D78:O78,"<>0",D78:O78))
A79: 77 | B79: 浙江 | C79: 系统运行费折价 | D79: ='分表8-2025三类细分价'!D196 | E79: ='分表8-2025三类细分价'!E196 | F79: ='分表8-2025三类细分价'!F196 | G79: ='分表8-2025三类细分价'!G196 | H79: ='分表8-2025三类细分价'!H196 | I79: ='分表8-2025三类细分价'!I196 | J79: ='分表8-2025三类细分价'!J196 | K79: ='分表8-2025三类细分价'!K196 | ... O79: ='分表8-2025三类细分价'!O196 | P79: =IF(SUM(D79:O79)=0,"0",AVERAGEIF(D79:O79,"<>0",D79:O79))
A80: 78 | B80: 浙江 | C80: 综合平段电价--电网代购 | D80: =IF(D77="/","/",SUM(D75:D79)) | E80: =IF(E77="/","/",SUM(E75:E79)) | F80: =IF(F77="/","/",SUM(F75:F79)) | G80: =IF(G77="/","/",SUM(G75:G79)) | H80: =IF(H77="/","/",SUM(H75:H79)) | I80: =IF(I77="/","/",SUM(I75:I79)) | J80: =IF(J77="/","/",SUM(J75:J79)) | K80: =IF(K77="/","/",SUM(K75:K79)) | ... O80: =IF(O77="/","/",SUM(O75:O79)) | P80: =IF(SUM(D80:O80)=0,"0",AVERAGEIF(D80:O80,"<>0",D80:O80))
A81: 79 | B81: 浙江 | C81: 入市交易购电价格 | D81: ='分表9-2025交易价格'!D11 | E81: ='分表9-2025交易价格'!E11 | F81: ='分表9-2025交易价格'!F11 | G81: ='分表9-2025交易价格'!G11 | H81: ='分表9-2025交易价格'!H11 | I81: ='分表9-2025交易价格'!I11 | J81: ='分表9-2025交易价格'!J11 | K81: ='分表9-2025交易价格'!K11 | ... O81: ='分表9-2025交易价格'!O11 | P81: =IF(SUM(D81:O81)=0,"0",AVERAGEIF(D81:O81,"<>0",D81:O81))
A82: 80 | B82: 浙江 | C82: 综合平段电价--入市交易 | D82: =IF(D77="/","/",IF(D81>0,D81+SUM(D76:D79),"/")) | E82: =IF(E77="/","/",IF(E81>0,E81+SUM(E76:E79),"/")) | F82: =IF(F77="/","/",IF(F81>0,F81+SUM(F76:F79),"/")) | G82: =IF(G77="/","/",IF(G81>0,G81+SUM(G76:G79),"/")) | H82: =IF(H77="/","/",IF(H81>0,H81+SUM(H76:H79),"/")) | I82: =IF(I77="/","/",IF(I81>0,I81+SUM(I76:I79),"/")) | J82: =IF(J77="/","/",IF(J81>0,J81+SUM(J76:J79),"/")) | K82: =IF(K77="/","/",IF(K81>0,K81+SUM(K76:K79),"/")) | ... O82: =IF(O77="/","/",IF(O81>0,O81+SUM(O76:O79),"/")) | P82: =IF(SUM(D82:O82)=0,"0",AVERAGEIF(D82:O82,"<>0",D82:O82))
A83: 81 | B83: 安徽 | C83: 代理购电价格 | D83: ='分表8-2025三类细分价'!D213 | E83: ='分表8-2025三类细分价'!E213 | F83: ='分表8-2025三类细分价'!F213 | G83: ='分表8-2025三类细分价'!G213 | H83: ='分表8-2025三类细分价'!H213 | I83: ='分表8-2025三类细分价'!I213 | J83: ='分表8-2025三类细分价'!J213 | K83: ='分表8-2025三类细分价'!K213 | ... O83: ='分表8-2025三类细分价'!O213 | P83: =IF(SUM(D83:O83)=0,"0",AVERAGEIF(D83:O83,"<>0",D83:O83))
A84: 82 | B84: 安徽 | C84: 上网环节线损电价 | D84: ='分表8-2025三类细分价'!D216 | E84: ='分表8-2025三类细分价'!E216 | F84: ='分表8-2025三类细分价'!F216 | G84: ='分表8-2025三类细分价'!G216 | H84: ='分表8-2025三类细分价'!H216 | I84: ='分表8-2025三类细分价'!I216 | J84: ='分表8-2025三类细分价'!J216 | K84: ='分表8-2025三类细分价'!K216 | ... O84: ='分表8-2025三类细分价'!O216 | P84: =IF(SUM(D84:O84)=0,"0",AVERAGEIF(D84:O84,"<>0",D84:O84))
A85: 83 | B85: 安徽 | C85: 电度输配电价 | D85: {=_xlfn.XLOOKUP($C$1,'分表4-电度输配电价'!$C82：'分表4-电度输配电价'!$C89&'分表4-电度输配电价'!$D82：'分表4-电度输配电价'!$D89,'分表4-电度输配电价'!$E82：'分表4-电度输配电价'!$E89)} | E85: {=_xlfn.XLOOKUP($C$1,'分表4-电度输配电价'!$C82：'分表4-电度输配电价'!$C89&'分表4-电度输配电价'!$D82：'分表4-电度输配电价'!$D89,'分表4-电度输配电价'!$E82：'分表4-电度输配电价'!$E89)} | F85: {=_xlfn.XLOOKUP($C$1,'分表4-电度输配电价'!$C82：'分表4-电度输配电价'!$C89&'分表4-电度输配电价'!$D82：'分表4-电度输配电价'!$D89,'分表4-电度输配电价'!$E82：'分表4-电度输配电价'!$E89)} | G85: {=_xlfn.XLOOKUP($C$1,'分表4-电度输配电价'!$C82：'分表4-电度输配电价'!$C89&'分表4-电度输配电价'!$D82：'分表4-电度输配电价'!$D89,'分表4-电度输配电价'!$E82：'分表4-电度输配电价'!$E89)} | H85: {=_xlfn.XLOOKUP($C$1,'分表4-电度输配电价'!$C82：'分表4-电度输配电价'!$C89&'分表4-电度输配电价'!$D82：'分表4-电度输配电价'!$D89,'分表4-电度输配电价'!$E82：'分表4-电度输配电价'!$E89)} | I85: {=_xlfn.XLOOKUP($C$1,'分表4-电度输配电价'!$C82：'分表4-电度输配电价'!$C89&'分表4-电度输配电价'!$D82：'分表4-电度输配电价'!$D89,'分表4-电度输配电价'!$E82：'分表4-电度输配电价'!$E89)} | J85: {=_xlfn.XLOOKUP($C$1,'分表4-电度输配电价'!$C82：'分表4-电度输配电价'!$C89&'分表4-电度输配电价'!$D82：'分表4-电度输配电价'!$D89,'分表4-电度输配电价'!$E82：'分表4-电度输配电价'!$E89)} | K85: {=_xlfn.XLOOKUP($C$1,'分表4-电度输配电价'!$C82：'分表4-电度输配电价'!$C89&'分表4-电度输配电价'!$D82：'分表4-电度输配电价'!$D89,'分表4-电度输配电价'!$E82：'分表4-电度输配电价'!$E89)} | ... O85: {=_xlfn.XLOOKUP($C$1,'分表4-电度输配电价'!$C82：'分表4-电度输配电价'!$C89&'分表4-电度输配电价'!$D82：'分表4-电度输配电价'!$D89,'分表4-电度输配电价'!$E82：'分表4-电度输配电价'!$E89)} | P85: =IF(SUM(D85:O85)=0,"0",AVERAGEIF(D85:O85,"<>0",D85:O85))
A86: 84 | B86: 安徽 | C86: 政府性基金及附加 | D86: {=_xlfn.XLOOKUP($B$86,'分表5-政府性基金及附加'!$B$2：'分表5-政府性基金及附加'!$B$199,'分表5-政府性基金及附加'!$D$2：'分表5-政府性基金及附加'!$D$199)} | E86: {=_xlfn.XLOOKUP($B$86,'分表5-政府性基金及附加'!$B$2：'分表5-政府性基金及附加'!$B$199,'分表5-政府性基金及附加'!$D$2：'分表5-政府性基金及附加'!$D$199)} | F86: {=_xlfn.XLOOKUP($B$86,'分表5-政府性基金及附加'!$B$2：'分表5-政府性基金及附加'!$B$199,'分表5-政府性基金及附加'!$D$2：'分表5-政府性基金及附加'!$D$199)} | G86: {=_xlfn.XLOOKUP($B$86,'分表5-政府性基金及附加'!$B$2：'分表5-政府性基金及附加'!$B$199,'分表5-政府性基金及附加'!$D$2：'分表5-政府性基金及附加'!$D$199)} | H86: {=_xlfn.XLOOKUP($B$86,'分表5-政府性基金及附加'!$B$2：'分表5-政府性基金及附加'!$B$199,'分表5-政府性基金及附加'!$D$2：'分表5-政府性基金及附加'!$D$199)} | I86: {=_xlfn.XLOOKUP($B$86,'分表5-政府性基金及附加'!$B$2：'分表5-政府性基金及附加'!$B$199,'分表5-政府性基金及附加'!$D$2：'分表5-政府性基金及附加'!$D$199)} | J86: {=_xlfn.XLOOKUP($B$86,'分表5-政府性基金及附加'!$B$2：'分表5-政府性基金及附加'!$B$199,'分表5-政府性基金及附加'!$D$2：'分表5-政府性基金及附加'!$D$199)} | K86: {=_xlfn.XLOOKUP($B$86,'分表5-政府性基金及附加'!$B$2：'分表5-政府性基金及附加'!$B$199,'分表5-政府性基金及附加'!$D$2：'分表5-政府性基金及附加'!$D$199)} | ... O86: {=_xlfn.XLOOKUP($B$86,'分表5-政府性基金及附加'!$B$2：'分表5-政府性基金及附加'!$B$199,'分表5-政府性基金及附加'!$D$2：'分表5-政府性基金及附加'!$D$199)} | P86: =IF(SUM(D86:O86)=0,"0",AVERAGEIF(D86:O86,"<>0",D86:O86))
A87: 85 | B87: 安徽 | C87: 系统运行费折价 | D87: ='分表8-2025三类细分价'!D217 | E87: ='分表8-2025三类细分价'!E217 | F87: ='分表8-2025三类细分价'!F217 | G87: ='分表8-2025三类细分价'!G217 | H87: ='分表8-2025三类细分价'!H217 | I87: ='分表8-2025三类细分价'!I217 | J87: ='分表8-2025三类细分价'!J217 | K87: ='分表8-2025三类细分价'!K217 | ... O87: ='分表8-2025三类细分价'!O217 | P87: =IF(SUM(D87:O87)=0,"0",AVERAGEIF(D87:O87,"<>0",D87:O87))
A88: 86 | B88: 安徽 | C88: 综合平段电价--电网代购 | D88: =IF(D85="/","/",SUM(D83:D87)) | E88: =IF(E85="/","/",SUM(E83:E87)) | F88: =IF(F85="/","/",SUM(F83:F87)) | G88: =IF(G85="/","/",SUM(G83:G87)) | H88: =IF(H85="/","/",SUM(H83:H87)) | I88: =IF(I85="/","/",SUM(I83:I87)) | J88: =IF(J85="/","/",SUM(J83:J87)) | K88: =IF(K85="/","/",SUM(K83:K87)) | ... O88: =IF(O85="/","/",SUM(O83:O87)) | P88: =IF(SUM(D88:O88)=0,"0",AVERAGEIF(D88:O88,"<>0",D88:O88))
A89: 87 | B89: 安徽 | C89: 入市交易购电价格 | D89: ='分表9-2025交易价格'!D12 | E89: ='分表9-2025交易价格'!E12 | F89: ='分表9-2025交易价格'!F12 | G89: ='分表9-2025交易价格'!G12 | H89: ='分表9-2025交易价格'!H12 | I89: ='分表9-2025交易价格'!I12 | J89: ='分表9-2025交易价格'!J12 | K89: ='分表9-2025交易价格'!K12 | ... O89: ='分表9-2025交易价格'!O12 | P89: =IF(SUM(D89:O89)=0,"0",AVERAGEIF(D89:O89,"<>0",D89:O89))
A90: 88 | B90: 安徽 | C90: 综合平段电价--入市交易 | D90: =IF(D85="/","/",IF(D89>0,D89+SUM(D84:D87),"/")) | E90: =IF(E85="/","/",IF(E89>0,E89+SUM(E84:E87),"/")) | F90: =IF(F85="/","/",IF(F89>0,F89+SUM(F84:F87),"/")) | G90: =IF(G85="/","/",IF(G89>0,G89+SUM(G84:G87),"/")) | H90: =IF(H85="/","/",IF(H89>0,H89+SUM(H84:H87),"/")) | I90: =IF(I85="/","/",IF(I89>0,I89+SUM(I84:I87),"/")) | J90: =IF(J85="/","/",IF(J89>0,J89+SUM(J84:J87),"/")) | K90: =IF(K85="/","/",IF(K89>0,K89+SUM(K84:K87),"/")) | ... O90: =IF(O85="/","/",IF(O89>0,O89+SUM(O84:O87),"/")) | P90: =IF(SUM(D90:O90)=0,"0",AVERAGEIF(D90:O90,"<>0",D90:O90))
A91: 89 | B91: 福建 | C91: 代理购电价格 | D91: ='分表8-2025三类细分价'!D234 | E91: ='分表8-2025三类细分价'!E234 | F91: ='分表8-2025三类细分价'!F234 | G91: ='分表8-2025三类细分价'!G234 | H91: ='分表8-2025三类细分价'!H234 | I91: ='分表8-2025三类细分价'!I234 | J91: ='分表8-2025三类细分价'!J234 | K91: ='分表8-2025三类细分价'!K234 | ... O91: ='分表8-2025三类细分价'!O234 | P91: =IF(SUM(D91:O91)=0,"0",AVERAGEIF(D91:O91,"<>0",D91:O91))
A92: 90 | B92: 福建 | C92: 上网环节线损电价 | D92: ='分表8-2025三类细分价'!D237 | E92: ='分表8-2025三类细分价'!E237 | F92: ='分表8-2025三类细分价'!F237 | G92: ='分表8-2025三类细分价'!G237 | H92: ='分表8-2025三类细分价'!H237 | I92: ='分表8-2025三类细分价'!I237 | J92: ='分表8-2025三类细分价'!J237 | K92: ='分表8-2025三类细分价'!K237 | ... O92: ='分表8-2025三类细分价'!O237 | P92: =IF(SUM(D92:O92)=0,"0",AVERAGEIF(D92:O92,"<>0",D92:O92))
A93: 91 | B93: 福建 | C93: 电度输配电价 | D93: {=_xlfn.XLOOKUP($C$1,'分表4-电度输配电价'!$C90：'分表4-电度输配电价'!$C97&'分表4-电度输配电价'!$D90：'分表4-电度输配电价'!$D97,'分表4-电度输配电价'!$E90：'分表4-电度输配电价'!$E97)} | E93: {=_xlfn.XLOOKUP($C$1,'分表4-电度输配电价'!$C90：'分表4-电度输配电价'!$C97&'分表4-电度输配电价'!$D90：'分表4-电度输配电价'!$D97,'分表4-电度输配电价'!$E90：'分表4-电度输配电价'!$E97)} | F93: {=_xlfn.XLOOKUP($C$1,'分表4-电度输配电价'!$C90：'分表4-电度输配电价'!$C97&'分表4-电度输配电价'!$D90：'分表4-电度输配电价'!$D97,'分表4-电度输配电价'!$E90：'分表4-电度输配电价'!$E97)} | G93: {=_xlfn.XLOOKUP($C$1,'分表4-电度输配电价'!$C90：'分表4-电度输配电价'!$C97&'分表4-电度输配电价'!$D90：'分表4-电度输配电价'!$D97,'分表4-电度输配电价'!$E90：'分表4-电度输配电价'!$E97)} | H93: {=_xlfn.XLOOKUP($C$1,'分表4-电度输配电价'!$C90：'分表4-电度输配电价'!$C97&'分表4-电度输配电价'!$D90：'分表4-电度输配电价'!$D97,'分表4-电度输配电价'!$E90：'分表4-电度输配电价'!$E97)} | I93: {=_xlfn.XLOOKUP($C$1,'分表4-电度输配电价'!$C90：'分表4-电度输配电价'!$C97&'分表4-电度输配电价'!$D90：'分表4-电度输配电价'!$D97,'分表4-电度输配电价'!$E90：'分表4-电度输配电价'!$E97)} | J93: {=_xlfn.XLOOKUP($C$1,'分表4-电度输配电价'!$C90：'分表4-电度输配电价'!$C97&'分表4-电度输配电价'!$D90：'分表4-电度输配电价'!$D97,'分表4-电度输配电价'!$E90：'分表4-电度输配电价'!$E97)} | K93: {=_xlfn.XLOOKUP($C$1,'分表4-电度输配电价'!$C90：'分表4-电度输配电价'!$C97&'分表4-电度输配电价'!$D90：'分表4-电度输配电价'!$D97,'分表4-电度输配电价'!$E90：'分表4-电度输配电价'!$E97)} | ... O93: {=_xlfn.XLOOKUP($C$1,'分表4-电度输配电价'!$C90：'分表4-电度输配电价'!$C97&'分表4-电度输配电价'!$D90：'分表4-电度输配电价'!$D97,'分表4-电度输配电价'!$E90：'分表4-电度输配电价'!$E97)} | P93: =IF(SUM(D93:O93)=0,"0",AVERAGEIF(D93:O93,"<>0",D93:O93))
A94: 92 | B94: 福建 | C94: 政府性基金及附加 | D94: {=_xlfn.XLOOKUP($B$94,'分表5-政府性基金及附加'!$B$2：'分表5-政府性基金及附加'!$B$199,'分表5-政府性基金及附加'!$D$2：'分表5-政府性基金及附加'!$D$199)} | E94: {=_xlfn.XLOOKUP($B$94,'分表5-政府性基金及附加'!$B$2：'分表5-政府性基金及附加'!$B$199,'分表5-政府性基金及附加'!$D$2：'分表5-政府性基金及附加'!$D$199)} | F94: {=_xlfn.XLOOKUP($B$94,'分表5-政府性基金及附加'!$B$2：'分表5-政府性基金及附加'!$B$199,'分表5-政府性基金及附加'!$D$2：'分表5-政府性基金及附加'!$D$199)} | G94: {=_xlfn.XLOOKUP($B$94,'分表5-政府性基金及附加'!$B$2：'分表5-政府性基金及附加'!$B$199,'分表5-政府性基金及附加'!$D$2：'分表5-政府性基金及附加'!$D$199)} | H94: {=_xlfn.XLOOKUP($B$94,'分表5-政府性基金及附加'!$B$2：'分表5-政府性基金及附加'!$B$199,'分表5-政府性基金及附加'!$D$2：'分表5-政府性基金及附加'!$D$199)} | I94: {=_xlfn.XLOOKUP($B$94,'分表5-政府性基金及附加'!$B$2：'分表5-政府性基金及附加'!$B$199,'分表5-政府性基金及附加'!$D$2：'分表5-政府性基金及附加'!$D$199)} | J94: {=_xlfn.XLOOKUP($B$94,'分表5-政府性基金及附加'!$B$2：'分表5-政府性基金及附加'!$B$199,'分表5-政府性基金及附加'!$D$2：'分表5-政府性基金及附加'!$D$199)} | K94: {=_xlfn.XLOOKUP($B$94,'分表5-政府性基金及附加'!$B$2：'分表5-政府性基金及附加'!$B$199,'分表5-政府性基金及附加'!$D$2：'分表5-政府性基金及附加'!$D$199)} | ... O94: {=_xlfn.XLOOKUP($B$94,'分表5-政府性基金及附加'!$B$2：'分表5-政府性基金及附加'!$B$199,'分表5-政府性基金及附加'!$D$2：'分表5-政府性基金及附加'!$D$199)} | P94: =IF(SUM(D94:O94)=0,"0",AVERAGEIF(D94:O94,"<>0",D94:O94))
A95: 93 | B95: 福建 | C95: 系统运行费折价 | D95: ='分表8-2025三类细分价'!D238 | E95: ='分表8-2025三类细分价'!E238 | F95: ='分表8-2025三类细分价'!F238 | G95: ='分表8-2025三类细分价'!G238 | H95: ='分表8-2025三类细分价'!H238 | I95: ='分表8-2025三类细分价'!I238 | J95: ='分表8-2025三类细分价'!J238 | K95: ='分表8-2025三类细分价'!K238 | ... O95: ='分表8-2025三类细分价'!O238 | P95: =IF(SUM(D95:O95)=0,"0",AVERAGEIF(D95:O95,"<>0",D95:O95))
A96: 94 | B96: 福建 | C96: 综合平段电价--电网代购 | D96: =IF(D93="/","/",SUM(D91:D95)) | E96: =IF(E93="/","/",SUM(E91:E95)) | F96: =IF(F93="/","/",SUM(F91:F95)) | G96: =IF(G93="/","/",SUM(G91:G95)) | H96: =IF(H93="/","/",SUM(H91:H95)) | I96: =IF(I93="/","/",SUM(I91:I95)) | J96: =IF(J93="/","/",SUM(J91:J95)) | K96: =IF(K93="/","/",SUM(K91:K95)) | ... O96: =IF(O93="/","/",SUM(O91:O95)) | P96: =IF(SUM(D96:O96)=0,"0",AVERAGEIF(D96:O96,"<>0",D96:O96))
A97: 95 | B97: 福建 | C97: 入市交易购电价格 | D97: ='分表9-2025交易价格'!D13 | E97: ='分表9-2025交易价格'!E13 | F97: ='分表9-2025交易价格'!F13 | G97: ='分表9-2025交易价格'!G13 | H97: ='分表9-2025交易价格'!H13 | I97: ='分表9-2025交易价格'!I13 | J97: ='分表9-2025交易价格'!J13 | K97: ='分表9-2025交易价格'!K13 | ... O97: ='分表9-2025交易价格'!O13 | P97: =IF(SUM(D97:O97)=0,"0",AVERAGEIF(D97:O97,"<>0",D97:O97))
A98: 96 | B98: 福建 | C98: 综合平段电价--入市交易 | D98: =IF(D93="/","/",IF(D97>0,D97+SUM(D92:D95),"/")) | E98: =IF(E93="/","/",IF(E97>0,E97+SUM(E92:E95),"/")) | F98: =IF(F93="/","/",IF(F97>0,F97+SUM(F92:F95),"/")) | G98: =IF(G93="/","/",IF(G97>0,G97+SUM(G92:G95),"/")) | H98: =IF(H93="/","/",IF(H97>0,H97+SUM(H92:H95),"/")) | I98: =IF(I93="/","/",IF(I97>0,I97+SUM(I92:I95),"/")) | J98: =IF(J93="/","/",IF(J97>0,J97+SUM(J92:J95),"/")) | K98: =IF(K93="/","/",IF(K97>0,K97+SUM(K92:K95),"/")) | ... O98: =IF(O93="/","/",IF(O97>0,O97+SUM(O92:O95),"/")) | P98: =IF(SUM(D98:O98)=0,"0",AVERAGEIF(D98:O98,"<>0",D98:O98))
A99: 97 | B99: 湖北 | C99: 代理购电价格 | D99: ='分表8-2025三类细分价'!D255 | E99: ='分表8-2025三类细分价'!E255 | F99: ='分表8-2025三类细分价'!F255 | G99: ='分表8-2025三类细分价'!G255 | H99: ='分表8-2025三类细分价'!H255 | I99: ='分表8-2025三类细分价'!I255 | J99: ='分表8-2025三类细分价'!J255 | K99: ='分表8-2025三类细分价'!K255 | ... O99: ='分表8-2025三类细分价'!O255 | P99: =IF(SUM(D99:O99)=0,"0",AVERAGEIF(D99:O99,"<>0",D99:O99))
A100: 98 | B100: 湖北 | C100: 上网环节线损电价 | D100: ='分表8-2025三类细分价'!D258 | E100: ='分表8-2025三类细分价'!E258 | F100: ='分表8-2025三类细分价'!F258 | G100: ='分表8-2025三类细分价'!G258 | H100: ='分表8-2025三类细分价'!H258 | I100: ='分表8-2025三类细分价'!I258 | J100: ='分表8-2025三类细分价'!J258 | K100: ='分表8-2025三类细分价'!K258 | ... O100: ='分表8-2025三类细分价'!O258 | P100: =IF(SUM(D100:O100)=0,"0",AVERAGEIF(D100:O100,"<>0",D100:O100))
...

Sheet 分表8-2025三类细分价
A1: 序号 | B1: 省份 | C1: 2025年代理购电价格表 | D1: 1月 | E1: 2月 | F1: 3月 | G1: 4月 | H1: 5月 | I1: 6月 | J1: 7月 | K1: 8月 | L1: 9月 | M1: 10月 | N1: 11月 | O1: 12月 | P1: 年均 | Q1: 趋势图
A2: 1 | B2: 北京 | C2: 代理工商业购电价格 | D2: =D3+D4 | E2: =E3+E4 | F2: =F3+F4 | G2: =G3+G4 | H2: =H3+H4 | I2: =I3+I4 | J2: =J3+J4 | K2: =K3+K4 | ... O2: =O3+O4 | P2: =IF(SUM(D2:O2)=0,"0",AVERAGEIF(D2:O2,"<>0",D2:O2))
A3: 2 | B3: 北京 | C3: （1）当月平均购电价格 | D3: 0.399691 | E3: 0.399137 | F3: 0.40102 | G3: 0.399278 | H3: 0.399299 | I3: 0.399984 | J3: 0.407267 | K3: 0.406582 | L3: 0.401998 | M3: 0.398963 | N3: 0.399529 | O3: 0.399999 | P3: =IF(SUM(D3:O3)=0,"0",AVERAGEIF(D3:O3,"<>0",D3:O3))
A4: 3 | B4: 北京 | C4: （2）历史偏差电费折价 | D4: -0.003747 | E4: -0.008913 | F4: -0.003355 | G4: 0.001327 | H4: -0.003028 | I4: -9.9e-05 | J4: -0.000869 | K4: -0.002018 | L4: -0.000873 | M4: -0.002559 | N4: -0.001875 | O4: -0.002755 | P4: =IF(SUM(D4:O4)=0,"0",AVERAGEIF(D4:O4,"<>0",D4:O4))
